Workbook

Sheet Instructions
A1: Worksheet definitions and DCE Instructions
A3: WORKBOOK TABS
A4: The "Tabs" listed below contain data used to develop the building estimates and in many cases are linked together. A description for each workbook (tab) is defined below:
A6: ADJUSTMENT (TAB) | B6: This will typically not change and is based on estimators experience, accuracy and availability of site information and previous experience.
A8: INPUT TAB: | B8: This tab allows the user to change parameters of the estimate. Any changes made will be reflected in various elements in the cost estimate.
A10: 1 | B10: Enter the year of the estimate.
A11: =A10+1 -> 2 | B11: Verify/change yearly escalation rates.
A12: =A11+1 -> 3 | B12: Verify/change waste density rate
A13: =A12+1 -> 4 | B13: Update exchange rate, US to AU.
A14: =A13+1 -> 5 | B14: Update ANSTO labor rates
A15: =A14+1 -> 6 | B15: Update ANSTO waste disposal rates.
A16: =A15+1 -> 7 | B16: Update equipment costs and quantities. Specify whether costs are US or AU dollars, cell D85. Specify cost year, cell E86.
A17: =A16+1 -> 8 | B17: Update consumable costs and quantities.
A18: =A17+1 -> 9 | B18: Review building specific data and modify as needed.
A19: =A18+1 -> 10 | B19: The base estimates are based on a crew size of 12. The crew size can modified for each building by changing the number of crews under the building specific inputs. A smaller building may a require a smaller crew size and vice versa. This will require estimators judgement.
A21: COMPARISON TAB: | B21: This tab is for "Information only". It compares the Cost Estimate prepared by CAA to the 2018 PT&C DCE.
A23: WBS SUMMARY TAB | B23: This tab contains the Work Breakdown Structure for each of the five areas into the 7 sections as requested by ANSTO.
A25: BUILDING TABS | B25: This is the build up of the building specific cost estimate. It includes the undistributed costs, such as staffing and equipment and material, and the activity costs. The activity costs are determined by the building square meters and the unit rates determined from previous estimates.
A26: 1 | B26: Review cells highlighted in green and adjust as necessary.
A27: 2 | B27: Insert building area
A28: 3 | B28: Insert project duration. This is not a calculated duration, it is estimator's judgement.
A29: 4 | B29: Insert length of asbestos pipe, if any.
A30: 5 | B30: Insert number of crews adjustment, see 10 above.
A32: SUMMARY 2026 $ TAB | B32: This is a breakdown of the averages obtained from CAA Cost estimating data from other estimates. It is updated into 2026 AUD. Protected worksheet and no action needed. This worksheet should not be altered or change in any way.
A34: HIDDEN TABS: | B34: There are a number of hidden tabs which have site specific data for other DCE prepared by the estimators. The data in these tabs are linked to the overall cost estimate. These are protected worksheets. These should not be altered or change in any way.
A37: HOW TO MAKE CHANGESS AND USE THE CAA WORKBOOK
B38: The five buildings in this workbook B17, 18, 54, 56, 70, and BXX (BXX is generic example for use and practice) are considered the “Master File”. The DCE for each of these buildings share the same data from the “adjustments” and “Input tab”. If you change any data in these tabs, it has the potential to impact one or more of the other buildings. For example hourly labor rates are defined in the input tab and are used to determine management cost for all five building in the master file. Changing hourly rate will change all five cost estimates. Listed below are methods you can use to prepare a DCE for a new structure or building.
A40: A. Adjust or change data in the "Master File" - B17, 18, 54, 56, & 70
B41: This approach will basically change the existing CAA DCE. ANSTO may chose to change generic global data such as labor rates. This will change the DC for each of the 5 building (6 if you include Building XX.)
A42: 1 | B42: Using the input tab as shown above, change parameters as needed. Again, it should be noted that changing data on the input tab in most cases will change the cost estimate for each of the five buildings originally estimated.
A43: 2 | B43: Change parameters on the "Building Tab" to reflect attributes of the structure as needed. Note: Changes in the building tab will only impact the ones applicable for the building selected and not the other structures.
A44: B. Prepare DCE for a 5 or 6 Structures at one time using the Master File as a template
B45: This approach is recommended and allows ANSTO to use the existing Master File building work sheets to update 5 (or six if using Building XX) DCEs at one time.
A46: 1 | B46: Select 5 (or 6) new structures for DCEs. Collect specific data for those structures..
A47: 2 | B47: Change the workbook building names in the Master File to reflect the structures you will be estimating and save it under a new unique file name. Do not change the CAA Master file since this will serve as a "template" future estimates.
A48: 3 | B48: Using the input tab (as shown above), change parameters as needed for each of the structure capturing unique attributes.. Again, it should be noted that changing data on the input tab in most cases will change the cost estimate for each of the structures being estimated.
A49: 4 | B49: Review and change parameters on the "Building Tab" as needed. Note: Changing data in a building tab will not impact other 4 or 5 building in the new master file.
A50: C. Using the Master File to add just one structure without impacting completed estimates of other structures.
B51: This approach should be used if you want to just update one structure as a stand alone DCE. The five buildings in this workbook B17, 18, 54, 56, & 70 are considered the “Master File”. The DCE for each of these buildings share the same data from the “adjustments” and “Input tab”. If you change any data in these tabs, it has the potential to impact one or more of the other buildings. For example hourly labor rates are defined in the input tab and are used to determine management cost for all five building in the master file. Changing hourly rate will change all five cost estimates. To prepare an independent DCE and not impact the master file, follow the steps below.
B52: How to add a new structure:
B53: 1. First determine which of the five buildings most closely resemble the building you want to Estimate.
B54: 2. Delete 4 of the five building tabs, keeping only the one that most closely resembles the one being estimated as shown below.
B62: 3. Rename the revised file and also rename the workbook tab to identify the structure (i.e. BXX) and save the file under a new name (i.e. BXX DCE). This allows you to prepare a building/structure without impacting the original master file.
B63: 4. Using the new file and spreadsheets you can change building specific data to most resemble the building being decommissioned.
B64: Note: This approach ensures you still have all of the links necessary to revise and change parameters specific to the new structure being estimated.

Sheet Adjustments
A1: Class of Structure | B1: Description | C1: Adjustment | D1: NOTE the adjustment factors, C2 - C4 should be adjusted based on estimator experience or experience gained from previously completed decommissioning projecs.
A2: B1 | B2: Lab/Rad | C2: 0.5
A3: C1 | B3: Industrial/Rad | C3: 0
A4: D1 | B4: Non-Indust/Rad | C4: -0.5
A5: D2 | B5: Non-Indust/Non-Rad | C5: -0.5
A6: NOTE: Class is extracted from the Project Time and Cost 2018 DCE
A8: Productivity Loss Factors | C8: Resp. | D8: Rad/ | F8: Protective
B9: Height | C9: Protection | D9: ALARA | F9: Clothing | H9: Breaks
B10: 0.15 | C10: 0.38 | D10: 0.15 | F10: 0.23 | H10: 0.0833
E11: Summary | G11: Summary
A12: All factors | B12: 0.15 | C12: 0.38 | D12: 0.15 | E12: =SUM(B12:D12) -> 0.68 | F12: 0.23 | G12: =(1+E12)*(1+F12) -> 2.0664 | H12: 0.0833 | I12: =G12*(1+H12) -> 2.2385311
A13: All except Height | C13: 0.38 | D13: 0.15 | E13: =SUM(B13:D13) -> 0.53 | F13: 0.23 | G13: =(1+E13)*(1+F13) -> 1.8819 | H13: 0.0833 | I13: =G13*(1+H13) -> 2.0386623
A14: PCs, Rad and Respirator only | C14: 0.38 | D14: 0.15 | E14: =SUM(B14:D14) -> 0.53 | F14: 0.23 | G14: =(1+E14)*(1+F14) -> 1.8819 | I14: =G14*(1+H14) -> 1.8819
A15: All except Resp. | B15: 0.15 | D15: 0.15 | E15: =SUM(B15:D15) -> 0.3 | F15: 0.23 | G15: =(1+E15)*(1+F15) -> 1.599 | H15: 0.0833 | I15: =G15*(1+H15) -> 1.7321967
A16: Height, PCs and Rad only | B16: 0.15 | D16: 0.15 | E16: =SUM(B16:D16) -> 0.3 | F16: 0.23 | G16: =(1+E16)*(1+F16) -> 1.599 | I16: =G16*(1+H16) -> 1.599
A17: PCs, Rad and Break only | D17: 0.15 | E17: =SUM(B17:D17) -> 0.15 | F17: 0.23 | G17: =(1+E17)*(1+F17) -> 1.4145 | H17: 0.0833 | I17: =G17*(1+H17) -> 1.5323278
A18: PCs and Rad only | D18: 0.15 | E18: =SUM(B18:D18) -> 0.15 | F18: 0.23 | G18: =(1+E18)*(1+F18) -> 1.4145 | I18: =G18*(1+H18) -> 1.4145
A19: Height and Breaks only | B19: 0.15 | E19: =SUM(B19:D19) -> 0.15 | G19: =(1+E19)*(1+F19) -> 1.15 | H19: 0.0833 | I19: =G19*(1+H19) -> 1.245795
A20: Height only | B20: 0.15 | E20: =SUM(B20:D20) -> 0.15 | G20: =(1+E20)*(1+F20) -> 1.15 | H20: 0 | I20: =G20*(1+H20) -> 1.15
A21: Breaks only | E21: =SUM(B21:D21) -> 0 | G21: =(1+E21)*(1+F21) -> 1 | H21: 0.0833 | I21: =G21*(1+H21) -> 1.0833
A23: NOTE: Source: AIF/NESP-036
A24: 1. The adjustment factors applies are the estimators judgement for a class 4 estimate. If this were a bottoms up estimate the below productivity loss factors would be applied on a line item basis.
A26: 2. The base estimate used to develop the ANSTO estimates are considered to be for facilities designated as C1. A designation of B1 would require an increase in costs, in this case a 50% increase. This increase falls within the adjustments identified in the PLF table.
A28: 3. Since the base estimates are considered for C1 buildings, D1 and D2 facilities would require less effort. Estimators judgement was used to arrive at these adjustment factors.

Sheet Inputs
A1: Items highlighted in green can be adjusted as needed.
A2: Year of Estimate: | B2: 2026 | C2: =LOOKUP(B$2,A6:A34,C6:C34) -> 1.6081076
B3: From | C3: =A6 -> 2008 | D3: =C3+1 -> 2009 | E3: =D3+1 -> 2010 | F3: =E3+1 -> 2011 | G3: =F3+1 -> 2012 | H3: =G3+1 -> 2013 | I3: =H3+1 -> 2014 | J3: =I3+1 -> 2015 | K3: =J3+1 -> 2016 | ... AD3: =AC3+1 -> 2035
A4: Escalation | B4: To | C4: =$B2 -> 2026 | D4: =$B2 -> 2026 | E4: =$B2 -> 2026 | F4: =$B2 -> 2026 | G4: =$B2 -> 2026 | H4: =$B2 -> 2026 | I4: =$B2 -> 2026 | J4: =$B2 -> 2026 | ... AD4: =$B2 -> 2026
C5: =IF($D6>0,$D6,"na") -> 0.60810763 | D5: =IF($D7>0,$D7,"na") -> 0.58013917 | E5: =IF($D8>0,$D8,"na") -> 0.53530817 | F5: =IF($D9>0,$D9,"na") -> 0.48626154 | G5: =IF($D10>0,$D10,"na") -> 0.46055576 | H5: =IF($D11>0,$D11,"na") -> 0.42562788 | I5: =IF($D12>0,$D12,"na") -> 0.39099217 | J5: =IF($D13>0,$D13,"na") -> 0.37030063 | K5: =IF($D14>0,$D14,"na") -> 0.35298246 | L5: =IF($D15>0,$D15,"na") -> 0.32710393 | M5: =IF($D16>0,$D16,"na") -> 0.30223131 | N5: =IF($D17>0,$D17,"na") -> 0.28159759 | O5: =IF($D18>0,$D18,"na") -> 0.27079583 | P5: =IF($D19>0,$D19,"na") -> 0.23546162 | Q5: =IF($D20>0,$D20,"na") -> 0.15907836 | R5: =IF($D21>0,$D21,"na") -> 0.097612084 | S5: =IF($D22>0,$D22,"na") -> 0.06399 | T5: =IF($D23>0,$D23,"na") -> 0.03 | U5: =IF($D24>0,$D24,"na") -> na | V5: =IF($D25>0,$D25,"na") -> na | W5: =IF($D26>0,$D26,"na") -> na | X5: =IF($D27>0,$D27,"na") -> na | Y5: =IF($D28>0,$D28,"na") -> na | Z5: =IF($D29>0,$D29,"na") -> na | AA5: =IF($D30>0,$D30,"na") -> na | AB5: =IF($D31>0,$D31,"na") -> na | AC5: =IF($D32>0,$D32,"na") -> na | AD5: =IF($D33>0,$D33,"na") -> na
A6: 2008 | B6: 1 | C6: =B6 -> 1 | D6: =(C$2-C6)/C6 -> 0.60810763
A7: =A6+1 -> 2009 | B7: 0.0177 | C7: =B6*(1+B7) -> 1.0177 | D7: =(C$2-C7)/C7 -> 0.58013917
A8: =A7+1 -> 2010 | B8: 0.0292 | C8: =C7*(1+B8) -> 1.0474168 | D8: =(C$2-C8)/C8 -> 0.53530817
A9: =A8+1 -> 2011 | B9: 0.033 | C9: =C8*(1+B9) -> 1.0819816 | D9: =(C$2-C9)/C9 -> 0.48626154
A10: =A9+1 -> 2012 | B10: 0.0176 | C10: =C9*(1+B10) -> 1.1010245 | D10: =(C$2-C10)/C10 -> 0.46055576
A11: =A10+1 -> 2013 | B11: 0.0245 | C11: =C10*(1+B11) -> 1.1279996 | D11: =(C$2-C11)/C11 -> 0.42562788
A12: =A11+1 -> 2014 | B12: 0.0249 | C12: =C11*(1+B12) -> 1.1560868 | D12: =(C$2-C12)/C12 -> 0.39099217
A13: =A12+1 -> 2015 | B13: 0.0151 | C13: =C12*(1+B13) -> 1.1735437 | D13: =(C$2-C13)/C13 -> 0.37030063
A14: =A13+1 -> 2016 | B14: 0.0128 | C14: =C13*(1+B14) -> 1.188565 | D14: =(C$2-C14)/C14 -> 0.35298246
A15: =A14+1 -> 2017 | B15: 0.0195 | C15: =C14*(1+B15) -> 1.211742 | D15: =(C$2-C15)/C15 -> 0.32710393
A16: =A15+1 -> 2018 | B16: 0.0191 | C16: =C15*(1+B16) -> 1.2348863 | D16: =(C$2-C16)/C16 -> 0.30223131
A17: =A16+1 -> 2019 | B17: 0.0161 | C17: =C16*(1+B17) -> 1.254768 | D17: =(C$2-C17)/C17 -> 0.28159759
A18: =A17+1 -> 2020 | B18: 0.0085 | C18: =C17*(1+B18) -> 1.2654335 | D18: =(C$2-C18)/C18 -> 0.27079583
A19: =A18+1 -> 2021 | B19: 0.0286 | C19: =C18*(1+B19) -> 1.3016249 | D19: =(C$2-C19)/C19 -> 0.23546162
... A24: =A23+1 -> 2026 | B24: 0.03 | C24: =C23*(1+B24) -> 1.6081076 | D24: =(C$2-C24)/C24 -> 0
A25: =A24+1 -> 2027 | B25: =AVERAGE(B$7:B$24) -> 0.026838889 | C25: =C24*(1+B25) -> 1.6512675 | D25: =(C$2-C25)/C25 -> -0.02613739
A26: =A25+1 -> 2028 | B26: =AVERAGE(B$7:B$24) -> 0.026838889 | C26: =C25*(1+B26) -> 1.6955856 | D26: =(C$2-C26)/C26 -> -0.051591618
A27: =A26+1 -> 2029 | B27: =AVERAGE(B$7:B$24) -> 0.026838889 | C27: =C26*(1+B27) -> 1.7410933 | D27: =(C$2-C27)/C27 -> -0.076380538
A28: =A27+1 -> 2030 | B28: =AVERAGE(B$7:B$24) -> 0.026838889 | C28: =C27*(1+B28) -> 1.7878223 | D28: =(C$2-C28)/C28 -> -0.10052154
A29: =A28+1 -> 2031 | B29: =AVERAGE(B$7:B$24) -> 0.026838889 | C29: =C28*(1+B29) -> 1.8358054 | D29: =(C$2-C29)/C29 -> -0.12403156
A30: =A29+1 -> 2032 | B30: =AVERAGE(B$7:B$24) -> 0.026838889 | C30: =C29*(1+B30) -> 1.8850764 | D30: =(C$2-C30)/C30 -> -0.14692709
A31: =A30+1 -> 2033 | B31: =AVERAGE(B$7:B$24) -> 0.026838889 | C31: =C30*(1+B31) -> 1.9356698 | D31: =(C$2-C31)/C31 -> -0.16922419
A32: =A31+1 -> 2034 | B32: =AVERAGE(B$7:B$24) -> 0.026838889 | C32: =C31*(1+B32) -> 1.987621 | D32: =(C$2-C32)/C32 -> -0.1909385
A33: =A32+1 -> 2035 | B33: =AVERAGE(B$7:B$24) -> 0.026838889 | C33: =C32*(1+B33) -> 2.0409665 | D33: =(C$2-C33)/C33 -> -0.21208526
A34: =A33+1 -> 2036 | B34: =AVERAGE(B$7:B$24) -> 0.026838889 | C34: =C33*(1+B34) -> 2.0957438 | D34: =(C$2-C34)/C34 -> -0.23267929
A36: Waste Density | B36: 100 | C36: lbs/cuft
A37: Exchange rate | B37: 45946.508 | C37: 1.54
B39: Rates | D39: Actuals | E39: Actuals | F39: +4.8% (3.4% EBA +1.4% Band Level) | G39: +4.8% (3.4% EBA +1.4% Band Level)
A40: ANSTO LABOR RATES | D40: Jul-Apr26 | E40: May-Jun26. +3.4%
B41: CLASS | C41: Band | D41: FY26 | F41: FY27 (Forecast) | G41: FY28
G42: (Forecast)
A43: Resource Type | B43: (SAP Name) | C43: (EA name) | D43: $/hour | E43: $/hour | F43: $/hour | G43: $/hour
B44: CLASS1 | C44: Band 1 | D44: 45.99 | E44: 47.55 | F44: 48.2 | G44: 50.51
B45: CLASS2 | C45: Band 2 | D45: 52.44 | E45: 54.22 | F45: 54.96 | G45: 57.6
B46: CLASS3 | C46: Band 3 | D46: 63.63 | E46: 65.79 | F46: 66.68 | G46: 69.88
B47: CLASS4 | C47: Band 4 | D47: 74.65 | E47: 77.19 | F47: 78.23 | G47: 81.99
A48: Decom Technician / Safety SME | B48: CLASS5 | C48: Band 5 | D48: 86.32 | E48: 89.25 | F48: 90.46 | G48: 94.8
A49: Project Manager / Waste Management | B49: CLASS6 | C49: Band 6 | D49: 104.63 | E49: 108.19 | F49: 109.65 | G49: 114.91
A50: Senior Project Manager / Characterization SME | B50: CLASS7 | C50: Band 7 | D50: 123.09 | E50: 127.28 | F50: 129 | G50: 135.19
A51: Portfolio Manager | B51: CLASS8 | C51: Band 8 | D51: 152.68 | E51: 157.87 | F51: 160.01 | G51: 167.69
B52: CLASS9 | C52: Band 9 | D52: 186.99 | E52: 193.35 | F52: 193.35 | G52: 199.92
B53: CLAS10 | C53: Band 10 | D53: 240.73 | E53: 248.91 | F53: 248.91 | G53: 257.37
A77: Waste Disposal rates
B79: 300 | C79: Industrial Wastes
B80: 500 | C80: Hazardous Waste
B81: 90 | C81: /hr | D81: Contaminated Waste Cleaning
B83: 0 | C83: Low Level Solid Waste (Stored)
B84: 0 | C84: Intermediate Level Solid waste
D85: US | E85: dollars
C86: B1 | D86: Rate Year | E86: 2009 | F86: =LOOKUP(E86,Inputs!C3:AD3,Inputs!C5:AD5) -> 0.58013917 | G86: C1 | J86: D1 | M86: D2
A87: Equipment | C87: Quantity | D87: Rate | E87: Equipment | G87: Quantity | H87: Equipment | J87: Quantity | K87: Equipment | M87: Quantity
A88: HEPA filter systems | C88: 2 | D88: 3598.14 | E88: HEPA filter systems | G88: 2 | H88: HEPA filter systems | J88: 2 | K88: HEPA filter systems | M88: 0
A89: Replacement filters | C89: 24 | D89: 581.07 | E89: Replacement filters | G89: 24 | H89: Replacement filters | J89: 24 | K89: Replacement filters | M89: 0
A90: Respirator | C90: 12 | D90: 259 | E90: Respirator | G90: 12 | H90: Respirator | J90: 12 | K90: Respirator | M90: 0
A91: Rad/Vac wet-dry high eff. vacuum | C91: 1 | D91: 3879 | E91: Rad/Vac wet-dry high eff. vacuum | G91: 2 | H91: Rad/Vac wet-dry high eff. vacuum | J91: 1 | K91: Rad/Vac wet-dry high eff. vacuum | M91: 0
A92: Rad/Vac wet-dry high eff. vacuum filters | C92: 5 | D92: 412 | E92: Rad/Vac wet-dry high eff. vacuum filters | G92: 5 | H92: Rad/Vac wet-dry high eff. vacuum filters | J92: 5 | K92: Rad/Vac wet-dry high eff. vacuum filters | M92: 0
A93: Reciprocating Saws | C93: 5 | D93: 1252.26 | E93: Reciprocating Saws | G93: 5 | H93: Reciprocating Saws | J93: 5 | K93: Reciprocating Saws | M93: 0
A94: Pneumatic chipping hammers | C94: 2 | D94: 1606.71 | E94: Pneumatic chipping hammers | G94: 2 | H94: Pneumatic chipping hammers | J94: 2 | K94: Pneumatic chipping hammers | M94: 2
A95: Chipping hammer blades | C95: 20 | D95: 27.42 | E95: Chipping hammer blades | G95: 20 | H95: Chipping hammer blades | J95: 20 | K95: Chipping hammer blades | M95: 20
A96: Purchase an air compressor: | C96: 2 | D96: 1723.44 | E96: Purchase an air compressor: | G96: 2 | H96: Purchase an air compressor: | J96: 2 | K96: Purchase an air compressor: | M96: 2
A97: Jackhammer | C97: 4 | D97: 1417.11 | E97: Jackhammer | G97: 4 | H97: Jackhammer | J97: 4 | K97: Jackhammer | M97: 4
A98: Jackhammer Chisels | C98: 10 | D98: 24.35 | E98: Jackhammer Chisels | G98: 10 | H98: Jackhammer Chisels | J98: 10 | K98: Jackhammer Chisels | M98: 10
A99: Safety glasses | C99: 15 | D99: 8.6 | E99: Safety glasses | G99: 15 | H99: Safety glasses | J99: 15 | K99: Safety glasses | M99: 15
... A105: Phone and computer hook-up | C105: 1 | D105: 250 | E105: Phone and computer hook-up | G105: 1 | H105: Phone and computer hook-up | J105: 1 | K105: Phone and computer hook-up | M105: 1
A106: Instrumentation | C106: 0 | E106: Instrumentation | G106: 0 | H106: Instrumentation | J106: 0 | K106: Instrumentation | M106: 0
A107: Tractor loader, wheeled | C107: 1 | D107: 7160.5905 | E107: Tractor loader, wheeled | G107: 1 | H107: Tractor loader, wheeled | J107: 1 | K107: Tractor loader, wheeled | M107: 1
A108: Wheeled Skid steer with conc. Hammer | C108: 1 | D108: 4421.3693 | E108: Wheeled Skid steer with conc. Hammer | G108: 1 | H108: Wheeled Skid steer with conc. Hammer | J108: 1 | K108: Wheeled Skid steer with conc. Hammer | M108: 1
A109: Excavator | C109: 1 | D109: 28738.389 | E109: Excavator | G109: 1 | H109: Excavator | J109: 1 | K109: Excavator | M109: 1
A110: Floor Shaver | C110: 1 | D110: 8000 | E110: Floor Shaver | G110: 1 | H110: Floor Shaver | J110: 1 | K110: Floor Shaver | M110: 0
A111: Wall Shaver | C111: 1 | D111: 15000 | E111: Wall Shaver | G111: 1 | H111: Wall Shaver | J111: 1 | K111: Wall Shaver | M111: 0
A112: Man lift | C112: 2 | D112: 4727.44 | E112: Man lift | G112: 2 | H112: Man lift | J112: 2 | K112: Man lift | M112: 0
A113: Crane rental for building removal | C113: 1 | D113: 15600 | E113: Crane rental for building removal | G113: 1 | H113: Crane rental for building removal | J113: 1 | K113: Crane rental for building removal | M113: 0
C115: B1 | D115: C1 | E115: D1 | F115: D2 | H115: US | I115: dollars
A116: Consumables | C116: Quantity | D116: Quantity | E116: Quantity | F116: Quantity | H116: Unit Cost
A117: Coveralls | C117: 2 | D117: 2 | E117: 2 | F117: 0 | G117: /man/day | H117: 11
A118: Hoods | C118: 0.1 | D118: 0.1 | E118: 0.1 | F118: 0 | G118: /man/day | H118: 0
A119: Shoe covers | C119: 4 | D119: 4 | E119: 4 | F119: 0 | G119: /man/day | H119: 0.94
A120: Latex gloves | C120: 4 | D120: 4 | E120: 4 | F120: 0 | G120: /man/day | H120: 0.94
A121: Rubber overshoes | C121: 0.01 | D121: 0.01 | E121: 0.01 | F121: 0 | G121: /man/day | H121: 3
A122: Gloves | C122: 0.01 | D122: 0.01 | E122: 0.01 | F122: 0 | G122: /man/day | H122: 2
A123: Dosimeters | C123: 1 | D123: 1 | E123: 1 | F123: 0 | G123: /man/year | H123: 200
A124: TLDs | C124: 1 | D124: 1 | E124: 1 | F124: 0 | G124: /man/mo | H124: 3
A125: Bioassays | C125: 2 | D125: 2 | E125: 2 | F125: 0 | G125: /man/year | H125: 250
A126: (Bioassays for aver. crew & management)
A128: Small Tools - 2% of total labor costs = | F128: 0.02
A130: HP Equipment Replacement - 5% of total labor | F130: 0.05
A132: DGC OH &P on equipment and materials | F132: 0.08
A134: 1 cubic foot = | B134: 0.02832 | C134: cubic meter | D134: 1 square foot = | E134: 0.0929 | F134: square meter | G134: 1 foot = | H134: 0.3048 | I134: meters
A135: 1cubic foot/square foot = | C135: =B134/E134 -> 0.30484392 | D135: cubic meter/square meter | K135: B17
A136: 1cubic foot/foot = | B136: =B134/H134 -> 0.092913386 | C136: cubic meter/meter
A137: Building Information for B17, B18, 54, 56 & 70
A139: Building B17 | B139: 17A | C139: D1 | D139: Non-Indust/Rad | E139: 17B = | F139: C1 | G139: Industrial/Rad
A140: Number of floors | B140: 2 | F140: 17A | G140: 17B
A142: Floor Area | B142: 100 | C142: sqft | F142: 704 | G142: 158
A144: Project Duration | B144: 180 | C144: days | G144: =G142 -> 158
...

Sheet Comparison
A1: COMPARISON OF ESTIMATES BETWEEN 2018 PT&C ESITMATE AND CAA ESTIMATE
A2: Facility Name/Description | B2: Gross Area (SM) | C2: Facility Class Adj | D2: Total Cost (FY18 AU$) | E2: Unit Cost (AU$/SM) | F2: Total Cost (FY26 AU$) | G2: Unit Cost (AU$/SM) | H2: CAA Estimate, 2026AU$ | I2: Delta
A3: B17A - Nuclear Services (Material Storage) | B3: =Inputs!G142 -> 158 | C3: =Inputs!C139 -> D1 | I3: Variance from PT&C and CAA
A4: B17B - Nuclear Operations (Workshop) | B4: =Inputs!F142 -> 704 | C4: =Inputs!F139 -> C1 | I4: Delta | J4: % | K4: Item
A5: B17 | B5: =SUM(B3:B4) -> 862 | D5: 1931756.7 | E5: =D5/B5 -> 2241.017 | F5: =(1+Inputs!$M$5)*Comparison!D5 -> 2515594.1 | G5: =F5/B5 -> 2918.3226 | H5: ='WBS Summary'!M27 -> 2665719.5 | I5: =H5-F5 -> 150125.43 | J5: =I5/F5 -> 0.059677925 | K5: B17
A6: B18 | C6: =Inputs!B150 -> D2 | D6: 3579999.2 | F6: =(1+Inputs!$M$5)*Comparison!D6 -> 4661987.1 | H6: ='WBS Summary'!M51 -> 5140902.6 | I6: =H6-F6 -> 478915.52 | J6: =I6/F6 -> 0.10272777 | K6: B18
A7: B54 | C7: =Inputs!B169 -> B1 | D7: 12388722 | F7: =(1+Inputs!$M$5)*Comparison!D7 -> 16132982 | H7: ='WBS Summary'!M78 -> 14159309 | I7: =H7-F7 -> -1973672.5 | J7: =I7/F7 -> -0.12233774 | K7: B54
A8: B56 | C8: =Inputs!B206 -> B1 | D8: 13866487 | F8: =(1+Inputs!$M$5)*Comparison!D8 -> 18057374 | H8: ='WBS Summary'!M104 -> 14150956 | I8: =H8-F8 -> -3906418 | J8: =I8/F8 -> -0.21633367 | K8: B56
A9: B70 | C9: =Inputs!B248 -> D2 | D9: 487422.3 | F9: =(1+Inputs!$M$5)*Comparison!D9 -> 634736.58 | H9: ='WBS Summary'!M133 -> 765186.91 | I9: =H9-F9 -> 130450.33 | J9: =I9/F9 -> 0.20551885 | K9: B70

Sheet WBS Summary
A2: ESTIMATED COSTS BY WORK BREAKDOWN STRUCTURE - B17, 18, 54 ,56 & 70
A4: WBS | B4: Description | C4: LSA Waste (M3) | D4: Hazardous Waste Vol (M3) | E4: Mixed Waste Vol (M3) | F4: Clean Waste Vol. (M3) | G4: Mat's, Consumables & Equip. | H4: Labor Cost | I4: LSA Waste Cost (TBD) | J4: Hazardous Waste Cost | K4: Mixed Waste Cost | L4: Clean Waste Cost | M4: Total Cost
A5: 1.0 | B5: Building B17
A6: 1.1 | B6: Project Management
A7: 1.1.1 | B7: Staff | H7: ='Building B17'!I14 -> 268756.2 | M7: =SUM(G7:L7) -> 268756.2
A8: 1.1.2 | B8: Equipment, Materials & Consumables | G8: ='Building B17'!S7 -> 649056.62 | M8: =SUM(G8:L8) -> 649056.62
A9: 1.2 | B9: Project Planning
A10: 1.2.1 | B10: Procedure Development | H10: ='Building B17'!T67 -> 22935.2 | M10: =SUM(G10:L10) -> 22935.2
A11: 1.2.2 | B11: QA and Safety Documents | H11: ='Building B17'!T74 -> 22935.2 | M11: =SUM(G11:L11) -> 22935.2
A12: 1.2.3 | B12: Mobilization | H12: ='Building B17'!T81 -> 123378.7 | M12: =SUM(G12:L12) -> 123378.7
A13: 1.3 | B13: Preliminary Site Investigation | M13: =SUM(G13:L13) -> 0
A14: 1.3.1 | B14: Decontamination Readiness Review | H14: See Note | M14: =SUM(G14:L14) -> 0
A15: 1.3.2 | B15: Site Prep | H15: ='Building B17'!T121 -> 45402.544 | M15: =SUM(G15:L15) -> 45402.544
A16: 1.4 | B16: Detailed Characterization | H16: ='Building B17'!T176 -> 74430.4 | M16: =SUM(G16:L16) -> 74430.4
A17: 1.5 | B17: Decontamination
A18: 1.5.1 | B18: Asbestos Removal | H18: 0 | M18: =SUM(G18:L18) -> 0
A19: 1.5.2 | B19: Remove systems and Components | H19: ='Building B17'!I196 -> 365585.28 | M19: =SUM(G19:L19) -> 365585.28
A20: 1.5.3 | B20: Decontaminate Structure | C20: =IF('Building B17'!N184>0,'Building B17'!N184, " ") -> 15.960162 | D20: =IF('Building B17'!O184>0,'Building B17'!O184, " ") -> 0.24497299 | E20: =IF('Building B17'!Q184>0,'Building B17'!Q184, " ") -> 2.0286826 | F20: =IF('Building B17'!R184>0,'Building B17'!R184, " ") -> 155.49774 | H20: ='Building B17'!I200 -> 156964.76 | M20: =SUM(G20:L20) -> 156964.76
A21: 1.5.4 | B21: Final Survey | H21: ='Building B17'!I202 -> 170610.12 | M21: =SUM(G21:L21) -> 170610.12
A22: 1.6 | B22: Site Remediation | F22: =IF('Building B17'!R204>0,'Building B17'!R204, " ") -> 542.69535
A23: 1.6.1 | B23: Remove Building | H23: ='Building B17'!I205 -> 320487.65 | M23: =SUM(G23:L23) -> 320487.65
A24: 1.6.2 | B24: Grade and Seed | H24: ='Building B17'!I206 -> 22280.855 | M24: =SUM(G24:L24) -> 22280.855
A25: 1.6.3 | B25: Backfill | H25: ='Building B17'!I207 -> 51041.169 | M25: =SUM(G25:L25) -> 51041.169
A26: 1.7 | B26: Waste Disposal | J26: =IF('Building B17'!V210>0,'Building B17'!V210, " ") -> 2007.338 | L26: =IF('Building B17'!Y210>0,'Building B17'!Y210, " ") -> 369847.45 | M26: =SUM(G26:L26) -> 371854.79
B27: TOTAL | C27: =IF('Building B17'!N5>0,'Building B17'!N5, " ") -> 15.960162 | D27: =IF('Building B17'!O5>0,'Building B17'!O5, " ") -> 0.24497299 | E27: =IF('Building B17'!Q5>0,'Building B17'!Q5, " ") -> 2.0286826 | F27: =IF('Building B17'!R5>0,'Building B17'!R5, " ") -> 698.19309 | G27: =SUM(G6:G26) -> 649056.62 | H27: =SUM(H6:H26) -> 1644808.1 | I27: =SUM(I6:I26) -> 0 | J27: =SUM(J6:J26) -> 2007.338 | K27: =SUM(K6:K26) -> 0 | L27: =SUM(L6:L26) -> 369847.45 | M27: =SUM(M6:M26) -> 2665719.5
B28: NOTE: Cost included in overall staff costs
A30: WBS | B30: Description | C30: LSA Waste (M3) | D30: Hazardous Waste Vol (M3) | E30: Mixed Waste Vol (M3) | F30: Clean Waste Vol. (M3) | G30: Mat's, Consumables & Equip. | H30: Labor Cost | I30: LSA Waste Cost (TBD) | J30: Hazardous Waste Cost | K30: Mixed Waste Cost | L30: Clean Waste Cost | M30: Total Cost
A31: 1.0 | B31: Building B18
A32: 1.1 | B32: Project Management
A33: 1.1.1 | B33: Staff | H33: ='Building B18'!T8 -> 134378.1 | M33: =SUM(G33:L33) -> 134378.1
A34: 1.1.2 | B34: Equipment, Material & Consumables | G34: ='Building B18'!S8 -> 461768.17 | M34: =SUM(G34:L34) -> 461768.17
A35: 1.2 | B35: Project Planning
A36: 1.2.1 | B36: Procedure Development | H36: ='Building B18'!T68 -> 22935.2 | M36: =SUM(G36:L36) -> 22935.2
A37: 1.2.2 | B37: QA and Safety Documents | H37: ='Building B18'!T75 -> 22935.2 | M37: =SUM(G37:L37) -> 22935.2
A38: 1.2.3 | B38: Mobilization | H38: ='Building B18'!T82 -> 123378.7 | M38: =SUM(G38:L38) -> 123378.7
A39: 1.3 | B39: Preliminary Site Investigation | M39: =SUM(G39:L39) -> 0
A40: 1.3.1 | B40: Decontamination Readiness Review | H40: See Note 1 | M40: =SUM(G40:L40) -> 0
A41: 1.3.2 | B41: Site Prep | H41: ='Building B18'!T118 -> 44658.24 | M41: =SUM(G41:L41) -> 44658.24
A42: 1.4 | B42: Detailed Characterization | H42: ='Building B18'!T177 -> 297721.6 | M42: =SUM(G42:L42) -> 297721.6
A43: 1.5 | B43: Decontamination
A44: 1.5.1 | B44: Remove Soil and Asphalt | C44: =IF('Building B18'!N185>0,'Building B18'!N185, " ") -> 3450 | D44: =IF('Building B17'!O2010>0,'Building B17'!O2010, " ") | E44: =IF('Building B17'!Q2010>0,'Building B17'!Q2010, " ") | F44: =IF('Building B18'!R185>0,'Building B18'!R185, " ") -> 3450 | H44: ='Building B18'!I197 -> 260100.75 | M44: =SUM(G44:L44) -> 260100.75
A45: 1.5.2 | B45: Final Survey | H45: ='Building B18'!I203 -> 1672173.1 | M45: =SUM(G45:L45) -> 1672173.1
A46: 1.6 | B46: Site Remediation | F46: =IF('Building B17'!R230>0,'Building B17'!R230, " ")
A47: 1.6.1 | B47: Remove Building | H47: See Note 2 | M47: =SUM(G47:L47) -> 0
A48: 1.6.2 | B48: Grade and Seed | H48: ='Building B18'!I207 -> 109188.85 | M48: =SUM(G48:L48) -> 109188.85
A49: 1.6.3 | B49: Backfill | H49: ='Building B18'!I208 -> 164127.77 | M49: =SUM(G49:L49) -> 164127.77
A50: 1.7 | B50: Waste Disposal | J50: =IF('Building B17'!V236>0,'Building B17'!V236, " ") | L50: =IF('Building B18'!Y211>0,'Building B18'!Y211, " ") -> 1827537 | M50: =SUM(G50:L50) -> 1827537
B51: TOTAL | C51: =SUM(C32:C50) -> 3450 | D51: =SUM(D32:D50) -> 0 | E51: =SUM(E32:E50) -> 0 | F51: =SUM(F32:F50) -> 3450 | G51: =SUM(G32:G50) -> 461768.17 | H51: =SUM(H32:H50) -> 2851597.5 | I51: =SUM(I32:I50) -> 0 | J51: =SUM(J32:J50) -> 0 | ... M51: =SUM(M32:M50) -> 5140902.6
B52: NOTE: Cost included in overall staff costs
A53: =IF('Building B18'!A213>0,'Building B18'!A213, " ") | B53: =IF('Building B18'!B213>0,'Building B18'!B213, " ") | C53: =IF('Building B18'!N213>0,'Building B18'!N213, " ") | D53: =IF('Building B18'!O213>0,'Building B18'!O213, " ") | E53: =IF('Building B18'!Q213>0,'Building B18'!Q213, " ") | F53: =IF('Building B18'!R213>0,'Building B18'!R213, " ") | G53: =IF('Building B18'!S213>0,'Building B18'!S213, " ") | H53: =IF('Building B18'!T213>0,'Building B18'!T213, " ") | I53: =IF('Building B18'!U213>0,'Building B18'!U213, " ") | J53: =IF('Building B18'!V213>0,'Building B18'!V213, " ") | K53: =IF('Building B18'!X213>0,'Building B18'!X213, " ") | L53: =IF('Building B18'!Y213>0,'Building B18'!Y213, " ") | M53: =IF('Building B18'!Z213>0,'Building B18'!Z213, " ")
A54: WBS | B54: Description | C54: LSA Waste (M3) | D54: Hazardous Waste Vol (M3) | E54: Mixed Waste Vol (M3) | F54: Clean Waste Vol. (M3) | G54: Mat's, Consumables & Equip. | H54: Labor Cost | I54: LSA Waste Cost (TBD) | J54: Hazardous Waste Cost | K54: Mixed Waste Cost | L54: Clean Waste Cost | M54: Total Cost
A55: 1.0 | B55: Building B54
A56: 1.1 | B56: Project Management
A57: 1.1.1 | B57: Staff | H57: ='Building B54'!T8 -> 614958.12 | M57: =SUM(G57:L57) -> 614958.12
A58: 1.1.2 | B58: Equipment, Material & Consumables | G58: ='Building B54'!S6 -> 1975720.3 | M58: =SUM(G58:L58) -> 1975720.3
A59: 1.2 | B59: Project Planning
A60: 1.2.1 | B60: Procedure Development | H60: ='Building B54'!T68 -> 22935.2 | M60: =SUM(G60:L60) -> 22935.2
A61: 1.2.2 | B61: QA and Safety Documents | H61: ='Building B54'!T75 -> 22935.2 | M61: =SUM(G61:L61) -> 22935.2
A62: 1.2.3 | B62: Mobilization | H62: ='Building B54'!T82 -> 225123.7 | M62: =SUM(G62:L62) -> 225123.7
A63: 1.3 | B63: Preliminary Site Investigation | M63: =SUM(G63:L63) -> 0
A64: 1.3.1 | B64: Decontamination Readiness Review | H64: See Note | M64: =SUM(G64:L64) -> 0
A65: 1.3.2 | B65: Site Prep | H65: ='Building B54'!T118 -> 44658.24 | M65: =SUM(G65:L65) -> 44658.24
A66: 1.4 | B66: Detailed Characterization | H66: ='Building B54'!T177 -> 446582.4 | M66: =SUM(G66:L66) -> 446582.4
A67: 1.5 | B67: Decontamination | C67: ='Building B54'!N185 -> 30.356693 | D67: ='Building B54'!O185 -> 328.66293 | E67: ='Building B54'!Q185 -> 3.4695083 | F67: ='Building B54'!R185 -> 265.93648
A68: 1.5.1 | B68: Asbestos Removal | H68: ='Building B54'!I189 -> 880073.36 | M68: =SUM(G68:L68) -> 880073.36
A69: 1.5.2 | B69: Remove systems and Components | H69: ='Building B54'!I197 -> 3751403.5 | M69: =SUM(G69:L69) -> 3751403.5
A70: 1.5.3 | B70: Decontaminate Structure | C70: =IF('Building B17'!N246>0,'Building B17'!N246, " ") | D70: =IF('Building B17'!O246>0,'Building B17'!O246, " ") | E70: =IF('Building B17'!Q246>0,'Building B17'!Q246, " ") | F70: =IF('Building B17'!R246>0,'Building B17'!R246, " ") | H70: ='Building B54'!I203 -> 2123535.8 | M70: =SUM(G70:L70) -> 2123535.8
A71: 1.5.4 | B71: Final Survey | H71: ='Building B54'!I205 -> 583564.16 | M71: =SUM(G71:L71) -> 583564.16
A72: 1.6 | B72: Site Remediation | F72: ='Building B54'!R207 -> 1075.2731
A73: 1.6.1 | B73: Remove Building | H73: ='Building B54'!I208 -> 1644320.2 | M73: =SUM(G73:L73) -> 1644320.2
A74: 1.6.2 | B74: Remove Hot Cell | H74: ='Building B54'!I209 -> 544168.89 | M74: =SUM(G74:L74) -> 544168.89
A75: 1.6.3 | B75: Grade and Seed | H75: ='Building B54'!I210 -> 76210.652 | M75: =SUM(G75:L75) -> 76210.652
A76: 1.6.4 | B76: Backfill | H76: ='Building B54'!I211 -> 174584 | M76: =SUM(G76:L76) -> 174584
A77: 1.7 | B77: Waste Disposal | J77: ='Building B54'!V214 -> 290166.02 | K77: ='Building B54'!X214 -> 27902.761 | L77: ='Building B54'!Y214 -> 710466.68 | M77: =SUM(G77:L77) -> 1028535.5
B78: TOTAL | C78: =SUM(C56:C77) -> 30.356693 | D78: =SUM(D56:D77) -> 328.66293 | E78: =SUM(E56:E77) -> 3.4695083 | F78: =SUM(F56:F77) -> 1341.2095 | G78: =SUM(G56:G77) -> 1975720.3 | H78: =SUM(H56:H77) -> 11155053 | I78: =SUM(I56:I77) -> 0 | J78: =SUM(J56:J77) -> 290166.02 | ... M78: =SUM(M56:M77) -> 14159309
B79: NOTE: Cost included in overall staff costs
A81: WBS | B81: Description | C81: LSA Waste (M3) | D81: Hazardous Waste Vol (M3) | E81: Mixed Waste Vol (M3) | F81: Clean Waste Vol. (M3) | G81: Mat's, Consumables & Equip. | H81: Labor Cost | I81: LSA Waste Cost (TBD) | J81: Hazardous Waste Cost | K81: Mixed Waste Cost | L81: Clean Waste Cost | M81: Total Cost
A82: 1.0 | B82: Building B56
A83: 1.1 | B83: Project Management
A84: 1.1.1 | B84: Staff | H84: ='Building B56'!T8 -> 256232.55 | M84: =SUM(G84:L84) -> 256232.55
A85: 1.1.2 | B85: Equipment, Material & Consumables | G85: ='Building B56'!S8 -> 1843800 | M85: =SUM(G85:L85) -> 1843800
A86: 1.2 | B86: Project Planning
A87: 1.2.1 | B87: Procedure Development | H87: ='Building B56'!T68 -> 22935.2 | M87: =SUM(G87:L87) -> 22935.2
A88: 1.2.2 | B88: QA and Safety Documents | H88: ='Building B56'!T75 -> 22935.2 | M88: =SUM(G88:L88) -> 22935.2
A89: 1.2.3 | B89: Mobilization | H89: ='Building B56'!T82 -> 225123.7 | M89: =SUM(G89:L89) -> 225123.7
A90: 1.3 | B90: Preliminary Site Investigation | M90: =SUM(G90:L90) -> 0
A91: 1.3.1 | B91: Decontamination Readiness Review | H91: See Note | M91: =SUM(G91:L91) -> 0
A92: 1.3.2 | B92: Site Prep | H92: ='Building B56'!T118 -> 44658.24 | M92: =SUM(G92:L92) -> 44658.24
A93: 1.4 | B93: Detailed Characterization | H93: ='Building B56'!T177 -> 297721.6 | M93: =SUM(G93:L93) -> 297721.6
A94: 1.5 | B94: Decontamination | C94: ='Building B56'!N185 -> 39.256953 | D94: ='Building B56'!O185 -> 425.0234 | E94: ='Building B56'!Q185 -> 4.4867312 | F94: ='Building B56'!R185 -> 343.90622
A95: 1.5.1 | B95: Asbestos Removal | H95: ='Building B56'!I189 -> 0 | M95: =SUM(G95:L95) -> 0
A96: 1.5.2 | B96: Remove systems and Components | H96: ='Building B56'!I197 -> 4851275.2 | M96: =SUM(G96:L96) -> 4851275.2
A97: 1.5.3 | B97: Decontaminate Structure | C97: =IF('Building B17'!N284>0,'Building B17'!N284, " ") | D97: =IF('Building B17'!O284>0,'Building B17'!O284, " ") | E97: =IF('Building B17'!Q284>0,'Building B17'!Q284, " ") | F97: =IF('Building B17'!R284>0,'Building B17'!R284, " ") | H97: ='Building B56'!I203 -> 2082904.5 | M97: =SUM(G97:L97) -> 2082904.5
A98: 1.5.4 | B98: Final Survey | H98: ='Building B56'!I205 -> 754658.97 | M98: =SUM(G98:L98) -> 754658.97
A99: 1.6 | B99: Site Remediation | F99: ='Building B56'!R207 -> 1390.5317
A100: 1.6.1 | B100: Remove Building | H100: ='Building B56'!I208 -> 2126417.3 | M100: =SUM(G100:L100) -> 2126417.3
A101: 1.6.2 | B101: Grade and Seed | H101: ='Building B56'!I210 -> 98554.805 | M101: =SUM(G101:L101) -> 98554.805
A102: 1.6.3 | B102: Backfill | H102: ='Building B56'!I211 -> 225770.17 | M102: =SUM(G102:L102) -> 225770.17
A103: 1.7 | B103: Waste Disposal | J103: ='Building B56'!V214 -> 375239.61 | K103: ='Building B56'!X214 -> 3961.1919 | L103: ='Building B56'!Y214 -> 918767.96 | M103: =SUM(G103:L103) -> 1297968.8
B104: TOTAL | C104: =SUM(C83:C103) -> 39.256953 | D104: =SUM(D83:D103) -> 425.0234 | E104: =SUM(E83:E103) -> 4.4867312 | F104: =SUM(F83:F103) -> 1734.4379 | G104: =SUM(G83:G103) -> 1843800 | H104: =SUM(H83:H103) -> 11009187 | I104: =SUM(I83:I103) -> 0 | J104: =SUM(J83:J103) -> 375239.61 | ... M104: =SUM(M83:M103) -> 14150956
...

Sheet Building B17
A1: B 17 DATA - Data highlighted in GREEN can be adjusted as needed
J2: Uncorrected Duration
I3: Crew | J3: (No. of Hours) | K3: Prod. Factor | L3: Adjusted Duration (hrs) | M3: Man-hours | N3: LSA Waste Disp. Vol (cm) | O3: Hazardous Waste Vol (cm) | Q3: Mixed Waste Volume (cm) | R3: Clean Waste Volume (cm) | S3: Materials, Consumables & Equipment | T3: Labor Cost | U3: LSA Waste Costs | V3: Hazardous Waste Costs | W3: LSA Waste Costs | X3: Mixed Waste Costs | Y3: Clean Waste Costs | Z3: Total Cost
A5: 1.0 | B5: Building B17 | L5: =L7+L65+L117+L176+L184+L204 -> 631 | M5: =M7+M65+M117+M176+M184+M204 -> 3073 | N5: =N7+N65+N117+N176+N184+N204 -> 15.960162 | O5: =O7+O65+O117+O176+O184+O204 -> 0.24497299 | Q5: =Q7+Q65+Q117+Q176+Q184+Q204 -> 2.0286826 | R5: =R7+R65+R117+R176+R184+R204 -> 698.19309 | S5: =S7+S65+S117+S176+S184+S204+S210 -> 649056.62 | T5: =T7+T65+T117+T176+T184+T204+T210 -> 1644808.1 | V5: =V7+V65+V117+V176+V184+V204+V210 -> 2007.338 | Y5: =Y7+Y65+Y117+Y176+Y184+Y204+Y210 -> 369847.45 | Z5: =SUM(S5:Y5) -> 2665719.5
A7: 1.1 | B7: Project Management | S7: =IF(G17="US",(H45+M57+K59+K61+K63)*Inputs!C37,(H45+M57+K59+K61+K63)) -> 649056.62 | T7: =I14 -> 268756.2 | Z7: =SUM(S7:Y7) -> 917812.82
A9: 1.1.1 | B9: Staff | E9: Number | F9: Rate | G9: Duration, days* | H9: Use Factor | I9: Cost | J9: Man-hours
B10: =Inputs!A$51 -> Portfolio Manager | E10: 1 | F10: =Inputs!E51 -> 157.87 | G10: =Inputs!B$144 -> 180 | H10: 0.25 | I10: =H10*G10*F10*E10*8 -> 56833.2 | J10: =H10*G10*10 -> 450
B11: =Inputs!A$50 -> Senior Project Manager / Characterization SME | E11: 1 | F11: =Inputs!E50 -> 127.28 | G11: =Inputs!B$144 -> 180 | H11: 0.5 | I11: =H11*G11*F11*E11*10 -> 114552 | J11: =H11*G11*10 -> 900
B12: =Inputs!A$49 -> Project Manager / Waste Management | E12: 1 | F12: =Inputs!E49 -> 108.19 | G12: =Inputs!B$144 -> 180 | H12: 0.5 | I12: =H12*G12*F12*E12*10 -> 97371 | J12: =H12*G12*10 -> 900
B13: =Inputs!A$48 -> Decom Technician / Safety SME | E13: 0 | F13: =Inputs!E48 -> 89.25 | G13: =Inputs!B$144 -> 180 | H13: 1 | I13: =H13*G13*F13*E13*10 -> 0 | J13: =H13*G13*10 -> 1800
E14: =SUM(E10:E13) -> 3 | I14: =SUM(I10:I13) -> 268756.2 | J14: =SUM(J10:J13) -> 4050
A16: 1.1.2 | B16: Equipment & Materials
G17: =Inputs!D85 -> US
C18: Equipment | F18: Quantity | G18: Rate | H18: Escalated Cost
C19: HEPA filter systems | F19: =IF(Inputs!$F$139=Inputs!$C$86,Inputs!C88,IF(Inputs!$F$139=Inputs!$G$86,Inputs!G88,IF(Inputs!$F$139=Inputs!$J$86,Inputs!J88,IF(Inputs!$F$139=Inputs!$M$86,Inputs!M88,"na")))) -> 2 | G19: =Inputs!D88 -> 3598.14 | H19: =G19*F19*(1+Inputs!$F$86) -> 11371.124
C20: Replacement filters | F20: =IF(Inputs!$F$139=Inputs!$C$86,Inputs!C89,IF(Inputs!$F$139=Inputs!$G$86,Inputs!G89,IF(Inputs!$F$139=Inputs!$J$86,Inputs!J89,IF(Inputs!$F$139=Inputs!$M$86,Inputs!M89,"na")))) -> 24 | G20: =Inputs!D89 -> 581.07 | H20: =G20*F20*(1+Inputs!$F$86) -> 22036.115
C21: Respirator | F21: =IF(Inputs!$F$139=Inputs!$C$86,Inputs!C90,IF(Inputs!$F$139=Inputs!$G$86,Inputs!G90,IF(Inputs!$F$139=Inputs!$J$86,Inputs!J90,IF(Inputs!$F$139=Inputs!$M$86,Inputs!M90,"na")))) -> 12 | G21: =Inputs!D90 -> 259 | H21: =G21*F21*(1+Inputs!$F$86) -> 4911.0725
C22: Rad/Vac wet-dry high eff. vacuum | F22: =IF(Inputs!$F$139=Inputs!$C$86,Inputs!C91,IF(Inputs!$F$139=Inputs!$G$86,Inputs!G91,IF(Inputs!$F$139=Inputs!$J$86,Inputs!J91,IF(Inputs!$F$139=Inputs!$M$86,Inputs!M91,"na")))) -> 2 | G22: =Inputs!D91 -> 3879 | H22: =G22*F22*(1+Inputs!$F$86) -> 12258.72
C23: Rad/Vac wet-dry high eff. vacuum filters | F23: =IF(Inputs!$F$139=Inputs!$C$86,Inputs!C92,IF(Inputs!$F$139=Inputs!$G$86,Inputs!G92,IF(Inputs!$F$139=Inputs!$J$86,Inputs!J92,IF(Inputs!$F$139=Inputs!$M$86,Inputs!M92,"na")))) -> 5 | G23: =Inputs!D92 -> 412 | H23: =G23*F23*(1+Inputs!$F$86) -> 3255.0867
C24: Reciprocating Saws | F24: =IF(Inputs!$F$139=Inputs!$C$86,Inputs!C93,IF(Inputs!$F$139=Inputs!$G$86,Inputs!G93,IF(Inputs!$F$139=Inputs!$J$86,Inputs!J93,IF(Inputs!$F$139=Inputs!$M$86,Inputs!M93,"na")))) -> 5 | G24: =Inputs!D93 -> 1252.26 | H24: =G24*F24*(1+Inputs!$F$86) -> 9893.7254
C25: Pneumatic chipping hammers | F25: =IF(Inputs!$F$139=Inputs!$C$86,Inputs!C94,IF(Inputs!$F$139=Inputs!$G$86,Inputs!G94,IF(Inputs!$F$139=Inputs!$J$86,Inputs!J94,IF(Inputs!$F$139=Inputs!$M$86,Inputs!M94,"na")))) -> 2 | G25: =Inputs!D94 -> 1606.71 | H25: =G25*F25*(1+Inputs!$F$86) -> 5077.6508
C26: Chipping hammer blades | F26: =IF(Inputs!$F$139=Inputs!$C$86,Inputs!C95,IF(Inputs!$F$139=Inputs!$G$86,Inputs!G95,IF(Inputs!$F$139=Inputs!$J$86,Inputs!J95,IF(Inputs!$F$139=Inputs!$M$86,Inputs!M95,"na")))) -> 20 | G26: =Inputs!D95 -> 27.42 | H26: =G26*F26*(1+Inputs!$F$86) -> 866.54832
C27: Purchase an air compressor: | F27: =IF(Inputs!$F$139=Inputs!$C$86,Inputs!C96,IF(Inputs!$F$139=Inputs!$G$86,Inputs!G96,IF(Inputs!$F$139=Inputs!$J$86,Inputs!J96,IF(Inputs!$F$139=Inputs!$M$86,Inputs!M96,"na")))) -> 2 | G27: =Inputs!D96 -> 1723.44 | H27: =G27*F27*(1+Inputs!$F$86) -> 5446.5501
C28: Jackhammer | F28: =IF(Inputs!$F$139=Inputs!$C$86,Inputs!C97,IF(Inputs!$F$139=Inputs!$G$86,Inputs!G97,IF(Inputs!$F$139=Inputs!$J$86,Inputs!J97,IF(Inputs!$F$139=Inputs!$M$86,Inputs!M97,"na")))) -> 4 | G28: =Inputs!D97 -> 1417.11 | H28: =G28*F28*(1+Inputs!$F$86) -> 8956.9241
C29: Jackhammer Chisels | F29: =IF(Inputs!$F$139=Inputs!$C$86,Inputs!C98,IF(Inputs!$F$139=Inputs!$G$86,Inputs!G98,IF(Inputs!$F$139=Inputs!$J$86,Inputs!J98,IF(Inputs!$F$139=Inputs!$M$86,Inputs!M98,"na")))) -> 10 | G29: =Inputs!D98 -> 24.35 | H29: =G29*F29*(1+Inputs!$F$86) -> 384.76389
C30: Safety glasses | F30: =IF(Inputs!$F$139=Inputs!$C$86,Inputs!C99,IF(Inputs!$F$139=Inputs!$G$86,Inputs!G99,IF(Inputs!$F$139=Inputs!$J$86,Inputs!J99,IF(Inputs!$F$139=Inputs!$M$86,Inputs!M99,"na")))) -> 15 | G30: =Inputs!D99 -> 8.6 | H30: =G30*F30*(1+Inputs!$F$86) -> 203.83795
... C44: Crane rental for building removal | F44: =IF(Inputs!$F$139=Inputs!$C$86,Inputs!C113,IF(Inputs!$F$139=Inputs!$G$86,Inputs!G113,IF(Inputs!$F$139=Inputs!$J$86,Inputs!J113,IF(Inputs!$F$139=Inputs!$M$86,Inputs!M113,"na")))) -> 1 | G44: =Inputs!D113 -> 15600 | H44: =G44*F44*(1+Inputs!$F$86) -> 24650.171
H45: =SUM(H19:H44) -> 232543.75
L46: =Inputs!H115 -> US
C47: Consumables | E47: Quantity | G47: Duration | I47: # workers | J47: quantity | K47: Unit Qty | L47: Unit Cost | M47: Escalated Cost
C48: Coveralls | E48: =IF(Inputs!$F$139=Inputs!$C$86,Inputs!B117,IF(Inputs!$F$139=Inputs!$G$86,Inputs!D117,IF(Inputs!$F$139=Inputs!$J$86,Inputs!E117,IF(Inputs!$F$139=Inputs!$M$86,Inputs!F117,"na")))) -> 2 | F48: /man/day | G48: =Inputs!B145 -> 90 | H48: days | I48: =Inputs!F$148 -> 12 | J48: =I48*G48*E48 -> 2160 | K48: 1 | L48: =Inputs!H117 -> 11 | M48: =J48/K48*L48*(1+Inputs!$F$86) -> 37544.107
C49: Hoods | E49: =IF(Inputs!$F$139=Inputs!$C$86,Inputs!B118,IF(Inputs!$F$139=Inputs!$G$86,Inputs!D118,IF(Inputs!$F$139=Inputs!$J$86,Inputs!E118,IF(Inputs!$F$139=Inputs!$M$86,Inputs!F118,"na")))) -> 0.1 | F49: /man/day | G49: =Inputs!B145 -> 90 | H49: days | I49: =Inputs!F$148 -> 12 | J49: =I49*G49*E49 -> 108 | K49: 1 | L49: =Inputs!H118 -> 0 | M49: =J49/K49*L49*(1+Inputs!$F$86) -> 0
C50: Shoe covers | E50: =IF(Inputs!$F$139=Inputs!$C$86,Inputs!B119,IF(Inputs!$F$139=Inputs!$G$86,Inputs!D119,IF(Inputs!$F$139=Inputs!$J$86,Inputs!E119,IF(Inputs!$F$139=Inputs!$M$86,Inputs!F119,"na")))) -> 4 | F50: /man/day | G50: =Inputs!B145 -> 90 | H50: days | I50: =Inputs!F$148 -> 12 | J50: =I50*G50*E50 -> 4320 | K50: 1 | L50: =Inputs!H119 -> 0.94 | M50: =J50/K50*L50*(1+Inputs!$F$86) -> 6416.6291
C51: Latex gloves | E51: =IF(Inputs!$F$139=Inputs!$C$86,Inputs!B120,IF(Inputs!$F$139=Inputs!$G$86,Inputs!D120,IF(Inputs!$F$139=Inputs!$J$86,Inputs!E120,IF(Inputs!$F$139=Inputs!$M$86,Inputs!F120,"na")))) -> 4 | F51: /man/day | G51: =Inputs!B145 -> 90 | H51: days | I51: =Inputs!F$148 -> 12 | J51: =I51*G51*E51 -> 4320 | K51: 1 | L51: =Inputs!H120 -> 0.94 | M51: =J51/K51*L51*(1+Inputs!$F$86) -> 6416.6291
C52: Rubber overshoes | E52: =IF(Inputs!$F$139=Inputs!$C$86,Inputs!B121,IF(Inputs!$F$139=Inputs!$G$86,Inputs!D121,IF(Inputs!$F$139=Inputs!$J$86,Inputs!E121,IF(Inputs!$F$139=Inputs!$M$86,Inputs!F121,"na")))) -> 0.01 | F52: /man/day | G52: =Inputs!B145 -> 90 | H52: days | I52: =Inputs!F$148 -> 12 | J52: =I52*G52*E52 -> 10.8 | K52: 1 | L52: =Inputs!H121 -> 3 | M52: =J52/K52*L52*(1+Inputs!$F$86) -> 51.196509
C53: Gloves | E53: =IF(Inputs!$F$139=Inputs!$C$86,Inputs!B122,IF(Inputs!$F$139=Inputs!$G$86,Inputs!D122,IF(Inputs!$F$139=Inputs!$J$86,Inputs!E122,IF(Inputs!$F$139=Inputs!$M$86,Inputs!F122,"na")))) -> 0.01 | F53: /man/day | G53: =Inputs!B145 -> 90 | H53: days | I53: =Inputs!F$148 -> 12 | J53: =I53*G53*E53 -> 10.8 | K53: 1 | L53: =Inputs!H122 -> 2 | M53: =J53/K53*L53*(1+Inputs!$F$86) -> 34.131006
C54: Dosimeters | E54: =IF(Inputs!$F$139=Inputs!$C$86,Inputs!B123,IF(Inputs!$F$139=Inputs!$G$86,Inputs!D123,IF(Inputs!$F$139=Inputs!$J$86,Inputs!E123,IF(Inputs!$F$139=Inputs!$M$86,Inputs!F123,"na")))) -> 1 | F54: /man/year | G54: =1/3 -> 0.33333333 | H54: year | I54: =Inputs!F$148 -> 12 | J54: =I54*G54*E54 -> 4 | K54: 1 | L54: =Inputs!H123 -> 200 | M54: =J54/K54*L54*(1+Inputs!$F$86) -> 1264.1113
C55: TLDs | E55: =IF(Inputs!$F$139=Inputs!$C$86,Inputs!B124,IF(Inputs!$F$139=Inputs!$G$86,Inputs!D124,IF(Inputs!$F$139=Inputs!$J$86,Inputs!E124,IF(Inputs!$F$139=Inputs!$M$86,Inputs!F124,"na")))) -> 1 | F55: /man/mo | G55: 3 | H55: month | I55: =Inputs!F$148 -> 12 | J55: =I55*G55*E55 -> 36 | K55: 1 | L55: =Inputs!H124 -> 3 | M55: =J55/K55*L55*(1+Inputs!$F$86) -> 170.65503
C56: Bioassays | E56: =IF(Inputs!$F$139=Inputs!$C$86,Inputs!B125,IF(Inputs!$F$139=Inputs!$G$86,Inputs!D125,IF(Inputs!$F$139=Inputs!$J$86,Inputs!E125,IF(Inputs!$F$139=Inputs!$M$86,Inputs!F125,"na")))) -> 2 | F56: /man/year | G56: 1 | H56: year | I56: =Inputs!F$148 -> 12 | J56: =I56*G56*E56 -> 24 | K56: 1 | L56: =Inputs!H125 -> 250 | M56: =J56/K56*L56*(1+Inputs!$F$86) -> 9480.835
C57: (Bioassays for aver. crew & management) | M57: =SUM(M48:M56) -> 61378.294
C59: Small Tools - 2% of total labor costs = | G59: =(T5-T7) -> 1376051.9 | H59: labor costs x | I59: =Inputs!F128 -> 0.02 | J59: = | K59: =I59*G59 -> 27521.038
C61: HP Equipment Replacement - 5% of total labor | G61: =G59 -> 1376051.9 | H61: labor costs x | I61: =Inputs!F130 -> 0.05 | J61: = | K61: =I61*G61 -> 68802.594
C63: DGC OH &P on equipment and materials | G63: =R67+K61+K59+M57+H45 -> 390245.68 | I63: =Inputs!F132 -> 0.08 | J63: = | K63: =I63*G63 -> 31219.654
A65: 1.2 | B65: Project Planning | J65: =J67+J74+J81 -> 415 | L65: =L67+L74+L81 -> 415 | M65: =M67+M74+M81 -> 1785 | T65: =T67+T74+T81 -> 169249.1 | Z65: =SUM(T65:Y65) -> 169249.1
A67: 1.2.1 | B67: Procedure Development and Review | J67: =I72 -> 160 | K67: 1 | L67: =J67*K67 -> 160 | M67: =L72 -> 240 | T67: =K72 -> 22935.2
D69: Staff | G69: Number | H69: Rate | I69: Duration | J69: PLF | K69: Cost | L69: Man-hours
D70: Project Specialist | G70: 2 | H70: =Inputs!E$48 -> 89.25 | I70: 80 | J70: 1 | K70: =G70*H70*I70*J70 -> 14280 | L70: =J70*I70*G70 -> 160
D71: Project Manager | G71: 1 | H71: =Inputs!E$49 -> 108.19 | I71: 80 | J71: 1 | K71: =G71*H71*I71*J71 -> 8655.2 | L71: =J71*I71*G71 -> 80
G72: =SUM(G70:G71) -> 3 | I72: =SUM(I70:I71) -> 160 | K72: =SUM(K70:K71) -> 22935.2 | L72: =SUM(L70:L71) -> 240
A74: 1.2.2 | B74: Preparation of QA and Safety Documents | J74: =I79 -> 160 | K74: 1 | L74: =J74*K74 -> 160 | M74: =L79 -> 240 | T74: =K79 -> 22935.2
D76: Staff | G76: Number | H76: Rate | I76: Duration | J76: PLF | K76: Cost | L76: Man-hours
D77: Project Specialist | G77: 2 | H77: =Inputs!E$48 -> 89.25 | I77: 80 | J77: 1 | K77: =J77*I77*H77*G77 -> 14280 | L77: =J77*I77*G77 -> 160
D78: Project Manager | G78: 1 | H78: =Inputs!E$49 -> 108.19 | I78: 80 | J78: 1 | K78: =J78*I78*H78*G78 -> 8655.2 | L78: =J78*I78*G78 -> 80
G79: =SUM(G77:G78) -> 3 | I79: =SUM(I77:I78) -> 160 | K79: =SUM(K77:K78) -> 22935.2 | L79: =SUM(L77:L78) -> 240
A81: 1.2.3 | B81: Site Mobilization and General Employee Training (GET) | J81: =J83+J96 -> 95 | K81: 1 | L81: =J81*K81 -> 95 | M81: =M83+M96 -> 1305 | T81: =T83+T96 -> 123378.7
C83: 1.2.3.1 | D83: Site Mobilization | J83: =F94 -> 40 | K83: 1 | L83: =J83*K83 -> 40 | M83: =J83*D86 -> 480 | T83: =I94 -> 42840
D85: Crew | G85: Rate, $/hr | H85: Cost, $/hr
D86: 12 | E86: Decom Technician / Safety SME | G86: =Inputs!E48 -> 89.25 | H86: =G86*D86 -> 1071
D88: Receipt of material and equipment | G88: 16 | H88: hr
D89: Staging of equipment | G89: 8 | H89: hr
D90: Set up office and amenities | G90: 12 | H90: hr
D91: Familiarize staff with facility | G91: 4 | H91: hr
G92: =SUM(G88:G91) -> 40 | H92: hr
D94: Total Cost = | F94: =G92 -> 40 | G94: x | H94: =H86 -> 1071 | I94: =H94*F94 -> 42840
C96: 1.2.3.2 | D96: General Employee Training (All proj. management and 3 crews of 4) | J96: =F115 -> 55 | K96: 1 | L96: =K96*J96 -> 55 | M96: =D103*F115 -> 825 | S96: =J115*Inputs!C37 -> 30030 | T96: =K115 -> 80538.7
D98: Crew | G98: Rate, $/hr | H98: Cost, $/hr
D99: 1 | E99: =B10 -> Portfolio Manager | G99: =F10 -> 157.87 | H99: =G99*D99 -> 157.87
D100: 1 | E100: =B11 -> Senior Project Manager / Characterization SME | G100: =F11 -> 127.28 | H100: =G100*D100 -> 127.28
D101: 1 | E101: =B12 -> Project Manager / Waste Management | G101: =F12 -> 108.19 | H101: =G101*D101 -> 108.19
D102: 12 | E102: =B13 -> Decom Technician / Safety SME | G102: =F13 -> 89.25 | H102: =G102*D102 -> 1071
D103: =SUM(D99:D102) -> 15 | H103: =SUM(H99:H102) -> 1464.34
I105: Number | J105: Test | K105: Labor | L105: Total
H106: Unit Cost | I106: Required | J106: Cost | K106: Costs | L106: Cost
D107: In-Vivo | H107: 600 | I107: =D$103 -> 15 | J107: =I107*H107 -> 9000 | K107: =F107*H$103 -> 0 | L107: =K107+J107 -> 9000
D108: In-Vitro | H108: 350 | I108: =D$103 -> 15 | J108: =I108*H108 -> 5250 | K108: =F108*H$103 -> 0 | L108: =K108+J108 -> 5250
D109: Physical @ | F109: 4 | G109: hour and | H109: 150 | I109: =D$103 -> 15 | J109: =I109*H109 -> 2250 | K109: =F109*H$103 -> 5857.36 | L109: =K109+J109 -> 8107.36
D110: Resp. Tests | F110: 1 | G110: hour and | H110: 50 | I110: =D$103 -> 15 | J110: =I110*H110 -> 750 | K110: =F110*H$103 -> 1464.34 | L110: =K110+J110 -> 2214.34
D111: Resp Fit Tests | F111: 1 | G111: hour and | H111: 25 | I111: =D$103 -> 15 | J111: =I111*H111 -> 375 | K111: =F111*H$103 -> 1464.34 | L111: =K111+J111 -> 1839.34
D112: Blood Tests | F112: 1 | G112: hour and | H112: 125 | I112: =D$103 -> 15 | J112: =I112*H112 -> 1875 | K112: =F112*H$103 -> 1464.34 | L112: =K112+J112 -> 3339.34
D113: OSHA recertification | F113: 8 | G113: hour | K113: =F113*H$103 -> 11714.72 | L113: =K113+J113 -> 11714.72
D114: Site specific 1 week of training | F114: 40 | G114: hour | K114: =F114*H$103 -> 58573.6 | L114: =K114+J114 -> 58573.6
F115: =SUM(F109:F114) -> 55 | J115: =SUM(J107:J114) -> 19500 | K115: =SUM(K109:K114) -> 80538.7 | L115: =SUM(L107:L114) -> 100038.7
A117: 1.3 | B117: Preliminary Site Investigation | J117: =J119+J121 -> 176 | L117: =L119+L121 -> 176 | M117: =M119+M121 -> 488 | T117: =T119+T121 -> 45402.544 | U117: using this for 1.3.1 | Z117: =SUM(T117:Y117) -> 45402.544
A119: 1.3.1 | B119: Decontamination Readiness Review - (Contractor staff cost included in Undistributed Costs) | J119: 80 | K119: 1 | L119: =K119*J119 -> 80
A121: 1.3.2 | B121: Site Preparation | H121: A | J121: =J123+J132+J150+J158 -> 96 | K121: 1 | L121: =L123+L132+L150+L158 -> 96 | M121: =M123+M132+M150+M158 -> 488 | S121: 1.3.2 | T121: =T123+T132+T150+T158 -> 45402.544
B123: 1.3.2.1 | C123: Initial Site Survey | H123: A | J123: =F125 -> 16 | K123: 1 | L123: =K123*J123 -> 16 | M123: =L129 -> 88 | T123: =K129 -> 8187.344
E125: Estimated Duration | F125: 16 | G125: hrs
D126: Staff | G126: Number | H126: Rate | I126: Duration | J126: PLF | K126: Cost | L126: Man-hours
D127: Project Specialist | G127: 4 | H127: =Inputs!E$48 -> 89.25 | I127: =F125 -> 16 | J127: 1.1 | K127: =J127*I127*H127*G127 -> 6283.2 | L127: =J127*I127*G127 -> 70.4
D128: Project Manager | G128: 1 | H128: =Inputs!E$49 -> 108.19 | I128: =F125 -> 16 | J128: 1.1 | K128: =J128*I128*H128*G128 -> 1904.144 | L128: =J128*I128*G128 -> 17.6
G129: =SUM(G127:G128) -> 5 | I129: =SUM(I127:I128) -> 32 | K129: =SUM(K127:K128) -> 8187.344 | L129: =SUM(L127:L128) -> 88
B132: 1.3.2.2 | C132: Setup work areas | J132: =J134+J142 -> 32 | L132: =L134+L142 -> 32 | M132: =M134+M142 -> 160 | T132: =T134+T142 -> 14886.08
B134: 1.3.2.2.1 | C134: Setup boundaries, install HEPA filters & seal off openings | H134: A | J134: =F136 -> 16 | K134: 1 | L134: =K134*J134 -> 16 | M134: =L140 -> 80 | T134: =K140 -> 7443.04
E136: Estimated Duration | F136: 16 | G136: hrs
D137: Staff | G137: Number | H137: Rate | I137: Duration | J137: PLF | K137: Cost | L137: Man-hours
D138: Project Specialist | G138: 4 | H138: =Inputs!E$48 -> 89.25 | I138: =F136 -> 16 | J138: 1 | K138: =J138*I138*H138*G138 -> 5712 | L138: =J138*I138*G138 -> 64
D139: Project Manager | G139: 1 | H139: =Inputs!E$49 -> 108.19 | I139: =F136 -> 16 | J139: 1 | K139: =J139*I139*H139*G139 -> 1731.04 | L139: =J139*I139*G139 -> 16
G140: =SUM(G138:G139) -> 5 | I140: =SUM(I138:I139) -> 32 | K140: =SUM(K138:K139) -> 7443.04 | L140: =SUM(L138:L139) -> 80
B142: 1.3.2.2.2 | C142: Establish staging area | H142: A | J142: =F144 -> 16 | K142: 1 | L142: =K142*J142 -> 16 | M142: =L148 -> 80 | T142: =K148 -> 7443.04
E144: Estimated Duration | F144: 16 | G144: hrs
...

Sheet Building B54
A1: B 54 DATA - Data highlighted in GREEN can be adjusted as needed
J2: Uncorrected Duration
I3: Crew | J3: (No. of Hours) | K3: Prod. Factor | L3: Adjusted Duration (hrs) | M3: Man-hours | N3: LSA Waste Disp. Vol (cm) | O3: Hazardous Waste Vol (cm) | Q3: Mixed Waste Volume (cm) | R3: Clean Waste Volume (cm) | S3: Materials, Consumables & Equipment | T3: Labor Cost | U3: LSA Waste Costs | V3: Hazardous Waste Costs | W3: LSA Waste Costs | X3: Mixed Waste Costs | Y3: Clean Waste Costs | Z3: Total Cost
A6: 1.0 | B6: Building B54 | L6: =L8+L66+L118+L177+L185+L207 -> 631 | M6: =M8+M66+M118+M177+M185+M207 -> 8205 | N6: =N8+N66+N118+N177+N185+N207 -> 30.356693 | O6: =O8+O66+O118+O177+O185+O207 -> 328.66293 | Q6: =Q8+Q66+Q118+Q177+Q185+Q207 -> 3.4695083 | R6: =R8+R66+R118+R177+R185+R207 -> 1341.2095 | S6: =S8+S66+S118+S177+S185+S207+S214 -> 1975720.3 | T6: =T8+T66+T118+T177+T185+T207+T214 -> 11155053 | V6: =V8+V66+V118+V177+V185+V207+V214 -> 290166.02 | X6: =X8+X66+X118+X177+X185+X207+X214 -> 27902.761 | Y6: =Y8+Y66+Y118+Y177+Y185+Y207+Y214 -> 710466.68 | Z6: =SUM(S6:Y6) -> 14159309
A8: 1.1 | B8: Project Management | S8: =IF(G18="US",(H46+M58+K60+K62+K64)*Inputs!C37,(H46+M58+K60+K62+K64)) -> 1975720.3 | T8: =I15 -> 614958.12 | Z8: =SUM(S8:Y8) -> 2590678.4
A10: 1.1.1 | B10: Staff | E10: Number | F10: Rate | G10: Duration, days* | H10: Use Factor | I10: Cost | J10: Man-hours
B11: =Inputs!A$51 -> Portfolio Manager | E11: 1 | F11: =Inputs!E51 -> 157.87 | G11: =Inputs!G$172 -> 252 | H11: 1 | I11: =H11*G11*F11*E11*8 -> 318265.92 | J11: =H11*G11*10 -> 2520
B12: =Inputs!A$50 -> Senior Project Manager / Characterization SME | E12: 1 | F12: =Inputs!E50 -> 127.28 | G12: =Inputs!G$172 -> 252 | H12: 0.5 | I12: =H12*G12*F12*E12*10 -> 160372.8 | J12: =H12*G12*10 -> 1260
B13: =Inputs!A$49 -> Project Manager / Waste Management | E13: 1 | F13: =Inputs!E49 -> 108.19 | G13: =Inputs!G$172 -> 252 | H13: 0.5 | I13: =H13*G13*F13*E13*10 -> 136319.4 | J13: =H13*G13*10 -> 1260
B14: =Inputs!A$48 -> Decom Technician / Safety SME | E14: 0 | F14: =Inputs!E48 -> 89.25 | G14: =Inputs!G$172 -> 252 | H14: 1 | I14: =H14*G14*F14*E14*10 -> 0 | J14: =H14*G14*10 -> 2520
E15: =SUM(E11:E14) -> 3 | I15: =SUM(I11:I14) -> 614958.12 | J15: =SUM(J11:J14) -> 7560
A17: 1.1.2 | B17: Equipment & Materials
G18: =Inputs!D85 -> US
C19: Equipment | F19: Quantity | G19: Rate | H19: Escalated Cost
C20: HEPA filter systems | F20: =IF(Inputs!$B$169=Inputs!$C$86,Inputs!C88,IF(Inputs!$B$169=Inputs!$G$86,Inputs!G88,IF(Inputs!$B$169=Inputs!$J$86,Inputs!J88,IF(Inputs!$B$169=Inputs!$M$86,Inputs!M88,"na")))) -> 2 | G20: =Inputs!D88 -> 3598.14 | H20: =G20*F20*(1+Inputs!$F$86) -> 11371.124
C21: Replacement filters | F21: =IF(Inputs!$B$169=Inputs!$C$86,Inputs!C89,IF(Inputs!$B$169=Inputs!$G$86,Inputs!G89,IF(Inputs!$B$169=Inputs!$J$86,Inputs!J89,IF(Inputs!$B$169=Inputs!$M$86,Inputs!M89,"na")))) -> 24 | G21: =Inputs!D89 -> 581.07 | H21: =G21*F21*(1+Inputs!$F$86) -> 22036.115
C22: Respirator | F22: =IF(Inputs!$B$169=Inputs!$C$86,Inputs!C90,IF(Inputs!$B$169=Inputs!$G$86,Inputs!G90,IF(Inputs!$B$169=Inputs!$J$86,Inputs!J90,IF(Inputs!$B$169=Inputs!$M$86,Inputs!M90,"na")))) -> 12 | G22: =Inputs!D90 -> 259 | H22: =G22*F22*(1+Inputs!$F$86) -> 4911.0725
C23: Rad/Vac wet-dry high eff. vacuum | F23: =IF(Inputs!$B$169=Inputs!$C$86,Inputs!C91,IF(Inputs!$B$169=Inputs!$G$86,Inputs!G91,IF(Inputs!$B$169=Inputs!$J$86,Inputs!J91,IF(Inputs!$B$169=Inputs!$M$86,Inputs!M91,"na")))) -> 1 | G23: =Inputs!D91 -> 3879 | H23: =G23*F23*(1+Inputs!$F$86) -> 6129.3598
C24: Rad/Vac wet-dry high eff. vacuum filters | F24: =IF(Inputs!$B$169=Inputs!$C$86,Inputs!C92,IF(Inputs!$B$169=Inputs!$G$86,Inputs!G92,IF(Inputs!$B$169=Inputs!$J$86,Inputs!J92,IF(Inputs!$B$169=Inputs!$M$86,Inputs!M92,"na")))) -> 5 | G24: =Inputs!D92 -> 412 | H24: =G24*F24*(1+Inputs!$F$86) -> 3255.0867
C25: Reciprocating Saws | F25: =IF(Inputs!$B$169=Inputs!$C$86,Inputs!C93,IF(Inputs!$B$169=Inputs!$G$86,Inputs!G93,IF(Inputs!$B$169=Inputs!$J$86,Inputs!J93,IF(Inputs!$B$169=Inputs!$M$86,Inputs!M93,"na")))) -> 5 | G25: =Inputs!D93 -> 1252.26 | H25: =G25*F25*(1+Inputs!$F$86) -> 9893.7254
C26: Pneumatic chipping hammers | F26: =IF(Inputs!$B$169=Inputs!$C$86,Inputs!C94,IF(Inputs!$B$169=Inputs!$G$86,Inputs!G94,IF(Inputs!$B$169=Inputs!$J$86,Inputs!J94,IF(Inputs!$B$169=Inputs!$M$86,Inputs!M94,"na")))) -> 2 | G26: =Inputs!D94 -> 1606.71 | H26: =G26*F26*(1+Inputs!$F$86) -> 5077.6508
C27: Chipping hammer blades | F27: =IF(Inputs!$B$169=Inputs!$C$86,Inputs!C95,IF(Inputs!$B$169=Inputs!$G$86,Inputs!G95,IF(Inputs!$B$169=Inputs!$J$86,Inputs!J95,IF(Inputs!$B$169=Inputs!$M$86,Inputs!M95,"na")))) -> 20 | G27: =Inputs!D95 -> 27.42 | H27: =G27*F27*(1+Inputs!$F$86) -> 866.54832
C28: Purchase an air compressor: | F28: =IF(Inputs!$B$169=Inputs!$C$86,Inputs!C96,IF(Inputs!$B$169=Inputs!$G$86,Inputs!G96,IF(Inputs!$B$169=Inputs!$J$86,Inputs!J96,IF(Inputs!$B$169=Inputs!$M$86,Inputs!M96,"na")))) -> 2 | G28: =Inputs!D96 -> 1723.44 | H28: =G28*F28*(1+Inputs!$F$86) -> 5446.5501
C29: Jackhammer | F29: =IF(Inputs!$B$169=Inputs!$C$86,Inputs!C97,IF(Inputs!$B$169=Inputs!$G$86,Inputs!G97,IF(Inputs!$B$169=Inputs!$J$86,Inputs!J97,IF(Inputs!$B$169=Inputs!$M$86,Inputs!M97,"na")))) -> 4 | G29: =Inputs!D97 -> 1417.11 | H29: =G29*F29*(1+Inputs!$F$86) -> 8956.9241
C30: Jackhammer Chisels | F30: =IF(Inputs!$B$169=Inputs!$C$86,Inputs!C98,IF(Inputs!$B$169=Inputs!$G$86,Inputs!G98,IF(Inputs!$B$169=Inputs!$J$86,Inputs!J98,IF(Inputs!$B$169=Inputs!$M$86,Inputs!M98,"na")))) -> 10 | G30: =Inputs!D98 -> 24.35 | H30: =G30*F30*(1+Inputs!$F$86) -> 384.76389
C31: Safety glasses | F31: =IF(Inputs!$B$169=Inputs!$C$86,Inputs!C99,IF(Inputs!$B$169=Inputs!$G$86,Inputs!G99,IF(Inputs!$B$169=Inputs!$J$86,Inputs!J99,IF(Inputs!$B$169=Inputs!$M$86,Inputs!M99,"na")))) -> 15 | G31: =Inputs!D99 -> 8.6 | H31: =G31*F31*(1+Inputs!$F$86) -> 203.83795
... C45: Crane rental for building removal | F45: =IF(Inputs!$B$169=Inputs!$C$86,Inputs!C113,IF(Inputs!$B$169=Inputs!$G$86,Inputs!G113,IF(Inputs!$B$169=Inputs!$J$86,Inputs!J113,IF(Inputs!$B$169=Inputs!$M$86,Inputs!M113,"na")))) -> 1 | G45: =Inputs!D113 -> 15600 | H45: =G45*F45*(1+Inputs!$F$86) -> 24650.171
H46: =SUM(H20:H45) -> 226414.4
C48: Consumables | E48: Quantity | G48: Duration | I48: # workers | J48: quantity | K48: Unit Qty | L48: Unit Cost | M48: Escalated Cost
C49: Coveralls | E49: =IF(Inputs!$B$169=Inputs!$C$86,Inputs!C117,IF(Inputs!$B$169=Inputs!$G$86,Inputs!D117,IF(Inputs!$B$169=Inputs!$J$86,Inputs!E117,IF(Inputs!$B$169=Inputs!$M$86,Inputs!F117,"na")))) -> 2 | F49: /man/day | G49: =Inputs!B$172 -> 180 | H49: days | I49: =Inputs!H$175 -> 24 | J49: =I49*G49*E49 -> 8640 | K49: 1 | L49: =Inputs!H117 -> 11 | M49: =J49/K49*L49*(1+Inputs!$F$86) -> 150176.43
C50: Hoods | E50: =IF(Inputs!$B$169=Inputs!$C$86,Inputs!C118,IF(Inputs!$B$169=Inputs!$G$86,Inputs!D118,IF(Inputs!$B$169=Inputs!$J$86,Inputs!E118,IF(Inputs!$B$169=Inputs!$M$86,Inputs!F118,"na")))) -> 0.1 | F50: /man/day | G50: =Inputs!B$172 -> 180 | H50: days | I50: =Inputs!H$175 -> 24 | J50: =I50*G50*E50 -> 432 | K50: 1 | L50: =Inputs!H118 -> 0 | M50: =J50/K50*L50*(1+Inputs!$F$86) -> 0
C51: Shoe covers | E51: =IF(Inputs!$B$169=Inputs!$C$86,Inputs!C119,IF(Inputs!$B$169=Inputs!$G$86,Inputs!D119,IF(Inputs!$B$169=Inputs!$J$86,Inputs!E119,IF(Inputs!$B$169=Inputs!$M$86,Inputs!F119,"na")))) -> 4 | F51: /man/day | G51: =Inputs!B$172 -> 180 | H51: days | I51: =Inputs!H$175 -> 24 | J51: =I51*G51*E51 -> 17280 | K51: 1 | L51: =Inputs!H119 -> 0.94 | M51: =J51/K51*L51*(1+Inputs!$F$86) -> 25666.517
C52: Latex gloves | E52: =IF(Inputs!$B$169=Inputs!$C$86,Inputs!C120,IF(Inputs!$B$169=Inputs!$G$86,Inputs!D120,IF(Inputs!$B$169=Inputs!$J$86,Inputs!E120,IF(Inputs!$B$169=Inputs!$M$86,Inputs!F120,"na")))) -> 4 | F52: /man/day | G52: =Inputs!B$172 -> 180 | H52: days | I52: =Inputs!H$175 -> 24 | J52: =I52*G52*E52 -> 17280 | K52: 1 | L52: =Inputs!H120 -> 0.94 | M52: =J52/K52*L52*(1+Inputs!$F$86) -> 25666.517
C53: Rubber overshoes | E53: =IF(Inputs!$B$169=Inputs!$C$86,Inputs!C121,IF(Inputs!$B$169=Inputs!$G$86,Inputs!D121,IF(Inputs!$B$169=Inputs!$J$86,Inputs!E121,IF(Inputs!$B$169=Inputs!$M$86,Inputs!F121,"na")))) -> 0.01 | F53: /man/day | G53: =Inputs!B$172 -> 180 | H53: days | I53: =Inputs!H$175 -> 24 | J53: =I53*G53*E53 -> 43.2 | K53: 1 | L53: =Inputs!H121 -> 3 | M53: =J53/K53*L53*(1+Inputs!$F$86) -> 204.78604
C54: Gloves | E54: =IF(Inputs!$B$169=Inputs!$C$86,Inputs!C122,IF(Inputs!$B$169=Inputs!$G$86,Inputs!D122,IF(Inputs!$B$169=Inputs!$J$86,Inputs!E122,IF(Inputs!$B$169=Inputs!$M$86,Inputs!F122,"na")))) -> 0.01 | F54: /man/day | G54: =Inputs!B$172 -> 180 | H54: days | I54: =Inputs!H$175 -> 24 | J54: =I54*G54*E54 -> 43.2 | K54: 1 | L54: =Inputs!H122 -> 2 | M54: =J54/K54*L54*(1+Inputs!$F$86) -> 136.52402
C55: Dosimeters | E55: =IF(Inputs!$B$169=Inputs!$C$86,Inputs!C123,IF(Inputs!$B$169=Inputs!$G$86,Inputs!D123,IF(Inputs!$B$169=Inputs!$J$86,Inputs!E123,IF(Inputs!$B$169=Inputs!$M$86,Inputs!F123,"na")))) -> 1 | F55: /man/year | G55: =1/3 -> 0.33333333 | H55: year | I55: =Inputs!H$175 -> 24 | J55: =I55*G55*E55 -> 8 | K55: 1 | L55: =Inputs!H123 -> 200 | M55: =J55/K55*L55*(1+Inputs!$F$86) -> 2528.2227
C56: TLDs | E56: =IF(Inputs!$B$169=Inputs!$C$86,Inputs!C124,IF(Inputs!$B$169=Inputs!$G$86,Inputs!D124,IF(Inputs!$B$169=Inputs!$J$86,Inputs!E124,IF(Inputs!$B$169=Inputs!$M$86,Inputs!F124,"na")))) -> 1 | F56: /man/mo | G56: 3 | H56: month | I56: =Inputs!H$175 -> 24 | J56: =I56*G56*E56 -> 72 | K56: 1 | L56: =Inputs!H124 -> 3 | M56: =J56/K56*L56*(1+Inputs!$F$86) -> 341.31006
C57: Bioassays | E57: =IF(Inputs!$B$169=Inputs!$C$86,Inputs!C125,IF(Inputs!$B$169=Inputs!$G$86,Inputs!D125,IF(Inputs!$B$169=Inputs!$J$86,Inputs!E125,IF(Inputs!$B$169=Inputs!$M$86,Inputs!F125,"na")))) -> 2 | F57: /man/year | G57: 1 | H57: year | I57: =Inputs!H$175 -> 24 | J57: =I57*G57*E57 -> 48 | K57: 1 | L57: =Inputs!H125 -> 250 | M57: =J57/K57*L57*(1+Inputs!$F$86) -> 18961.67
C58: (Bioassays for aver. crew & management) | M58: =SUM(M49:M57) -> 223681.97
C60: Small Tools - 2% of total labor costs = | G60: =(T6-T8) -> 10540095 | H60: labor costs x | I60: =Inputs!F128 -> 0.02 | J60: = | K60: =I60*G60 -> 210801.91
C62: HP Equipment Replacement - 5% of total labor | G62: =G60 -> 10540095 | H62: labor costs x | I62: =Inputs!F130 -> 0.05 | J62: = | K62: =I62*G62 -> 527004.76
C64: DGC OH &P on equipment and materials | G64: =R68+K62+K60+M58+H46 -> 1187903 | I64: =Inputs!F132 -> 0.08 | J64: = | K64: =I64*G64 -> 95032.243
A66: 1.2 | B66: Project Planning | J66: =J68+J75+J82 -> 415 | L66: =L68+L75+L82 -> 415 | M66: =M68+M75+M82 -> 2925 | T66: =T68+T75+T82 -> 270994.1 | Z66: =SUM(T66:Y66) -> 270994.1
A68: 1.2.1 | B68: Procedure Development and Review | J68: =I73 -> 160 | K68: 1 | L68: =J68*K68 -> 160 | M68: =L73 -> 240 | T68: =K73 -> 22935.2
D70: Staff | G70: Number | H70: Rate | I70: Duration | J70: PLF | K70: Cost | L70: Man-hours
D71: Project Specialist | G71: 2 | H71: =Inputs!E$48 -> 89.25 | I71: 80 | J71: 1 | K71: =G71*H71*I71*J71 -> 14280 | L71: =J71*I71*G71 -> 160
D72: Project Manager | G72: 1 | H72: =Inputs!E$49 -> 108.19 | I72: 80 | J72: 1 | K72: =G72*H72*I72*J72 -> 8655.2 | L72: =J72*I72*G72 -> 80
G73: =SUM(G71:G72) -> 3 | I73: =SUM(I71:I72) -> 160 | K73: =SUM(K71:K72) -> 22935.2 | L73: =SUM(L71:L72) -> 240
A75: 1.2.2 | B75: Preparation of QA and Safety Documents | J75: =I80 -> 160 | K75: 1 | L75: =J75*K75 -> 160 | M75: =L80 -> 240 | T75: =K80 -> 22935.2
D77: Staff | G77: Number | H77: Rate | I77: Duration | J77: PLF | K77: Cost | L77: Man-hours
D78: Project Specialist | G78: 2 | H78: =Inputs!E$48 -> 89.25 | I78: 80 | J78: 1 | K78: =J78*I78*H78*G78 -> 14280 | L78: =J78*I78*G78 -> 160
D79: Project Manager | G79: 1 | H79: =Inputs!E$49 -> 108.19 | I79: 80 | J79: 1 | K79: =J79*I79*H79*G79 -> 8655.2 | L79: =J79*I79*G79 -> 80
G80: =SUM(G78:G79) -> 3 | I80: =SUM(I78:I79) -> 160 | K80: =SUM(K78:K79) -> 22935.2 | L80: =SUM(L78:L79) -> 240
A82: 1.2.3 | B82: Site Mobilization and General Employee Training (GET) | J82: =J84+J97 -> 95 | K82: 1 | L82: =J82*K82 -> 95 | M82: =M84+M97 -> 2445 | T82: =T84+T97 -> 225123.7
C84: 1.2.3.1 | D84: Site Mobilization | J84: =F95 -> 40 | K84: 1 | L84: =J84*K84 -> 40 | M84: =J84*D87 -> 960 | T84: =I95 -> 85680
D86: Crew | G86: Rate, $/hr | H86: Cost, $/hr
D87: =I49 -> 24 | E87: Decom Technician / Safety SME | G87: =Inputs!E48 -> 89.25 | H87: =G87*D87 -> 2142
D89: Receipt of material and equipment | G89: 16 | H89: hr
D90: Staging of equipment | G90: 8 | H90: hr
D91: Set up office and amenities | G91: 12 | H91: hr
D92: Familiarize staff with facility | G92: 4 | H92: hr
G93: =SUM(G89:G92) -> 40 | H93: hr
D95: Total Cost = | F95: =G93 -> 40 | G95: x | H95: =H87 -> 2142 | I95: =H95*F95 -> 85680
C97: 1.2.3.2 | D97: General Employee Training (All proj. management and 3 crews of 4) | J97: =F116 -> 55 | K97: 1 | L97: =K97*J97 -> 55 | M97: =D104*F116 -> 1485 | S97: =J116*Inputs!C37 -> 54054 | T97: =K116 -> 139443.7
D99: Crew | G99: Rate, $/hr | H99: Cost, $/hr
D100: 1 | E100: =B11 -> Portfolio Manager | G100: =F11 -> 157.87 | H100: =G100*D100 -> 157.87
D101: 1 | E101: =B12 -> Senior Project Manager / Characterization SME | G101: =F12 -> 127.28 | H101: =G101*D101 -> 127.28
D102: 1 | E102: =B13 -> Project Manager / Waste Management | G102: =F13 -> 108.19 | H102: =G102*D102 -> 108.19
D103: =I49 -> 24 | E103: =B14 -> Decom Technician / Safety SME | G103: =F14 -> 89.25 | H103: =G103*D103 -> 2142
D104: =SUM(D100:D103) -> 27 | H104: =SUM(H100:H103) -> 2535.34
I106: Number | J106: Test | K106: Labor | L106: Total
H107: Unit Cost | I107: Required | J107: Cost | K107: Costs | L107: Cost
D108: In-Vivo | H108: 600 | I108: =D$104 -> 27 | J108: =I108*H108 -> 16200 | K108: =F108*H$104 -> 0 | L108: =K108+J108 -> 16200
D109: In-Vitro | H109: 350 | I109: =D$104 -> 27 | J109: =I109*H109 -> 9450 | K109: =F109*H$104 -> 0 | L109: =K109+J109 -> 9450
D110: Physical @ | F110: 4 | G110: hour and | H110: 150 | I110: =D$104 -> 27 | J110: =I110*H110 -> 4050 | K110: =F110*H$104 -> 10141.36 | L110: =K110+J110 -> 14191.36
D111: Resp. Tests | F111: 1 | G111: hour and | H111: 50 | I111: =D$104 -> 27 | J111: =I111*H111 -> 1350 | K111: =F111*H$104 -> 2535.34 | L111: =K111+J111 -> 3885.34
D112: Resp Fit Tests | F112: 1 | G112: hour and | H112: 25 | I112: =D$104 -> 27 | J112: =I112*H112 -> 675 | K112: =F112*H$104 -> 2535.34 | L112: =K112+J112 -> 3210.34
D113: Blood Tests | F113: 1 | G113: hour and | H113: 125 | I113: =D$104 -> 27 | J113: =I113*H113 -> 3375 | K113: =F113*H$104 -> 2535.34 | L113: =K113+J113 -> 5910.34
D114: OSHA recertification | F114: 8 | G114: hour | K114: =F114*H$104 -> 20282.72 | L114: =K114+J114 -> 20282.72
D115: Site specific 1 week of training | F115: 40 | G115: hour | K115: =F115*H$104 -> 101413.6 | L115: =K115+J115 -> 101413.6
F116: =SUM(F110:F115) -> 55 | J116: =SUM(J108:J115) -> 35100 | K116: =SUM(K110:K115) -> 139443.7 | L116: =SUM(L108:L115) -> 174543.7
A118: 1.3 | B118: Preliminary Site Investigation | J118: =J120+J122 -> 176 | L118: =L120+L122 -> 176 | M118: =M120+M122 -> 480 | T118: =T120+T122 -> 44658.24 | Z118: =SUM(T118:Y118) -> 44658.24
A120: 1.3.1 | B120: Decontamination Readiness Review - (Contractor staff cost included in Undistributed Costs) | J120: 80 | K120: 1 | L120: =K120*J120 -> 80
A122: 1.3.2 | B122: Site Preparation | H122: A | J122: =J124+J133+J151+J159 -> 96 | K122: 1 | L122: =L124+L133+L151+L159 -> 96 | M122: =M124+M133+M151+M159 -> 480 | T122: =T124+T133+T151+T159 -> 44658.24
B124: 1.3.2.1 | C124: Initial Site Survey | H124: A | J124: =F126 -> 16 | K124: 1 | L124: =K124*J124 -> 16 | M124: =L130 -> 80 | T124: =K130 -> 7443.04
E126: Estimated Duration | F126: 16 | G126: hrs
D127: Staff | G127: Number | H127: Rate | I127: Duration | J127: PLF | K127: Cost | L127: Man-hours
D128: Project Specialist | G128: 4 | H128: =Inputs!E$48 -> 89.25 | I128: =F126 -> 16 | J128: 1 | K128: =J128*I128*H128*G128 -> 5712 | L128: =J128*I128*G128 -> 64
D129: Project Manager | G129: 1 | H129: =Inputs!E$49 -> 108.19 | I129: =F126 -> 16 | J129: 1 | K129: =J129*I129*H129*G129 -> 1731.04 | L129: =J129*I129*G129 -> 16
G130: =SUM(G128:G129) -> 5 | I130: =SUM(I128:I129) -> 32 | K130: =SUM(K128:K129) -> 7443.04 | L130: =SUM(L128:L129) -> 80
B133: 1.3.2.2 | C133: Setup work areas | J133: =J135+J143 -> 32 | L133: =L135+L143 -> 32 | M133: =M135+M143 -> 160 | T133: =T135+T143 -> 14886.08
B135: 1.3.2.2.1 | C135: Setup boundaries, install HEPA filters & seal off openings | H135: A | J135: =F137 -> 16 | K135: 1 | L135: =K135*J135 -> 16 | M135: =L141 -> 80 | T135: =K141 -> 7443.04
E137: Estimated Duration | F137: 16 | G137: hrs
D138: Staff | G138: Number | H138: Rate | I138: Duration | J138: PLF | K138: Cost | L138: Man-hours
D139: Project Specialist | G139: 4 | H139: =Inputs!E$48 -> 89.25 | I139: =F137 -> 16 | J139: 1 | K139: =J139*I139*H139*G139 -> 5712 | L139: =J139*I139*G139 -> 64
D140: Project Manager | G140: 1 | H140: =Inputs!E$49 -> 108.19 | I140: =F137 -> 16 | J140: 1 | K140: =J140*I140*H140*G140 -> 1731.04 | L140: =J140*I140*G140 -> 16
G141: =SUM(G139:G140) -> 5 | I141: =SUM(I139:I140) -> 32 | K141: =SUM(K139:K140) -> 7443.04 | L141: =SUM(L139:L140) -> 80
B143: 1.3.2.2.2 | C143: Establish staging area | H143: A | J143: =F145 -> 16 | K143: 1 | L143: =K143*J143 -> 16 | M143: =L149 -> 80 | T143: =K149 -> 7443.04
E145: Estimated Duration | F145: 16 | G145: hrs
D146: Staff | G146: Number | H146: Rate | I146: Duration | J146: PLF | K146: Cost | L146: Man-hours
...

Sheet Building B18
A1: B 18 DATA - Data highlighted in GREEN can be adjusted as needed
J2: Uncorrected Duration
I3: Crew | J3: (No. of Hours) | K3: Prod. Factor | L3: Adjusted Duration (hrs) | M3: Man-hours | N3: LSA Waste Disp. Vol (cm) | O3: Hazardous Waste Vol (cm) | Q3: Mixed Waste Volume (cm) | R3: Clean Waste Volume (cm) | S3: Materials, Consumables & Equipment | T3: Labor Cost | U3: LSA Waste Costs | V3: Hazardous Waste Costs | W3: LSA Waste Costs | X3: Mixed Waste Costs | Y3: Clean Waste Costs | Z3: Total Cost
A6: 1.0 | B6: Building B18 | L6: =L8+L66+L118+L177+L185+L205 -> 663 | M6: =M8+M66+M118+M177+M185+M205 -> 5465 | N6: =N8+N66+N118+N177+N185+N205 -> 3450 | O6: =O8+O66+O118+O177+O185+O205 -> 0 | Q6: =Q8+Q66+Q118+Q177+Q185+Q205 -> 0 | R6: =R8+R66+R118+R177+R185+R205 -> 3450 | S6: =S8+S66+S118+S177+S185+S205+S211 -> 461768.17 | T6: =T8+T66+T118+T177+T185+T205+T211 -> 2851597.5 | V6: =V8+V66+V118+V177+V185+V205+V211 -> 0 | Y6: =Y8+Y66+Y118+Y177+Y185+Y205+Y211 -> 1827537 | Z6: =SUM(S6:Y6) -> 5140902.6
A8: 1.1 | B8: Project Management | S8: =IF(G18="US",(H46+M58+K60+K62+K64)*Inputs!C37,(H46+M58+K60+K62+K64)) -> 461768.17 | T8: =I15 -> 134378.1 | Z8: =SUM(S8:Y8) -> 596146.27
A10: 1.1.1 | B10: Staff | E10: Number | F10: Rate | G10: Duration, days* | H10: Use Factor | I10: Cost | J10: Man-hours
B11: =Inputs!A$51 -> Portfolio Manager | E11: 1 | F11: =Inputs!E51 -> 157.87 | G11: =Inputs!B$161 -> 90 | H11: 0.25 | I11: =H11*G11*F11*E11*8 -> 28416.6 | J11: =H11*G11*10 -> 225
B12: =Inputs!A$50 -> Senior Project Manager / Characterization SME | E12: 1 | F12: =Inputs!E50 -> 127.28 | G12: =Inputs!B$161 -> 90 | H12: 0.5 | I12: =H12*G12*F12*E12*10 -> 57276 | J12: =H12*G12*10 -> 450
B13: =Inputs!A$49 -> Project Manager / Waste Management | E13: 1 | F13: =Inputs!E49 -> 108.19 | G13: =Inputs!B$161 -> 90 | H13: 0.5 | I13: =H13*G13*F13*E13*10 -> 48685.5 | J13: =H13*G13*10 -> 450
B14: =Inputs!A$48 -> Decom Technician / Safety SME | E14: 0 | F14: =Inputs!E48 -> 89.25 | G14: =Inputs!B$161 -> 90 | H14: 1 | I14: =H14*G14*F14*E14*10 -> 0 | J14: =H14*G14*10 -> 900
E15: =SUM(E11:E14) -> 3 | I15: =SUM(I11:I14) -> 134378.1 | J15: =SUM(J11:J14) -> 2025
A17: 1.1.2 | B17: Equipment & Materials
G18: =Inputs!D85 -> US
C19: Equipment | F19: Quantity | G19: Rate | H19: Escalated Cost
C20: HEPA filter systems | F20: =IF(Inputs!$B$150=Inputs!$C$86,Inputs!C88,IF(Inputs!$B$150=Inputs!$G$86,Inputs!G88,IF(Inputs!$B$150=Inputs!$J$86,Inputs!J88,IF(Inputs!$B$150=Inputs!$M$86,Inputs!M88,"na")))) -> 0 | G20: =Inputs!D88 -> 3598.14 | H20: =G20*F20*(1+Inputs!$F$86) -> 0
C21: Replacement filters | F21: =IF(Inputs!$B$150=Inputs!$C$86,Inputs!C89,IF(Inputs!$B$150=Inputs!$G$86,Inputs!G89,IF(Inputs!$B$150=Inputs!$J$86,Inputs!J89,IF(Inputs!$B$150=Inputs!$M$86,Inputs!M89,"na")))) -> 0 | G21: =Inputs!D89 -> 581.07 | H21: =G21*F21*(1+Inputs!$F$86) -> 0
C22: Respirator | F22: =IF(Inputs!$B$150=Inputs!$C$86,Inputs!C90,IF(Inputs!$B$150=Inputs!$G$86,Inputs!G90,IF(Inputs!$B$150=Inputs!$J$86,Inputs!J90,IF(Inputs!$B$150=Inputs!$M$86,Inputs!M90,"na")))) -> 0 | G22: =Inputs!D90 -> 259 | H22: =G22*F22*(1+Inputs!$F$86) -> 0
C23: Rad/Vac wet-dry high eff. vacuum | F23: =IF(Inputs!$B$150=Inputs!$C$86,Inputs!C91,IF(Inputs!$B$150=Inputs!$G$86,Inputs!G91,IF(Inputs!$B$150=Inputs!$J$86,Inputs!J91,IF(Inputs!$B$150=Inputs!$M$86,Inputs!M91,"na")))) -> 0 | G23: =Inputs!D91 -> 3879 | H23: =G23*F23*(1+Inputs!$F$86) -> 0
C24: Rad/Vac wet-dry high eff. vacuum filters | F24: =IF(Inputs!$B$150=Inputs!$C$86,Inputs!C92,IF(Inputs!$B$150=Inputs!$G$86,Inputs!G92,IF(Inputs!$B$150=Inputs!$J$86,Inputs!J92,IF(Inputs!$B$150=Inputs!$M$86,Inputs!M92,"na")))) -> 0 | G24: =Inputs!D92 -> 412 | H24: =G24*F24*(1+Inputs!$F$86) -> 0
C25: Reciprocating Saws | F25: =IF(Inputs!$B$150=Inputs!$C$86,Inputs!C93,IF(Inputs!$B$150=Inputs!$G$86,Inputs!G93,IF(Inputs!$B$150=Inputs!$J$86,Inputs!J93,IF(Inputs!$B$150=Inputs!$M$86,Inputs!M93,"na")))) -> 0 | G25: =Inputs!D93 -> 1252.26 | H25: =G25*F25*(1+Inputs!$F$86) -> 0
C26: Pneumatic chipping hammers | F26: =IF(Inputs!$B$150=Inputs!$C$86,Inputs!C94,IF(Inputs!$B$150=Inputs!$G$86,Inputs!G94,IF(Inputs!$B$150=Inputs!$J$86,Inputs!J94,IF(Inputs!$B$150=Inputs!$M$86,Inputs!M94,"na")))) -> 2 | G26: =Inputs!D94 -> 1606.71 | H26: =G26*F26*(1+Inputs!$F$86) -> 5077.6508
C27: Chipping hammer blades | F27: =IF(Inputs!$B$150=Inputs!$C$86,Inputs!C95,IF(Inputs!$B$150=Inputs!$G$86,Inputs!G95,IF(Inputs!$B$150=Inputs!$J$86,Inputs!J95,IF(Inputs!$B$150=Inputs!$M$86,Inputs!M95,"na")))) -> 20 | G27: =Inputs!D95 -> 27.42 | H27: =G27*F27*(1+Inputs!$F$86) -> 866.54832
C28: Purchase an air compressor: | F28: =IF(Inputs!$B$150=Inputs!$C$86,Inputs!C96,IF(Inputs!$B$150=Inputs!$G$86,Inputs!G96,IF(Inputs!$B$150=Inputs!$J$86,Inputs!J96,IF(Inputs!$B$150=Inputs!$M$86,Inputs!M96,"na")))) -> 2 | G28: =Inputs!D96 -> 1723.44 | H28: =G28*F28*(1+Inputs!$F$86) -> 5446.5501
C29: Jackhammer | F29: =IF(Inputs!$B$150=Inputs!$C$86,Inputs!C97,IF(Inputs!$B$150=Inputs!$G$86,Inputs!G97,IF(Inputs!$B$150=Inputs!$J$86,Inputs!J97,IF(Inputs!$B$150=Inputs!$M$86,Inputs!M97,"na")))) -> 4 | G29: =Inputs!D97 -> 1417.11 | H29: =G29*F29*(1+Inputs!$F$86) -> 8956.9241
C30: Jackhammer Chisels | F30: =IF(Inputs!$B$150=Inputs!$C$86,Inputs!C98,IF(Inputs!$B$150=Inputs!$G$86,Inputs!G98,IF(Inputs!$B$150=Inputs!$J$86,Inputs!J98,IF(Inputs!$B$150=Inputs!$M$86,Inputs!M98,"na")))) -> 10 | G30: =Inputs!D98 -> 24.35 | H30: =G30*F30*(1+Inputs!$F$86) -> 384.76389
C31: Safety glasses | F31: =IF(Inputs!$B$150=Inputs!$C$86,Inputs!C99,IF(Inputs!$B$150=Inputs!$G$86,Inputs!G99,IF(Inputs!$B$150=Inputs!$J$86,Inputs!J99,IF(Inputs!$B$150=Inputs!$M$86,Inputs!M99,"na")))) -> 15 | G31: =Inputs!D99 -> 8.6 | H31: =G31*F31*(1+Inputs!$F$86) -> 203.83795
... C45: Crane rental for building removal | F45: =IF(Inputs!$B$150=Inputs!$C$86,Inputs!C113,IF(Inputs!$B$150=Inputs!$G$86,Inputs!G113,IF(Inputs!$B$150=Inputs!$J$86,Inputs!J113,IF(Inputs!$B$150=Inputs!$M$86,Inputs!M113,"na")))) -> 0 | G45: =Inputs!D113 -> 15600 | H45: =G45*F45*(1+Inputs!$F$86) -> 0
H46: =SUM(H20:H45) -> 87433.033
C48: Consumables | E48: Quantity | G48: Duration | I48: # workers | J48: quantity | K48: Unit Qty | L48: Unit Cost | M48: Escalated Cost
C49: Coveralls | E49: =IF(Inputs!$B$150=Inputs!$C$86,Inputs!C117,IF(Inputs!$B$150=Inputs!$G$86,Inputs!D117,IF(Inputs!$B$150=Inputs!$J$86,Inputs!E117,IF(Inputs!$B$150=Inputs!$M$86,Inputs!F117,"na")))) -> 0 | F49: /man/day | G49: =Inputs!B$161 -> 90 | H49: days | I49: =Inputs!F$166 -> 12 | J49: =I49*G49*E49 -> 0 | K49: 1 | L49: =Inputs!H117 -> 11 | M49: =J49/K49*L49*(1+Inputs!$F$86) -> 0
C50: Hoods | E50: =IF(Inputs!$B$150=Inputs!$C$86,Inputs!C118,IF(Inputs!$B$150=Inputs!$G$86,Inputs!D118,IF(Inputs!$B$150=Inputs!$J$86,Inputs!E118,IF(Inputs!$B$150=Inputs!$M$86,Inputs!F118,"na")))) -> 0 | F50: /man/day | G50: =Inputs!B$161 -> 90 | H50: days | I50: =Inputs!F$166 -> 12 | J50: =I50*G50*E50 -> 0 | K50: 1 | L50: =Inputs!H118 -> 0 | M50: =J50/K50*L50*(1+Inputs!$F$86) -> 0
C51: Shoe covers | E51: =IF(Inputs!$B$150=Inputs!$C$86,Inputs!C119,IF(Inputs!$B$150=Inputs!$G$86,Inputs!D119,IF(Inputs!$B$150=Inputs!$J$86,Inputs!E119,IF(Inputs!$B$150=Inputs!$M$86,Inputs!F119,"na")))) -> 0 | F51: /man/day | G51: =Inputs!B$161 -> 90 | H51: days | I51: =Inputs!F$166 -> 12 | J51: =I51*G51*E51 -> 0 | K51: 1 | L51: =Inputs!H119 -> 0.94 | M51: =J51/K51*L51*(1+Inputs!$F$86) -> 0
C52: Latex gloves | E52: =IF(Inputs!$B$150=Inputs!$C$86,Inputs!C120,IF(Inputs!$B$150=Inputs!$G$86,Inputs!D120,IF(Inputs!$B$150=Inputs!$J$86,Inputs!E120,IF(Inputs!$B$150=Inputs!$M$86,Inputs!F120,"na")))) -> 0 | F52: /man/day | G52: =Inputs!B$161 -> 90 | H52: days | I52: =Inputs!F$166 -> 12 | J52: =I52*G52*E52 -> 0 | K52: 1 | L52: =Inputs!H120 -> 0.94 | M52: =J52/K52*L52*(1+Inputs!$F$86) -> 0
C53: Rubber overshoes | E53: =IF(Inputs!$B$150=Inputs!$C$86,Inputs!C121,IF(Inputs!$B$150=Inputs!$G$86,Inputs!D121,IF(Inputs!$B$150=Inputs!$J$86,Inputs!E121,IF(Inputs!$B$150=Inputs!$M$86,Inputs!F121,"na")))) -> 0 | F53: /man/day | G53: =Inputs!B$161 -> 90 | H53: days | I53: =Inputs!F$166 -> 12 | J53: =I53*G53*E53 -> 0 | K53: 1 | L53: =Inputs!H121 -> 3 | M53: =J53/K53*L53*(1+Inputs!$F$86) -> 0
C54: Gloves | E54: =IF(Inputs!$B$150=Inputs!$C$86,Inputs!C122,IF(Inputs!$B$150=Inputs!$G$86,Inputs!D122,IF(Inputs!$B$150=Inputs!$J$86,Inputs!E122,IF(Inputs!$B$150=Inputs!$M$86,Inputs!F122,"na")))) -> 0 | F54: /man/day | G54: =Inputs!B$161 -> 90 | H54: days | I54: =Inputs!F$166 -> 12 | J54: =I54*G54*E54 -> 0 | K54: 1 | L54: =Inputs!H122 -> 2 | M54: =J54/K54*L54*(1+Inputs!$F$86) -> 0
C55: Dosimeters | E55: =IF(Inputs!$B$150=Inputs!$C$86,Inputs!C123,IF(Inputs!$B$150=Inputs!$G$86,Inputs!D123,IF(Inputs!$B$150=Inputs!$J$86,Inputs!E123,IF(Inputs!$B$150=Inputs!$M$86,Inputs!F123,"na")))) -> 0 | F55: /man/year | G55: 0.25 | H55: year | I55: =Inputs!F$166 -> 12 | J55: =I55*G55*E55 -> 0 | K55: 1 | L55: =Inputs!H123 -> 200 | M55: =J55/K55*L55*(1+Inputs!$F$86) -> 0
C56: TLDs | E56: =IF(Inputs!$B$150=Inputs!$C$86,Inputs!C124,IF(Inputs!$B$150=Inputs!$G$86,Inputs!D124,IF(Inputs!$B$150=Inputs!$J$86,Inputs!E124,IF(Inputs!$B$150=Inputs!$M$86,Inputs!F124,"na")))) -> 0 | F56: /man/mo | G56: 3 | H56: month | I56: =Inputs!F$166 -> 12 | J56: =I56*G56*E56 -> 0 | K56: 1 | L56: =Inputs!H124 -> 3 | M56: =J56/K56*L56*(1+Inputs!$F$86) -> 0
C57: Bioassays | E57: =IF(Inputs!$B$150=Inputs!$C$86,Inputs!C125,IF(Inputs!$B$150=Inputs!$G$86,Inputs!D125,IF(Inputs!$B$150=Inputs!$J$86,Inputs!E125,IF(Inputs!$B$150=Inputs!$M$86,Inputs!F125,"na")))) -> 0 | F57: /man/year | G57: 0.25 | H57: year | I57: =Inputs!F$166 -> 12 | J57: =I57*G57*E57 -> 0 | K57: 1 | L57: =Inputs!H125 -> 250 | M57: =J57/K57*L57*(1+Inputs!$F$86) -> 0
C58: (Bioassays for aver. crew & management) | M58: =SUM(M49:M57) -> 0
C60: Small Tools - 2% of total labor costs = | G60: =(T6-T8) -> 2717219.4 | H60: labor costs x | I60: =Inputs!F128 -> 0.02 | J60: = | K60: =I60*G60 -> 54344.387
C62: HP Equipment Replacement - 5% of total labor | G62: =G60 -> 2717219.4 | H62: labor costs x | I62: =Inputs!F130 -> 0.05 | J62: = | K62: =I62*G62 -> 135860.97
C64: DGC OH &P on equipment and materials | G64: =R68+K62+K60+M58+H46 -> 277638.39 | I64: =Inputs!F132 -> 0.08 | J64: = | K64: =I64*G64 -> 22211.071
A66: 1.2 | B66: Project Planning | J66: =J68+J75+J82 -> 415 | L66: =L68+L75+L82 -> 447 | M66: =M68+M75+M82 -> 1785 | T66: =T68+T75+T82 -> 169249.1 | Z66: =SUM(T66:Y66) -> 169249.1
A68: 1.2.1 | B68: Procedure Development and Review | J68: =I73 -> 160 | K68: 1.1 | L68: =J68*K68 -> 176 | M68: =L73 -> 240 | T68: =K73 -> 22935.2
D70: Staff | G70: Number | H70: Rate | I70: Duration | J70: PLF | K70: Cost | L70: Man-hours
D71: Project Specialist | G71: 2 | H71: =Inputs!E$48 -> 89.25 | I71: 80 | J71: 1 | K71: =G71*H71*I71*J71 -> 14280 | L71: =J71*I71*G71 -> 160
D72: Project Manager | G72: 1 | H72: =Inputs!E$49 -> 108.19 | I72: 80 | J72: 1 | K72: =G72*H72*I72*J72 -> 8655.2 | L72: =J72*I72*G72 -> 80
G73: =SUM(G71:G72) -> 3 | I73: =SUM(I71:I72) -> 160 | K73: =SUM(K71:K72) -> 22935.2 | L73: =SUM(L71:L72) -> 240
A75: 1.2.2 | B75: Preparation of QA and Safety Documents | J75: =I80 -> 160 | K75: 1.1 | L75: =J75*K75 -> 176 | M75: =L80 -> 240 | R75: =T68+T75+T82 -> 169249.1 | T75: =K80 -> 22935.2
D77: Staff | G77: Number | H77: Rate | I77: Duration | J77: PLF | K77: Cost | L77: Man-hours
D78: Project Specialist | G78: 2 | H78: =Inputs!E$48 -> 89.25 | I78: 80 | J78: 1 | K78: =J78*I78*H78*G78 -> 14280 | L78: =J78*I78*G78 -> 160
D79: Project Manager | G79: 1 | H79: =Inputs!E$49 -> 108.19 | I79: 80 | J79: 1 | K79: =J79*I79*H79*G79 -> 8655.2 | L79: =J79*I79*G79 -> 80
G80: =SUM(G78:G79) -> 3 | I80: =SUM(I78:I79) -> 160 | K80: =SUM(K78:K79) -> 22935.2 | L80: =SUM(L78:L79) -> 240
A82: 1.2.3 | B82: Site Mobilization and General Employee Training (GET) | J82: =J84+J97 -> 95 | K82: 1 | L82: =J82*K82 -> 95 | M82: =M84+M97 -> 1305 | T82: =T84+T97 -> 123378.7
C84: 1.2.3.1 | D84: Site Mobilization | J84: =F95 -> 40 | K84: 1 | L84: =J84*K84 -> 40 | M84: =J84*D87 -> 480 | T84: =I95 -> 42840
D86: Crew | G86: Rate, $/hr | H86: Cost, $/hr
D87: 12 | E87: Decom Technician / Safety SME | G87: =Inputs!E48 -> 89.25 | H87: =G87*D87 -> 1071
D89: Receipt of material and equipment | G89: 16 | H89: hr
D90: Staging of equipment | G90: 8 | H90: hr
D91: Set up office and amenities | G91: 12 | H91: hr
D92: Familiarize staff with facility | G92: 4 | H92: hr
G93: =SUM(G89:G92) -> 40 | H93: hr
D95: Total Cost = | F95: =G93 -> 40 | G95: x | H95: =H87 -> 1071 | I95: =H95*F95 -> 42840
C97: 1.2.3.2 | D97: General Employee Training (All proj. management and 3 crews of 4) | J97: =F116 -> 55 | K97: 1 | L97: =K97*J97 -> 55 | M97: =D104*F116 -> 825 | S97: =J116*Inputs!C37 -> 30030 | T97: =K116 -> 80538.7
D99: Crew | G99: Rate, $/hr | H99: Cost, $/hr
D100: 1 | E100: =B11 -> Portfolio Manager | G100: =F11 -> 157.87 | H100: =G100*D100 -> 157.87
D101: 1 | E101: =B12 -> Senior Project Manager / Characterization SME | G101: =F12 -> 127.28 | H101: =G101*D101 -> 127.28
D102: 1 | E102: =B13 -> Project Manager / Waste Management | G102: =F13 -> 108.19 | H102: =G102*D102 -> 108.19
D103: 12 | E103: =B14 -> Decom Technician / Safety SME | G103: =F14 -> 89.25 | H103: =G103*D103 -> 1071
D104: =SUM(D100:D103) -> 15 | H104: =SUM(H100:H103) -> 1464.34
I106: Number | J106: Test | K106: Labor | L106: Total
H107: Unit Cost | I107: Required | J107: Cost | K107: Costs | L107: Cost
D108: In-Vivo | H108: 600 | I108: =D$104 -> 15 | J108: =I108*H108 -> 9000 | K108: =F108*H$104 -> 0 | L108: =K108+J108 -> 9000
D109: In-Vitro | H109: 350 | I109: =D$104 -> 15 | J109: =I109*H109 -> 5250 | K109: =F109*H$104 -> 0 | L109: =K109+J109 -> 5250
D110: Physical @ | F110: 4 | G110: hour and | H110: 150 | I110: =D$104 -> 15 | J110: =I110*H110 -> 2250 | K110: =F110*H$104 -> 5857.36 | L110: =K110+J110 -> 8107.36
D111: Resp. Tests | F111: 1 | G111: hour and | H111: 50 | I111: =D$104 -> 15 | J111: =I111*H111 -> 750 | K111: =F111*H$104 -> 1464.34 | L111: =K111+J111 -> 2214.34
D112: Resp Fit Tests | F112: 1 | G112: hour and | H112: 25 | I112: =D$104 -> 15 | J112: =I112*H112 -> 375 | K112: =F112*H$104 -> 1464.34 | L112: =K112+J112 -> 1839.34
D113: Blood Tests | F113: 1 | G113: hour and | H113: 125 | I113: =D$104 -> 15 | J113: =I113*H113 -> 1875 | K113: =F113*H$104 -> 1464.34 | L113: =K113+J113 -> 3339.34
D114: OSHA recertification | F114: 8 | G114: hour | K114: =F114*H$104 -> 11714.72 | L114: =K114+J114 -> 11714.72
D115: Site specific 1 week of training | F115: 40 | G115: hour | K115: =F115*H$104 -> 58573.6 | L115: =K115+J115 -> 58573.6
F116: =SUM(F110:F115) -> 55 | J116: =SUM(J108:J115) -> 19500 | K116: =SUM(K110:K115) -> 80538.7 | L116: =SUM(L108:L115) -> 100038.7
A118: 1.3 | B118: Preliminary Site Investigation | J118: =J120+J122 -> 176 | L118: =L120+L122 -> 176 | M118: =M120+M122 -> 480 | T118: =T120+T122 -> 44658.24 | Z118: =SUM(T118:Y118) -> 44658.24
A120: 1.3.1 | B120: Decontamination Readiness Review - (Contractor staff cost included in Undistributed Costs) | J120: 80 | K120: 1 | L120: =K120*J120 -> 80
A122: 1.3.2 | B122: Site Preparation | H122: A | J122: =J124+J133+J151+J159 -> 96 | K122: 1 | L122: =L124+L133+L151+L159 -> 96 | M122: =M124+M133+M151+M159 -> 480 | T122: =T124+T133+T151+T159 -> 44658.24
B124: 1.3.2.1 | C124: Initial Site Survey | H124: A | J124: =F126 -> 16 | K124: 1 | L124: =K124*J124 -> 16 | M124: =L130 -> 80 | T124: =K130 -> 7443.04
E126: Estimated Duration | F126: 16 | G126: hrs
D127: Staff | G127: Number | H127: Rate | I127: Duration | J127: PLF | K127: Cost | L127: Man-hours
D128: Project Specialist | G128: 4 | H128: =Inputs!E$48 -> 89.25 | I128: =F126 -> 16 | J128: 1 | K128: =J128*I128*H128*G128 -> 5712 | L128: =J128*I128*G128 -> 64
D129: Project Manager | G129: 1 | H129: =Inputs!E$49 -> 108.19 | I129: =F126 -> 16 | J129: 1 | K129: =J129*I129*H129*G129 -> 1731.04 | L129: =J129*I129*G129 -> 16
G130: =SUM(G128:G129) -> 5 | I130: =SUM(I128:I129) -> 32 | K130: =SUM(K128:K129) -> 7443.04 | L130: =SUM(L128:L129) -> 80
B133: 1.3.2.2 | C133: Setup work areas | J133: =J135+J143 -> 32 | L133: =L135+L143 -> 32 | M133: =M135+M143 -> 160 | T133: =T135+T143 -> 14886.08
B135: 1.3.2.2.1 | C135: Setup boundaries, install HEPA filters & seal off openings | H135: A | J135: =F137 -> 16 | K135: 1 | L135: =K135*J135 -> 16 | M135: =L141 -> 80 | T135: =K141 -> 7443.04
E137: Estimated Duration | F137: 16 | G137: hrs
D138: Staff | G138: Number | H138: Rate | I138: Duration | J138: PLF | K138: Cost | L138: Man-hours
D139: Project Specialist | G139: 4 | H139: =Inputs!E$48 -> 89.25 | I139: =F137 -> 16 | J139: 1 | K139: =J139*I139*H139*G139 -> 5712 | L139: =J139*I139*G139 -> 64
D140: Project Manager | G140: 1 | H140: =Inputs!E$49 -> 108.19 | I140: =F137 -> 16 | J140: 1 | K140: =J140*I140*H140*G140 -> 1731.04 | L140: =J140*I140*G140 -> 16
G141: =SUM(G139:G140) -> 5 | I141: =SUM(I139:I140) -> 32 | K141: =SUM(K139:K140) -> 7443.04 | L141: =SUM(L139:L140) -> 80
B143: 1.3.2.2.2 | C143: Establish staging area | H143: A | J143: =F145 -> 16 | K143: 1 | L143: =K143*J143 -> 16 | M143: =L149 -> 80 | T143: =K149 -> 7443.04
E145: Estimated Duration | F145: 16 | G145: hrs
D146: Staff | G146: Number | H146: Rate | I146: Duration | J146: PLF | K146: Cost | L146: Man-hours
...

Sheet Building B56
A1: B 56 DATA - Data highlighted in GREEN can be adjusted as needed
J2: Uncorrected Duration
I3: Crew | J3: (No. of Hours) | K3: Prod. Factor | L3: Adjusted Duration (hrs) | M3: Man-hours | N3: LSA Waste Disp. Vol (cm) | O3: Hazardous Waste Vol (cm) | Q3: Mixed Waste Volume (cm) | R3: Clean Waste Volume (cm) | S3: Materials, Consumables & Equipment | T3: Labor Cost | U3: LSA Waste Costs | V3: Hazardous Waste Costs | W3: LSA Waste Costs | X3: Mixed Waste Costs | Y3: Clean Waste Costs | Z3: Total Cost
A6: 1.0 | B6: Building B56 | L6: =L8+L66+L118+L177+L185+L207 -> 647 | M6: =M8+M66+M118+M177+M185+M207 -> 6605 | N6: =N8+N66+N118+N177+N185+N207 -> 39.256953 | O6: =O8+O66+O118+O177+O185+O207 -> 425.0234 | Q6: =Q8+Q66+Q118+Q177+Q185+Q207 -> 4.4867312 | R6: =R8+R66+R118+R177+R185+R207 -> 1734.4379 | S6: =S8+S66+S118+S177+S185+S207+S214 -> 1843800 | T6: =T8+T66+T118+T177+T185+T207+T214 -> 11009187 | V6: =V8+V66+V118+V177+V185+V207+V214 -> 375239.61 | X6: =X8+X66+X118+X177+X185+X207+X214 -> 3961.1919 | Y6: =Y8+Y66+Y118+Y177+Y185+Y207+Y214 -> 918767.96 | Z6: =SUM(S6:Y6) -> 14150956
A8: 1.1 | B8: Project Management | S8: =IF(G18="US",(H46+M58+K60+K62+K64)*Inputs!C37,(H46+M58+K60+K62+K64)) -> 1843800 | T8: =I15 -> 256232.55 | Z8: =SUM(S8:Y8) -> 2100032.5
A10: 1.1.1 | B10: Staff | E10: Number | F10: Rate | G10: Duration, days* | H10: Use Factor | I10: Cost | J10: Man-hours
B11: =Inputs!A$51 -> Portfolio Manager | E11: 1 | F11: =Inputs!E51 -> 157.87 | G11: =Inputs!G$209 -> 105 | H11: 1 | I11: =H11*G11*F11*E11*8 -> 132610.8 | J11: =H11*G11*10 -> 1050
B12: =Inputs!A$50 -> Senior Project Manager / Characterization SME | E12: 1 | F12: =Inputs!E50 -> 127.28 | G12: =Inputs!G$209 -> 105 | H12: 0.5 | I12: =H12*G12*F12*E12*10 -> 66822 | J12: =H12*G12*10 -> 525
B13: =Inputs!A$49 -> Project Manager / Waste Management | E13: 1 | F13: =Inputs!E49 -> 108.19 | G13: =Inputs!G$209 -> 105 | H13: 0.5 | I13: =H13*G13*F13*E13*10 -> 56799.75 | J13: =H13*G13*10 -> 525
B14: =Inputs!A$48 -> Decom Technician / Safety SME | E14: 0 | F14: =Inputs!E48 -> 89.25 | G14: =Inputs!G$209 -> 105 | H14: 1 | I14: =H14*G14*F14*E14*10 -> 0 | J14: =H14*G14*10 -> 1050
E15: =SUM(E11:E14) -> 3 | I15: =SUM(I11:I14) -> 256232.55 | J15: =SUM(J11:J14) -> 3150
A17: 1.1.2 | B17: Equipment & Materials
G18: =Inputs!D85 -> US
C19: Equipment | F19: Quantity | G19: Rate | H19: Escalated Cost
C20: HEPA filter systems | F20: =IF(Inputs!$B$206=Inputs!$C$86,Inputs!C88,IF(Inputs!$B$206=Inputs!$G$86,Inputs!G88,IF(Inputs!$B$206=Inputs!$J$86,Inputs!J88,IF(Inputs!$B$206=Inputs!$M$86,Inputs!M88,"na")))) -> 2 | G20: =Inputs!D88 -> 3598.14 | H20: =G20*F20*(1+Inputs!$F$86) -> 11371.124
C21: Replacement filters | F21: =IF(Inputs!$B$206=Inputs!$C$86,Inputs!C89,IF(Inputs!$B$206=Inputs!$G$86,Inputs!G89,IF(Inputs!$B$206=Inputs!$J$86,Inputs!J89,IF(Inputs!$B$206=Inputs!$M$86,Inputs!M89,"na")))) -> 24 | G21: =Inputs!D89 -> 581.07 | H21: =G21*F21*(1+Inputs!$F$86) -> 22036.115
C22: Respirator | F22: =IF(Inputs!$B$206=Inputs!$C$86,Inputs!C90,IF(Inputs!$B$206=Inputs!$G$86,Inputs!G90,IF(Inputs!$B$206=Inputs!$J$86,Inputs!J90,IF(Inputs!$B$206=Inputs!$M$86,Inputs!M90,"na")))) -> 12 | G22: =Inputs!D90 -> 259 | H22: =G22*F22*(1+Inputs!$F$86) -> 4911.0725
C23: Rad/Vac wet-dry high eff. vacuum | F23: =IF(Inputs!$B$206=Inputs!$C$86,Inputs!C91,IF(Inputs!$B$206=Inputs!$G$86,Inputs!G91,IF(Inputs!$B$206=Inputs!$J$86,Inputs!J91,IF(Inputs!$B$206=Inputs!$M$86,Inputs!M91,"na")))) -> 1 | G23: =Inputs!D91 -> 3879 | H23: =G23*F23*(1+Inputs!$F$86) -> 6129.3598
C24: Rad/Vac wet-dry high eff. vacuum filters | F24: =IF(Inputs!$B$206=Inputs!$C$86,Inputs!C92,IF(Inputs!$B$206=Inputs!$G$86,Inputs!G92,IF(Inputs!$B$206=Inputs!$J$86,Inputs!J92,IF(Inputs!$B$206=Inputs!$M$86,Inputs!M92,"na")))) -> 5 | G24: =Inputs!D92 -> 412 | H24: =G24*F24*(1+Inputs!$F$86) -> 3255.0867
C25: Reciprocating Saws | F25: =IF(Inputs!$B$206=Inputs!$C$86,Inputs!C93,IF(Inputs!$B$206=Inputs!$G$86,Inputs!G93,IF(Inputs!$B$206=Inputs!$J$86,Inputs!J93,IF(Inputs!$B$206=Inputs!$M$86,Inputs!M93,"na")))) -> 5 | G25: =Inputs!D93 -> 1252.26 | H25: =G25*F25*(1+Inputs!$F$86) -> 9893.7254
C26: Pneumatic chipping hammers | F26: =IF(Inputs!$B$206=Inputs!$C$86,Inputs!C94,IF(Inputs!$B$206=Inputs!$G$86,Inputs!G94,IF(Inputs!$B$206=Inputs!$J$86,Inputs!J94,IF(Inputs!$B$206=Inputs!$M$86,Inputs!M94,"na")))) -> 2 | G26: =Inputs!D94 -> 1606.71 | H26: =G26*F26*(1+Inputs!$F$86) -> 5077.6508
C27: Chipping hammer blades | F27: =IF(Inputs!$B$206=Inputs!$C$86,Inputs!C95,IF(Inputs!$B$206=Inputs!$G$86,Inputs!G95,IF(Inputs!$B$206=Inputs!$J$86,Inputs!J95,IF(Inputs!$B$206=Inputs!$M$86,Inputs!M95,"na")))) -> 20 | G27: =Inputs!D95 -> 27.42 | H27: =G27*F27*(1+Inputs!$F$86) -> 866.54832
C28: Purchase an air compressor: | F28: =IF(Inputs!$B$206=Inputs!$C$86,Inputs!C96,IF(Inputs!$B$206=Inputs!$G$86,Inputs!G96,IF(Inputs!$B$206=Inputs!$J$86,Inputs!J96,IF(Inputs!$B$206=Inputs!$M$86,Inputs!M96,"na")))) -> 2 | G28: =Inputs!D96 -> 1723.44 | H28: =G28*F28*(1+Inputs!$F$86) -> 5446.5501
C29: Jackhammer | F29: =IF(Inputs!$B$206=Inputs!$C$86,Inputs!C97,IF(Inputs!$B$206=Inputs!$G$86,Inputs!G97,IF(Inputs!$B$206=Inputs!$J$86,Inputs!J97,IF(Inputs!$B$206=Inputs!$M$86,Inputs!M97,"na")))) -> 4 | G29: =Inputs!D97 -> 1417.11 | H29: =G29*F29*(1+Inputs!$F$86) -> 8956.9241
C30: Jackhammer Chisels | F30: =IF(Inputs!$B$206=Inputs!$C$86,Inputs!C98,IF(Inputs!$B$206=Inputs!$G$86,Inputs!G98,IF(Inputs!$B$206=Inputs!$J$86,Inputs!J98,IF(Inputs!$B$206=Inputs!$M$86,Inputs!M98,"na")))) -> 10 | G30: =Inputs!D98 -> 24.35 | H30: =G30*F30*(1+Inputs!$F$86) -> 384.76389
C31: Safety glasses | F31: =IF(Inputs!$B$206=Inputs!$C$86,Inputs!C99,IF(Inputs!$B$206=Inputs!$G$86,Inputs!G99,IF(Inputs!$B$206=Inputs!$J$86,Inputs!J99,IF(Inputs!$B$206=Inputs!$M$86,Inputs!M99,"na")))) -> 15 | G31: =Inputs!D99 -> 8.6 | H31: =G31*F31*(1+Inputs!$F$86) -> 203.83795
... C45: Crane rental for building removal | F45: =IF(Inputs!$B$206=Inputs!$C$86,Inputs!C113,IF(Inputs!$B$206=Inputs!$G$86,Inputs!G113,IF(Inputs!$B$206=Inputs!$J$86,Inputs!J113,IF(Inputs!$B$206=Inputs!$M$86,Inputs!M113,"na")))) -> 1 | G45: =Inputs!D113 -> 15600 | H45: =G45*F45*(1+Inputs!$F$86) -> 24650.171
H46: =SUM(H20:H45) -> 226414.4
C48: Consumables | E48: Quantity | G48: Duration | I48: # workers | J48: quantity | K48: Unit Qty | L48: Unit Cost | M48: Escalated Cost
C49: Coveralls | E49: =IF(Inputs!$B$206=Inputs!$C$86,Inputs!C117,IF(Inputs!$B$206=Inputs!$G$86,Inputs!D117,IF(Inputs!$B$206=Inputs!$J$86,Inputs!E117,IF(Inputs!$B$206=Inputs!$M$86,Inputs!F117,"na")))) -> 2 | F49: /man/day | G49: =Inputs!G$209 -> 105 | H49: days | I49: =Inputs!H$212 -> 24 | J49: =I49*G49*E49 -> 5040 | K49: 1 | L49: =Inputs!H117 -> 11 | M49: =J49/K49*L49*(1+Inputs!$F$86) -> 87602.916
C50: Hoods | E50: =IF(Inputs!$B$206=Inputs!$C$86,Inputs!C118,IF(Inputs!$B$206=Inputs!$G$86,Inputs!D118,IF(Inputs!$B$206=Inputs!$J$86,Inputs!E118,IF(Inputs!$B$206=Inputs!$M$86,Inputs!F118,"na")))) -> 0.1 | F50: /man/day | G50: =Inputs!G$209 -> 105 | H50: days | I50: =Inputs!H$212 -> 24 | J50: =I50*G50*E50 -> 252 | K50: 1 | L50: =Inputs!H118 -> 0 | M50: =J50/K50*L50*(1+Inputs!$F$86) -> 0
C51: Shoe covers | E51: =IF(Inputs!$B$206=Inputs!$C$86,Inputs!C119,IF(Inputs!$B$206=Inputs!$G$86,Inputs!D119,IF(Inputs!$B$206=Inputs!$J$86,Inputs!E119,IF(Inputs!$B$206=Inputs!$M$86,Inputs!F119,"na")))) -> 4 | F51: /man/day | G51: =Inputs!G$209 -> 105 | H51: days | I51: =Inputs!H$212 -> 24 | J51: =I51*G51*E51 -> 10080 | K51: 1 | L51: =Inputs!H119 -> 0.94 | M51: =J51/K51*L51*(1+Inputs!$F$86) -> 14972.135
C52: Latex gloves | E52: =IF(Inputs!$B$206=Inputs!$C$86,Inputs!C120,IF(Inputs!$B$206=Inputs!$G$86,Inputs!D120,IF(Inputs!$B$206=Inputs!$J$86,Inputs!E120,IF(Inputs!$B$206=Inputs!$M$86,Inputs!F120,"na")))) -> 4 | F52: /man/day | G52: =Inputs!G$209 -> 105 | H52: days | I52: =Inputs!H$212 -> 24 | J52: =I52*G52*E52 -> 10080 | K52: 1 | L52: =Inputs!H120 -> 0.94 | M52: =J52/K52*L52*(1+Inputs!$F$86) -> 14972.135
C53: Rubber overshoes | E53: =IF(Inputs!$B$206=Inputs!$C$86,Inputs!C121,IF(Inputs!$B$206=Inputs!$G$86,Inputs!D121,IF(Inputs!$B$206=Inputs!$J$86,Inputs!E121,IF(Inputs!$B$206=Inputs!$M$86,Inputs!F121,"na")))) -> 0.01 | F53: /man/day | G53: =Inputs!G$209 -> 105 | H53: days | I53: =Inputs!H$212 -> 24 | J53: =I53*G53*E53 -> 25.2 | K53: 1 | L53: =Inputs!H121 -> 3 | M53: =J53/K53*L53*(1+Inputs!$F$86) -> 119.45852
C54: Gloves | E54: =IF(Inputs!$B$206=Inputs!$C$86,Inputs!C122,IF(Inputs!$B$206=Inputs!$G$86,Inputs!D122,IF(Inputs!$B$206=Inputs!$J$86,Inputs!E122,IF(Inputs!$B$206=Inputs!$M$86,Inputs!F122,"na")))) -> 0.01 | F54: /man/day | G54: =Inputs!G$209 -> 105 | H54: days | I54: =Inputs!H$212 -> 24 | J54: =I54*G54*E54 -> 25.2 | K54: 1 | L54: =Inputs!H122 -> 2 | M54: =J54/K54*L54*(1+Inputs!$F$86) -> 79.639014
C55: Dosimeters | E55: =IF(Inputs!$B$206=Inputs!$C$86,Inputs!C123,IF(Inputs!$B$206=Inputs!$G$86,Inputs!D123,IF(Inputs!$B$206=Inputs!$J$86,Inputs!E123,IF(Inputs!$B$206=Inputs!$M$86,Inputs!F123,"na")))) -> 1 | F55: /man/year | G55: 0.25 | H55: year | I55: =Inputs!H$212 -> 24 | J55: =I55*G55*E55 -> 6 | K55: 1 | L55: =Inputs!H123 -> 200 | M55: =J55/K55*L55*(1+Inputs!$F$86) -> 1896.167
C56: TLDs | E56: =IF(Inputs!$B$206=Inputs!$C$86,Inputs!C124,IF(Inputs!$B$206=Inputs!$G$86,Inputs!D124,IF(Inputs!$B$206=Inputs!$J$86,Inputs!E124,IF(Inputs!$B$206=Inputs!$M$86,Inputs!F124,"na")))) -> 1 | F56: /man/mo | G56: 3 | H56: month | I56: =Inputs!H$212 -> 24 | J56: =I56*G56*E56 -> 72 | K56: 1 | L56: =Inputs!H124 -> 3 | M56: =J56/K56*L56*(1+Inputs!$F$86) -> 341.31006
C57: Bioassays | E57: =IF(Inputs!$B$206=Inputs!$C$86,Inputs!C125,IF(Inputs!$B$206=Inputs!$G$86,Inputs!D125,IF(Inputs!$B$206=Inputs!$J$86,Inputs!E125,IF(Inputs!$B$206=Inputs!$M$86,Inputs!F125,"na")))) -> 2 | F57: /man/year | G57: 0.5 | H57: year | I57: =Inputs!H$212 -> 24 | J57: =I57*G57*E57 -> 24 | K57: 1 | L57: =Inputs!H125 -> 250 | M57: =J57/K57*L57*(1+Inputs!$F$86) -> 9480.835
C58: (Bioassays for aver. crew & management) | M58: =SUM(M49:M57) -> 129464.59
C60: Small Tools - 2% of total labor costs = | G60: =(T6-T8) -> 10752955 | H60: labor costs x | I60: =Inputs!F128 -> 0.02 | J60: = | K60: =I60*G60 -> 215059.1
C62: HP Equipment Replacement - 5% of total labor | G62: =G60 -> 10752955 | H62: labor costs x | I62: =Inputs!F130 -> 0.05 | J62: = | K62: =I62*G62 -> 537647.74
C64: DGC OH &P on equipment and materials | G64: =R68+K62+K60+M58+H46 -> 1108585.8 | I64: =Inputs!F132 -> 0.08 | J64: = | K64: =I64*G64 -> 88686.866
A66: 1.2 | B66: Project Planning | J66: =J68+J75+J82 -> 415 | L66: =L68+L75+L82 -> 431 | M66: =M68+M75+M82 -> 2925 | T66: =T68+T75+T82 -> 270994.1 | Z66: =SUM(T66:Y66) -> 270994.1
A68: 1.2.1 | B68: Procedure Development and Review | J68: =I73 -> 160 | K68: 1 | L68: =J68*K68 -> 160 | M68: =L73 -> 240 | T68: =K73 -> 22935.2
D70: Staff | G70: Number | H70: Rate | I70: Duration | J70: PLF | K70: Cost | L70: Man-hours
D71: Project Specialist | G71: 2 | H71: =Inputs!E$48 -> 89.25 | I71: 80 | J71: 1 | K71: =G71*H71*I71*J71 -> 14280 | L71: =J71*I71*G71 -> 160
D72: Project Manager | G72: 1 | H72: =Inputs!E$49 -> 108.19 | I72: 80 | J72: 1 | K72: =G72*H72*I72*J72 -> 8655.2 | L72: =J72*I72*G72 -> 80
G73: =SUM(G71:G72) -> 3 | I73: =SUM(I71:I72) -> 160 | K73: =SUM(K71:K72) -> 22935.2 | L73: =SUM(L71:L72) -> 240
A75: 1.2.2 | B75: Preparation of QA and Safety Documents | J75: =I80 -> 160 | K75: 1.1 | L75: =J75*K75 -> 176 | M75: =L80 -> 240 | T75: =K80 -> 22935.2
D77: Staff | G77: Number | H77: Rate | I77: Duration | J77: PLF | K77: Cost | L77: Man-hours
D78: Project Specialist | G78: 2 | H78: =Inputs!E$48 -> 89.25 | I78: 80 | J78: 1 | K78: =J78*I78*H78*G78 -> 14280 | L78: =J78*I78*G78 -> 160
D79: Project Manager | G79: 1 | H79: =Inputs!E$49 -> 108.19 | I79: 80 | J79: 1 | K79: =J79*I79*H79*G79 -> 8655.2 | L79: =J79*I79*G79 -> 80
G80: =SUM(G78:G79) -> 3 | I80: =SUM(I78:I79) -> 160 | K80: =SUM(K78:K79) -> 22935.2 | L80: =SUM(L78:L79) -> 240
A82: 1.2.3 | B82: Site Mobilization and General Employee Training (GET) | J82: =J84+J97 -> 95 | K82: 1 | L82: =J82*K82 -> 95 | M82: =M84+M97 -> 2445 | T82: =T84+T97 -> 225123.7
C84: 1.2.3.1 | D84: Site Mobilization | J84: =F95 -> 40 | K84: 1 | L84: =J84*K84 -> 40 | M84: =J84*D87 -> 960 | T84: =I95 -> 85680
D86: Crew | G86: Rate, $/hr | H86: Cost, $/hr
D87: =I49 -> 24 | E87: Decom Technician / Safety SME | G87: =Inputs!E48 -> 89.25 | H87: =G87*D87 -> 2142
D89: Receipt of material and equipment | G89: 16 | H89: hr
D90: Staging of equipment | G90: 8 | H90: hr
D91: Set up office and amenities | G91: 12 | H91: hr
D92: Familiarize staff with facility | G92: 4 | H92: hr
G93: =SUM(G89:G92) -> 40 | H93: hr
D95: Total Cost = | F95: =G93 -> 40 | G95: x | H95: =H87 -> 2142 | I95: =H95*F95 -> 85680
C97: 1.2.3.2 | D97: General Employee Training (All proj. management and 3 crews of 4) | J97: =F116 -> 55 | K97: 1 | L97: =K97*J97 -> 55 | M97: =D104*F116 -> 1485 | S97: =J116*Inputs!C37 -> 54054 | T97: =K116 -> 139443.7
D99: Crew | G99: Rate, $/hr | H99: Cost, $/hr
D100: 1 | E100: =B11 -> Portfolio Manager | G100: =F11 -> 157.87 | H100: =G100*D100 -> 157.87
D101: 1 | E101: =B12 -> Senior Project Manager / Characterization SME | G101: =F12 -> 127.28 | H101: =G101*D101 -> 127.28
D102: 1 | E102: =B13 -> Project Manager / Waste Management | G102: =F13 -> 108.19 | H102: =G102*D102 -> 108.19
D103: =I49 -> 24 | E103: =B14 -> Decom Technician / Safety SME | G103: =F14 -> 89.25 | H103: =G103*D103 -> 2142
D104: =SUM(D100:D103) -> 27 | H104: =SUM(H100:H103) -> 2535.34
I106: Number | J106: Test | K106: Labor | L106: Total
H107: Unit Cost | I107: Required | J107: Cost | K107: Costs | L107: Cost
D108: In-Vivo | H108: 600 | I108: =D$104 -> 27 | J108: =I108*H108 -> 16200 | K108: =F108*H$104 -> 0 | L108: =K108+J108 -> 16200
D109: In-Vitro | H109: 350 | I109: =D$104 -> 27 | J109: =I109*H109 -> 9450 | K109: =F109*H$104 -> 0 | L109: =K109+J109 -> 9450
D110: Physical @ | F110: 4 | G110: hour and | H110: 150 | I110: =D$104 -> 27 | J110: =I110*H110 -> 4050 | K110: =F110*H$104 -> 10141.36 | L110: =K110+J110 -> 14191.36
D111: Resp. Tests | F111: 1 | G111: hour and | H111: 50 | I111: =D$104 -> 27 | J111: =I111*H111 -> 1350 | K111: =F111*H$104 -> 2535.34 | L111: =K111+J111 -> 3885.34
D112: Resp Fit Tests | F112: 1 | G112: hour and | H112: 25 | I112: =D$104 -> 27 | J112: =I112*H112 -> 675 | K112: =F112*H$104 -> 2535.34 | L112: =K112+J112 -> 3210.34
D113: Blood Tests | F113: 1 | G113: hour and | H113: 125 | I113: =D$104 -> 27 | J113: =I113*H113 -> 3375 | K113: =F113*H$104 -> 2535.34 | L113: =K113+J113 -> 5910.34
D114: OSHA recertification | F114: 8 | G114: hour | K114: =F114*H$104 -> 20282.72 | L114: =K114+J114 -> 20282.72
D115: Site specific 1 week of training | F115: 40 | G115: hour | K115: =F115*H$104 -> 101413.6 | L115: =K115+J115 -> 101413.6
F116: =SUM(F110:F115) -> 55 | J116: =SUM(J108:J115) -> 35100 | K116: =SUM(K110:K115) -> 139443.7 | L116: =SUM(L108:L115) -> 174543.7
A118: 1.3 | B118: Preliminary Site Investigation | J118: =J120+J122 -> 176 | L118: =L120+L122 -> 176 | M118: =M120+M122 -> 480 | T118: =T120+T122 -> 44658.24 | Z118: =SUM(T118:Y118) -> 44658.24
A120: 1.3.1 | B120: Decontamination Readiness Review - (Contractor staff cost included in Undistributed Costs) | J120: 80 | K120: 1 | L120: =K120*J120 -> 80
A122: 1.3.2 | B122: Site Preparation | H122: A | J122: =J124+J133+J151+J159 -> 96 | K122: 1 | L122: =L124+L133+L151+L159 -> 96 | M122: =M124+M133+M151+M159 -> 480 | T122: =T124+T133+T151+T159 -> 44658.24
B124: 1.3.2.1 | C124: Initial Site Survey | H124: A | J124: =F126 -> 16 | K124: 1 | L124: =K124*J124 -> 16 | M124: =L130 -> 80 | T124: =K130 -> 7443.04
E126: Estimated Duration | F126: 16 | G126: hrs
D127: Staff | G127: Number | H127: Rate | I127: Duration | J127: PLF | K127: Cost | L127: Man-hours
D128: Project Specialist | G128: 4 | H128: =Inputs!E$48 -> 89.25 | I128: =F126 -> 16 | J128: 1 | K128: =J128*I128*H128*G128 -> 5712 | L128: =J128*I128*G128 -> 64
D129: Project Manager | G129: 1 | H129: =Inputs!E$49 -> 108.19 | I129: =F126 -> 16 | J129: 1 | K129: =J129*I129*H129*G129 -> 1731.04 | L129: =J129*I129*G129 -> 16
G130: =SUM(G128:G129) -> 5 | I130: =SUM(I128:I129) -> 32 | K130: =SUM(K128:K129) -> 7443.04 | L130: =SUM(L128:L129) -> 80
B133: 1.3.2.2 | C133: Setup work areas | J133: =J135+J143 -> 32 | L133: =L135+L143 -> 32 | M133: =M135+M143 -> 160 | T133: =T135+T143 -> 14886.08
B135: 1.3.2.2.1 | C135: Setup boundaries, install HEPA filters & seal off openings | H135: A | J135: =F137 -> 16 | K135: 1 | L135: =K135*J135 -> 16 | M135: =L141 -> 80 | T135: =K141 -> 7443.04
E137: Estimated Duration | F137: 16 | G137: hrs
D138: Staff | G138: Number | H138: Rate | I138: Duration | J138: PLF | K138: Cost | L138: Man-hours
D139: Project Specialist | G139: 4 | H139: =Inputs!E$48 -> 89.25 | I139: =F137 -> 16 | J139: 1 | K139: =J139*I139*H139*G139 -> 5712 | L139: =J139*I139*G139 -> 64
D140: Project Manager | G140: 1 | H140: =Inputs!E$49 -> 108.19 | I140: =F137 -> 16 | J140: 1 | K140: =J140*I140*H140*G140 -> 1731.04 | L140: =J140*I140*G140 -> 16
G141: =SUM(G139:G140) -> 5 | I141: =SUM(I139:I140) -> 32 | K141: =SUM(K139:K140) -> 7443.04 | L141: =SUM(L139:L140) -> 80
B143: 1.3.2.2.2 | C143: Establish staging area | H143: A | J143: =F145 -> 16 | K143: 1 | L143: =K143*J143 -> 16 | M143: =L149 -> 80 | T143: =K149 -> 7443.04
E145: Estimated Duration | F145: 16 | G145: hrs
D146: Staff | G146: Number | H146: Rate | I146: Duration | J146: PLF | K146: Cost | L146: Man-hours
...

Sheet Building B70
A1: B 56 DATA - Data highlighted in GREEN can be adjusted as needed
J2: Uncorrected Duration | Q2: Mixed | R2: Clean | S2: Materials, | V2: Hazardous | X2: Mixed | Y2: Clean
I3: Crew | J3: (No. of Hours) | K3: Prod. Factor | L3: Adjusted Duration (hrs) | M3: Man-hours | N3: LSA Waste Disp. Vol (cm) | O3: Hazardous Waste Vol (cm) | Q3: Mixed Waste Volume (cm) | R3: Clean Waste Volume (cm) | S3: Materials, Consumables & Equipment | T3: Labor Cost | U3: LSA Waste Costs | V3: Hazardous Waste Costs | W3: LSA Waste Costs | X3: Mixed Waste Costs | Y3: Clean Waste Costs | Z3: Total Cost
A6: 1.0 | B6: Building B70 | L6: =L8+L66+L118+L177+L185+L207 -> 416 | M6: =M8+M66+M118+M177+M185+M207 -> 1080 | N6: =N8+N66+N118+N177+N185+N207 -> 0 | O6: =O8+O66+O118+O177+O185+O207 -> 41.550719 | Q6: =Q8+Q66+Q118+Q177+Q185+Q207 -> 0.43862739 | R6: =R8+R66+R118+R177+R185+R207 -> 169.56041 | S6: =S8+S66+S118+S177+S185+S207+S214 -> 188017.77 | T6: =T8+T66+T118+T177+T185+T207+T214 -> 437858.58 | V6: =V8+V66+V118+V177+V185+V207+V214 -> 36683.805 | X6: =X8+X66+X118+X177+X185+X207+X214 -> 12807.071 | Y6: =Y8+Y66+Y118+Y177+Y185+Y207+Y214 -> 89819.688 | Z6: =SUM(S6:Y6) -> 765186.91
A8: 1.1 | B8: Project Management | S8: =IF(G18="US",(H46+M58+K60+K62+K64)*Inputs!C37,(H46+M58+K60+K62+K64)) -> 188017.77 | T8: =I15 -> 71961.96 | Z8: =SUM(S8:Y8) -> 259979.73
A10: 1.1.1 | B10: Staff | E10: Number | F10: Rate | G10: Duration, days* | H10: Use Factor | I10: Cost | J10: Man-hours
B11: =Inputs!A$51 -> Portfolio Manager | E11: 1 | F11: =Inputs!E51 -> 157.87 | G11: =Inputs!G$251 -> 84 | H11: 0.25 | I11: =H11*G11*F11*E11*8 -> 26522.16 | J11: =H11*G11*10 -> 210
B12: =Inputs!A$50 -> Senior Project Manager / Characterization SME | E12: 1 | F12: =Inputs!E50 -> 127.28 | G12: =Inputs!G$251 -> 84 | H12: 0 | I12: =H12*G12*F12*E12*10 -> 0 | J12: =H12*G12*10 -> 0
B13: =Inputs!A$49 -> Project Manager / Waste Management | E13: 1 | F13: =Inputs!E49 -> 108.19 | G13: =Inputs!G$251 -> 84 | H13: 0.5 | I13: =H13*G13*F13*E13*10 -> 45439.8 | J13: =H13*G13*10 -> 420
B14: =Inputs!A$48 -> Decom Technician / Safety SME | E14: 0 | F14: =Inputs!E48 -> 89.25 | G14: =Inputs!G$251 -> 84 | H14: 1 | I14: =H14*G14*F14*E14*10 -> 0 | J14: =H14*G14*10 -> 840
E15: =SUM(E11:E14) -> 3 | I15: =SUM(I11:I14) -> 71961.96 | J15: =SUM(J11:J14) -> 1470
A17: 1.1.2 | B17: Equipment & Materials
G18: =Inputs!D85 -> US
C19: Equipment | F19: Quantity | G19: Rate | H19: Escalated Cost
C20: HEPA filter systems | F20: =IF(Inputs!$B$248=Inputs!$C$86,Inputs!C88,IF(Inputs!$B$248=Inputs!$G$86,Inputs!G88,IF(Inputs!$B$248=Inputs!$J$86,Inputs!J88,IF(Inputs!$B$248=Inputs!$M$86,Inputs!M88,"na")))) -> 0 | G20: =Inputs!D88 -> 3598.14 | H20: =G20*F20*(1+Inputs!$F$86) -> 0
C21: Replacement filters | F21: =IF(Inputs!$B$248=Inputs!$C$86,Inputs!C89,IF(Inputs!$B$248=Inputs!$G$86,Inputs!G89,IF(Inputs!$B$248=Inputs!$J$86,Inputs!J89,IF(Inputs!$B$248=Inputs!$M$86,Inputs!M89,"na")))) -> 0 | G21: =Inputs!D89 -> 581.07 | H21: =G21*F21*(1+Inputs!$F$86) -> 0
C22: Respirator | F22: =IF(Inputs!$B$248=Inputs!$C$86,Inputs!C90,IF(Inputs!$B$248=Inputs!$G$86,Inputs!G90,IF(Inputs!$B$248=Inputs!$J$86,Inputs!J90,IF(Inputs!$B$248=Inputs!$M$86,Inputs!M90,"na")))) -> 0 | G22: =Inputs!D90 -> 259 | H22: =G22*F22*(1+Inputs!$F$86) -> 0
C23: Rad/Vac wet-dry high eff. vacuum | F23: =IF(Inputs!$B$248=Inputs!$C$86,Inputs!C91,IF(Inputs!$B$248=Inputs!$G$86,Inputs!G91,IF(Inputs!$B$248=Inputs!$J$86,Inputs!J91,IF(Inputs!$B$248=Inputs!$M$86,Inputs!M91,"na")))) -> 0 | G23: =Inputs!D91 -> 3879 | H23: =G23*F23*(1+Inputs!$F$86) -> 0
C24: Rad/Vac wet-dry high eff. vacuum filters | F24: =IF(Inputs!$B$248=Inputs!$C$86,Inputs!C92,IF(Inputs!$B$248=Inputs!$G$86,Inputs!G92,IF(Inputs!$B$248=Inputs!$J$86,Inputs!J92,IF(Inputs!$B$248=Inputs!$M$86,Inputs!M92,"na")))) -> 0 | G24: =Inputs!D92 -> 412 | H24: =G24*F24*(1+Inputs!$F$86) -> 0
C25: Reciprocating Saws | F25: =IF(Inputs!$B$248=Inputs!$C$86,Inputs!C93,IF(Inputs!$B$248=Inputs!$G$86,Inputs!G93,IF(Inputs!$B$248=Inputs!$J$86,Inputs!J93,IF(Inputs!$B$248=Inputs!$M$86,Inputs!M93,"na")))) -> 0 | G25: =Inputs!D93 -> 1252.26 | H25: =G25*F25*(1+Inputs!$F$86) -> 0
C26: Pneumatic chipping hammers | F26: =IF(Inputs!$B$248=Inputs!$C$86,Inputs!C94,IF(Inputs!$B$248=Inputs!$G$86,Inputs!G94,IF(Inputs!$B$248=Inputs!$J$86,Inputs!J94,IF(Inputs!$B$248=Inputs!$M$86,Inputs!M94,"na")))) -> 2 | G26: =Inputs!D94 -> 1606.71 | H26: =G26*F26*(1+Inputs!$F$86) -> 5077.6508
C27: Chipping hammer blades | F27: =IF(Inputs!$B$248=Inputs!$C$86,Inputs!C95,IF(Inputs!$B$248=Inputs!$G$86,Inputs!G95,IF(Inputs!$B$248=Inputs!$J$86,Inputs!J95,IF(Inputs!$B$248=Inputs!$M$86,Inputs!M95,"na")))) -> 20 | G27: =Inputs!D95 -> 27.42 | H27: =G27*F27*(1+Inputs!$F$86) -> 866.54832
C28: Purchase an air compressor: | F28: =IF(Inputs!$B$248=Inputs!$C$86,Inputs!C96,IF(Inputs!$B$248=Inputs!$G$86,Inputs!G96,IF(Inputs!$B$248=Inputs!$J$86,Inputs!J96,IF(Inputs!$B$248=Inputs!$M$86,Inputs!M96,"na")))) -> 2 | G28: =Inputs!D96 -> 1723.44 | H28: =G28*F28*(1+Inputs!$F$86) -> 5446.5501
C29: Jackhammer | F29: =IF(Inputs!$B$248=Inputs!$C$86,Inputs!C97,IF(Inputs!$B$248=Inputs!$G$86,Inputs!G97,IF(Inputs!$B$248=Inputs!$J$86,Inputs!J97,IF(Inputs!$B$248=Inputs!$M$86,Inputs!M97,"na")))) -> 4 | G29: =Inputs!D97 -> 1417.11 | H29: =G29*F29*(1+Inputs!$F$86) -> 8956.9241
C30: Jackhammer Chisels | F30: =IF(Inputs!$B$248=Inputs!$C$86,Inputs!C98,IF(Inputs!$B$248=Inputs!$G$86,Inputs!G98,IF(Inputs!$B$248=Inputs!$J$86,Inputs!J98,IF(Inputs!$B$248=Inputs!$M$86,Inputs!M98,"na")))) -> 10 | G30: =Inputs!D98 -> 24.35 | H30: =G30*F30*(1+Inputs!$F$86) -> 384.76389
C31: Safety glasses | F31: =IF(Inputs!$B$248=Inputs!$C$86,Inputs!C99,IF(Inputs!$B$248=Inputs!$G$86,Inputs!G99,IF(Inputs!$B$248=Inputs!$J$86,Inputs!J99,IF(Inputs!$B$248=Inputs!$M$86,Inputs!M99,"na")))) -> 15 | G31: =Inputs!D99 -> 8.6 | H31: =G31*F31*(1+Inputs!$F$86) -> 203.83795
... C45: Crane rental for building removal | F45: =IF(Inputs!$B$248=Inputs!$C$86,Inputs!C113,IF(Inputs!$B$248=Inputs!$G$86,Inputs!G113,IF(Inputs!$B$248=Inputs!$J$86,Inputs!J113,IF(Inputs!$B$248=Inputs!$M$86,Inputs!M113,"na")))) -> 0 | G45: =Inputs!D113 -> 15600 | H45: =G45*F45*(1+Inputs!$F$86) -> 0
H46: =SUM(H20:H45) -> 87433.033
C48: Consumables | E48: Quantity | G48: Duration | I48: # workers | J48: quantity | K48: Unit Qty | L48: Unit Cost | M48: Escalated Cost
C49: Coveralls | E49: =IF(Inputs!$B$248=Inputs!$C$86,Inputs!C117,IF(Inputs!$B$248=Inputs!$G$86,Inputs!D117,IF(Inputs!$B$248=Inputs!$J$86,Inputs!E117,IF(Inputs!$B$248=Inputs!$M$86,Inputs!F117,"na")))) -> 0 | F49: /man/day | G49: 0 | H49: days | I49: =Inputs!G$254 -> 9 | J49: =I49*G49*E49 -> 0 | K49: 1 | L49: =Inputs!H117 -> 11 | M49: =J49/K49*L49*(1+Inputs!$F$86) -> 0
C50: Hoods | E50: =IF(Inputs!$B$248=Inputs!$C$86,Inputs!C118,IF(Inputs!$B$248=Inputs!$G$86,Inputs!D118,IF(Inputs!$B$248=Inputs!$J$86,Inputs!E118,IF(Inputs!$B$248=Inputs!$M$86,Inputs!F118,"na")))) -> 0 | F50: /man/day | G50: 0 | H50: days | I50: =Inputs!G$254 -> 9 | J50: =I50*G50*E50 -> 0 | K50: 1 | L50: =Inputs!H118 -> 0 | M50: =J50/K50*L50*(1+Inputs!$F$86) -> 0
C51: Shoe covers | E51: =IF(Inputs!$B$248=Inputs!$C$86,Inputs!C119,IF(Inputs!$B$248=Inputs!$G$86,Inputs!D119,IF(Inputs!$B$248=Inputs!$J$86,Inputs!E119,IF(Inputs!$B$248=Inputs!$M$86,Inputs!F119,"na")))) -> 0 | F51: /man/day | G51: 0 | H51: days | I51: =Inputs!G$254 -> 9 | J51: =I51*G51*E51 -> 0 | K51: 1 | L51: =Inputs!H119 -> 0.94 | M51: =J51/K51*L51*(1+Inputs!$F$86) -> 0
C52: Latex gloves | E52: =IF(Inputs!$B$248=Inputs!$C$86,Inputs!C120,IF(Inputs!$B$248=Inputs!$G$86,Inputs!D120,IF(Inputs!$B$248=Inputs!$J$86,Inputs!E120,IF(Inputs!$B$248=Inputs!$M$86,Inputs!F120,"na")))) -> 0 | F52: /man/day | G52: 0 | H52: days | I52: =Inputs!G$254 -> 9 | J52: =I52*G52*E52 -> 0 | K52: 1 | L52: =Inputs!H120 -> 0.94 | M52: =J52/K52*L52*(1+Inputs!$F$86) -> 0
C53: Rubber overshoes | E53: =IF(Inputs!$B$248=Inputs!$C$86,Inputs!C121,IF(Inputs!$B$248=Inputs!$G$86,Inputs!D121,IF(Inputs!$B$248=Inputs!$J$86,Inputs!E121,IF(Inputs!$B$248=Inputs!$M$86,Inputs!F121,"na")))) -> 0 | F53: /man/day | G53: 0 | H53: days | I53: =Inputs!G$254 -> 9 | J53: =I53*G53*E53 -> 0 | K53: 1 | L53: =Inputs!H121 -> 3 | M53: =J53/K53*L53*(1+Inputs!$F$86) -> 0
C54: Gloves | E54: =IF(Inputs!$B$248=Inputs!$C$86,Inputs!C122,IF(Inputs!$B$248=Inputs!$G$86,Inputs!D122,IF(Inputs!$B$248=Inputs!$J$86,Inputs!E122,IF(Inputs!$B$248=Inputs!$M$86,Inputs!F122,"na")))) -> 0 | F54: /man/day | G54: 0 | H54: days | I54: =Inputs!G$254 -> 9 | J54: =I54*G54*E54 -> 0 | K54: 1 | L54: =Inputs!H122 -> 2 | M54: =J54/K54*L54*(1+Inputs!$F$86) -> 0
C55: Dosimeters | E55: =IF(Inputs!$B$248=Inputs!$C$86,Inputs!C123,IF(Inputs!$B$248=Inputs!$G$86,Inputs!D123,IF(Inputs!$B$248=Inputs!$J$86,Inputs!E123,IF(Inputs!$B$248=Inputs!$M$86,Inputs!F123,"na")))) -> 0 | F55: /man/year | G55: 0 | H55: year | I55: =Inputs!G$254 -> 9 | J55: =I55*G55*E55 -> 0 | K55: 1 | L55: =Inputs!H123 -> 200 | M55: =J55/K55*L55*(1+Inputs!$F$86) -> 0
C56: TLDs | E56: =IF(Inputs!$B$248=Inputs!$C$86,Inputs!C124,IF(Inputs!$B$248=Inputs!$G$86,Inputs!D124,IF(Inputs!$B$248=Inputs!$J$86,Inputs!E124,IF(Inputs!$B$248=Inputs!$M$86,Inputs!F124,"na")))) -> 0 | F56: /man/mo | G56: 0 | H56: month | I56: =Inputs!G$254 -> 9 | J56: =I56*G56*E56 -> 0 | K56: 1 | L56: =Inputs!H124 -> 3 | M56: =J56/K56*L56*(1+Inputs!$F$86) -> 0
C57: Bioassays | E57: =IF(Inputs!$B$248=Inputs!$C$86,Inputs!C125,IF(Inputs!$B$248=Inputs!$G$86,Inputs!D125,IF(Inputs!$B$248=Inputs!$J$86,Inputs!E125,IF(Inputs!$B$248=Inputs!$M$86,Inputs!F125,"na")))) -> 0 | F57: /man/year | G57: 0 | H57: year | I57: =Inputs!G$254 -> 9 | J57: =I57*G57*E57 -> 0 | K57: 1 | L57: =Inputs!H125 -> 250 | M57: =J57/K57*L57*(1+Inputs!$F$86) -> 0
C58: (Bioassays for aver. crew & management) | M58: =SUM(M49:M57) -> 0
C60: Small Tools - 2% of total labor costs = | G60: =(T6-T8) -> 365896.62 | H60: labor costs x | I60: =Inputs!F128 -> 0.02 | J60: = | K60: =I60*G60 -> 7317.9324
C62: HP Equipment Replacement - 5% of total labor | G62: =G60 -> 365896.62 | H62: labor costs x | I62: =Inputs!F130 -> 0.05 | J62: = | K62: =I62*G62 -> 18294.831
C64: DGC OH &P on equipment and materials | G64: =R68+K62+K60+M58+H46 -> 113045.8 | I64: =Inputs!F132 -> 0.08 | J64: = | K64: =I64*G64 -> 9043.6637
A66: 1.2 | B66: Project Planning | J66: =J68+J75+J82 -> 200 | L66: =L68+L75+L82 -> 200 | M66: =M68+M75+M82 -> 600 | T66: =T68+T75+T82 -> 55065.2 | Z66: =SUM(T66:Y66) -> 55065.2
A68: 1.2.1 | B68: Procedure Development and Review | J68: =I73 -> 80 | K68: 1 | L68: =J68*K68 -> 80 | M68: =L73 -> 120 | T68: =K73 -> 11467.6
D70: Staff | G70: Number | H70: Rate | I70: Duration | J70: PLF | K70: Cost | L70: Man-hours
D71: Project Specialist | G71: 2 | H71: =Inputs!E$48 -> 89.25 | I71: 40 | J71: 1 | K71: =G71*H71*I71*J71 -> 7140 | L71: =J71*I71*G71 -> 80
D72: Project Manager | G72: 1 | H72: =Inputs!E$49 -> 108.19 | I72: 40 | J72: 1 | K72: =G72*H72*I72*J72 -> 4327.6 | L72: =J72*I72*G72 -> 40
G73: =SUM(G71:G72) -> 3 | I73: =SUM(I71:I72) -> 80 | K73: =SUM(K71:K72) -> 11467.6 | L73: =SUM(L71:L72) -> 120
A75: 1.2.2 | B75: Preparation of QA and Safety Documents | J75: =I80 -> 80 | K75: 1 | L75: =J75*K75 -> 80 | M75: =L80 -> 120 | T75: =K80 -> 11467.6
D77: Staff | G77: Number | H77: Rate | I77: Duration | J77: PLF | K77: Cost | L77: Man-hours
D78: Project Specialist | G78: 2 | H78: =Inputs!E$48 -> 89.25 | I78: 40 | J78: 1 | K78: =J78*I78*H78*G78 -> 7140 | L78: =J78*I78*G78 -> 80
D79: Project Manager | G79: 1 | H79: =Inputs!E$49 -> 108.19 | I79: 40 | J79: 1 | K79: =J79*I79*H79*G79 -> 4327.6 | L79: =J79*I79*G79 -> 40
G80: =SUM(G78:G79) -> 3 | I80: =SUM(I78:I79) -> 80 | K80: =SUM(K78:K79) -> 11467.6 | L80: =SUM(L78:L79) -> 120
A82: 1.2.3 | B82: Site Mobilization and General Employee Training (GET) | J82: =J84+J97 -> 40 | K82: 1 | L82: =J82*K82 -> 40 | M82: =M84+M97 -> 360 | T82: =T84+T97 -> 32130
C84: 1.2.3.1 | D84: Site Mobilization | J84: =F95 -> 40 | K84: 1 | L84: =J84*K84 -> 40 | M84: =J84*D87 -> 360 | T84: =I95 -> 32130
D86: Crew | G86: Rate, $/hr | H86: Cost, $/hr
D87: =I49 -> 9 | E87: Decom Technician / Safety SME | G87: =Inputs!E48 -> 89.25 | H87: =G87*D87 -> 803.25
D89: Receipt of material and equipment | G89: 16 | H89: hr
D90: Staging of equipment | G90: 8 | H90: hr
D91: Set up office and amenities | G91: 12 | H91: hr
D92: Familiarize staff with facility | G92: 4 | H92: hr
G93: =SUM(G89:G92) -> 40 | H93: hr
D95: Total Cost = | F95: =G93 -> 40 | G95: x | H95: =H87 -> 803.25 | I95: =H95*F95 -> 32130
C97: 1.2.3.2 | D97: General Employee Training (All proj. management and 3 crews of 4) | J97: =F116 -> 0 | K97: 1 | L97: =K97*J97 -> 0 | M97: =D104*F116 -> 0 | S97: =J116*Inputs!C37 -> 0 | T97: =K116 -> 0
D99: Crew | G99: Rate, $/hr | H99: Cost, $/hr
D100: 1 | E100: =B11 -> Portfolio Manager | G100: =F11 -> 157.87 | H100: =G100*D100 -> 157.87
D101: 1 | E101: =B12 -> Senior Project Manager / Characterization SME | G101: =F12 -> 127.28 | H101: =G101*D101 -> 127.28
D102: 1 | E102: =B13 -> Project Manager / Waste Management | G102: =F13 -> 108.19 | H102: =G102*D102 -> 108.19
D103: =I49 -> 9 | E103: =B14 -> Decom Technician / Safety SME | G103: =F14 -> 89.25 | H103: =G103*D103 -> 803.25
D104: =SUM(D100:D103) -> 12 | H104: =SUM(H100:H103) -> 1196.59
I106: Number | J106: Test | K106: Labor | L106: Total
H107: Unit Cost | I107: Required | J107: Cost | K107: Costs | L107: Cost
D108: In-Vivo | H108: 600 | I108: 0 | J108: =I108*H108 -> 0 | K108: =F108*H$104 -> 0 | L108: =K108+J108 -> 0
D109: In-Vitro | H109: 350 | I109: 0 | J109: =I109*H109 -> 0 | K109: =F109*H$104 -> 0 | L109: =K109+J109 -> 0
D110: Physical @ | F110: 0 | G110: hour and | H110: 150 | I110: 0 | J110: =I110*H110 -> 0 | K110: =F110*H$104 -> 0 | L110: =K110+J110 -> 0
D111: Resp. Tests | F111: 0 | G111: hour and | H111: 50 | I111: 0 | J111: =I111*H111 -> 0 | K111: =F111*H$104 -> 0 | L111: =K111+J111 -> 0
D112: Resp Fit Tests | F112: 0 | G112: hour and | H112: 25 | I112: 0 | J112: =I112*H112 -> 0 | K112: =F112*H$104 -> 0 | L112: =K112+J112 -> 0
D113: Blood Tests | F113: 0 | G113: hour and | H113: 125 | I113: 0 | J113: =I113*H113 -> 0 | K113: =F113*H$104 -> 0 | L113: =K113+J113 -> 0
D114: OSHA recertification | F114: 0 | G114: hour | K114: =F114*H$104 -> 0 | L114: =K114+J114 -> 0
D115: Site specific 1 week of training | F115: 0 | G115: hour | K115: =F115*H$104 -> 0 | L115: =K115+J115 -> 0
F116: =SUM(F110:F115) -> 0 | J116: =SUM(J108:J115) -> 0 | K116: =SUM(K110:K115) -> 0 | L116: =SUM(L108:L115) -> 0
A118: 1.3 | B118: Preliminary Site Investigation | J118: =J120+J122 -> 176 | L118: =L120+L122 -> 176 | M118: =M120+M122 -> 480 | T118: =T120+T122 -> 44658.24 | Z118: =SUM(T118:Y118) -> 44658.24
A120: 1.3.1 | B120: Decontamination Readiness Review - (Contractor staff cost included in Undistributed Costs) | J120: 80 | K120: 1 | L120: =K120*J120 -> 80
A122: 1.3.2 | B122: Site Preparation | H122: A | J122: =J124+J133+J151+J159 -> 96 | K122: 1 | L122: =L124+L133+L151+L159 -> 96 | M122: =M124+M133+M151+M159 -> 480 | T122: =T124+T133+T151+T159 -> 44658.24
B124: 1.3.2.1 | C124: Initial Site Survey | H124: A | J124: =F126 -> 16 | K124: 1 | L124: =K124*J124 -> 16 | M124: =L130 -> 80 | T124: =K130 -> 7443.04
E126: Estimated Duration | F126: 16 | G126: hrs
D127: Staff | G127: Number | H127: Rate | I127: Duration | J127: PLF | K127: Cost | L127: Man-hours
D128: Project Specialist | G128: 4 | H128: =Inputs!E$48 -> 89.25 | I128: =F126 -> 16 | J128: 1 | K128: =J128*I128*H128*G128 -> 5712 | L128: =J128*I128*G128 -> 64
D129: Project Manager | G129: 1 | H129: =Inputs!E$49 -> 108.19 | I129: =F126 -> 16 | J129: 1 | K129: =J129*I129*H129*G129 -> 1731.04 | L129: =J129*I129*G129 -> 16
G130: =SUM(G128:G129) -> 5 | I130: =SUM(I128:I129) -> 32 | K130: =SUM(K128:K129) -> 7443.04 | L130: =SUM(L128:L129) -> 80
B133: 1.3.2.2 | C133: Setup work areas | J133: =J135+J143 -> 32 | L133: =L135+L143 -> 32 | M133: =M135+M143 -> 160 | T133: =T135+T143 -> 14886.08
B135: 1.3.2.2.1 | C135: Setup boundaries, install HEPA filters & seal off openings | H135: A | J135: =F137 -> 16 | K135: 1 | L135: =K135*J135 -> 16 | M135: =L141 -> 80 | T135: =K141 -> 7443.04
E137: Estimated Duration | F137: 16 | G137: hrs
D138: Staff | G138: Number | H138: Rate | I138: Duration | J138: PLF | K138: Cost | L138: Man-hours
D139: Project Specialist | G139: 4 | H139: =Inputs!E$48 -> 89.25 | I139: =F137 -> 16 | J139: 1 | K139: =J139*I139*H139*G139 -> 5712 | L139: =J139*I139*G139 -> 64
D140: Project Manager | G140: 1 | H140: =Inputs!E$49 -> 108.19 | I140: =F137 -> 16 | J140: 1 | K140: =J140*I140*H140*G140 -> 1731.04 | L140: =J140*I140*G140 -> 16
G141: =SUM(G139:G140) -> 5 | I141: =SUM(I139:I140) -> 32 | K141: =SUM(K139:K140) -> 7443.04 | L141: =SUM(L139:L140) -> 80
B143: 1.3.2.2.2 | C143: Establish staging area | H143: A | J143: =F145 -> 16 | K143: 1 | L143: =K143*J143 -> 16 | M143: =L149 -> 80 | T143: =K149 -> 7443.04
E145: Estimated Duration | F145: 16 | G145: hrs
D146: Staff | G146: Number | H146: Rate | I146: Duration | J146: PLF | K146: Cost | L146: Man-hours
...

Sheet Building  XX
A1: B XX DATA - Data highlighted in GREEN should be adjusted as needed
J2: Uncorrected Duration | Q2: Mixed | R2: Clean | S2: Materials, | V2: Hazardous | X2: Mixed | Y2: Clean
B3: GENERIC TEMPLATE | I3: Crew | J3: (No. of Hours) | K3: Prod. Factor | L3: Adjusted Duration (hrs) | M3: Man-hours | N3: LSA Waste Disp. Vol (cm) | O3: Hazardous Waste Vol (cm) | Q3: Mixed Waste Volume (cm) | R3: Clean Waste Volume (cm) | S3: Materials, Consumables & Equipment | T3: Labor Cost | U3: LSA Waste Costs | V3: Hazardous Waste Costs | W3: LSA Waste Costs | X3: Mixed Waste Costs | Y3: Clean Waste Costs | Z3: Total Cost
A6: 1.0 | B6: Building XX | L6: =L8+L66+L118+L177+L185+L207 -> 647 | M6: =M8+M66+M118+M177+M185+M207 -> 6605 | N6: =N8+N66+N118+N177+N185+N207 -> 39.256953 | O6: =O8+O66+O118+O177+O185+O207 -> 425.0234 | Q6: =Q8+Q66+Q118+Q177+Q185+Q207 -> 4.4867312 | R6: =R8+R66+R118+R177+R185+R207 -> 1734.4379 | S6: =S8+S66+S118+S177+S185+S207+S214 -> 1843800 | T6: =T8+T66+T118+T177+T185+T207+T214 -> 11009187 | V6: =V8+V66+V118+V177+V185+V207+V214 -> 375239.61 | X6: =X8+X66+X118+X177+X185+X207+X214 -> 3961.1919 | Y6: =Y8+Y66+Y118+Y177+Y185+Y207+Y214 -> 918767.96 | Z6: =SUM(S6:Y6) -> 14150956
A8: 1.1 | B8: Project Management | S8: =IF(G18="US",(H46+M58+K60+K62+K64)*Inputs!C37,(H46+M58+K60+K62+K64)) -> 1843800 | T8: =I15 -> 256232.55 | Z8: =SUM(S8:Y8) -> 2100032.5
A10: 1.1.1 | B10: Staff | E10: Number | F10: Rate | G10: Duration, days* | H10: Use Factor | I10: Cost | J10: Man-hours
B11: =Inputs!A$51 -> Portfolio Manager | E11: 1 | F11: =Inputs!E51 -> 157.87 | G11: =Inputs!G$293 -> 105 | H11: 1 | I11: =H11*G11*F11*E11*8 -> 132610.8 | J11: =H11*G11*10 -> 1050
B12: =Inputs!A$50 -> Senior Project Manager / Characterization SME | E12: 1 | F12: =Inputs!E50 -> 127.28 | G12: =Inputs!G$293 -> 105 | H12: 0.5 | I12: =H12*G12*F12*E12*10 -> 66822 | J12: =H12*G12*10 -> 525
B13: =Inputs!A$49 -> Project Manager / Waste Management | E13: 1 | F13: =Inputs!E49 -> 108.19 | G13: =Inputs!G$293 -> 105 | H13: 0.5 | I13: =H13*G13*F13*E13*10 -> 56799.75 | J13: =H13*G13*10 -> 525
B14: =Inputs!A$48 -> Decom Technician / Safety SME | E14: 0 | F14: =Inputs!E48 -> 89.25 | G14: =Inputs!G$293 -> 105 | H14: 1 | I14: =H14*G14*F14*E14*10 -> 0 | J14: =H14*G14*10 -> 1050
E15: =SUM(E11:E14) -> 3 | I15: =SUM(I11:I14) -> 256232.55 | J15: =SUM(J11:J14) -> 3150
A17: 1.1.2 | B17: Equipment & Materials
G18: =Inputs!D85 -> US
C19: Equipment | F19: Quantity | G19: Rate | H19: Escalated Cost
C20: HEPA filter systems | F20: =IF(Inputs!$B$290=Inputs!$C$86,Inputs!C88,IF(Inputs!$B$290=Inputs!$G$86,Inputs!G88,IF(Inputs!$B$290=Inputs!$J$86,Inputs!J88,IF(Inputs!$B$290=Inputs!$M$86,Inputs!M88,"na")))) -> 2 | G20: =Inputs!D88 -> 3598.14 | H20: =G20*F20*(1+Inputs!$F$86) -> 11371.124
C21: Replacement filters | F21: =IF(Inputs!$B$290=Inputs!$C$86,Inputs!C89,IF(Inputs!$B$290=Inputs!$G$86,Inputs!G89,IF(Inputs!$B$290=Inputs!$J$86,Inputs!J89,IF(Inputs!$B$290=Inputs!$M$86,Inputs!M89,"na")))) -> 24 | G21: =Inputs!D89 -> 581.07 | H21: =G21*F21*(1+Inputs!$F$86) -> 22036.115
C22: Respirator | F22: =IF(Inputs!$B$290=Inputs!$C$86,Inputs!C90,IF(Inputs!$B$290=Inputs!$G$86,Inputs!G90,IF(Inputs!$B$290=Inputs!$J$86,Inputs!J90,IF(Inputs!$B$290=Inputs!$M$86,Inputs!M90,"na")))) -> 12 | G22: =Inputs!D90 -> 259 | H22: =G22*F22*(1+Inputs!$F$86) -> 4911.0725
C23: Rad/Vac wet-dry high eff. vacuum | F23: =IF(Inputs!$B$290=Inputs!$C$86,Inputs!C91,IF(Inputs!$B$290=Inputs!$G$86,Inputs!G91,IF(Inputs!$B$290=Inputs!$J$86,Inputs!J91,IF(Inputs!$B$290=Inputs!$M$86,Inputs!M91,"na")))) -> 1 | G23: =Inputs!D91 -> 3879 | H23: =G23*F23*(1+Inputs!$F$86) -> 6129.3598
C24: Rad/Vac wet-dry high eff. vacuum filters | F24: =IF(Inputs!$B$290=Inputs!$C$86,Inputs!C92,IF(Inputs!$B$290=Inputs!$G$86,Inputs!G92,IF(Inputs!$B$290=Inputs!$J$86,Inputs!J92,IF(Inputs!$B$290=Inputs!$M$86,Inputs!M92,"na")))) -> 5 | G24: =Inputs!D92 -> 412 | H24: =G24*F24*(1+Inputs!$F$86) -> 3255.0867
C25: Reciprocating Saws | F25: =IF(Inputs!$B$290=Inputs!$C$86,Inputs!C93,IF(Inputs!$B$290=Inputs!$G$86,Inputs!G93,IF(Inputs!$B$290=Inputs!$J$86,Inputs!J93,IF(Inputs!$B$290=Inputs!$M$86,Inputs!M93,"na")))) -> 5 | G25: =Inputs!D93 -> 1252.26 | H25: =G25*F25*(1+Inputs!$F$86) -> 9893.7254
C26: Pneumatic chipping hammers | F26: =IF(Inputs!$B$290=Inputs!$C$86,Inputs!C94,IF(Inputs!$B$290=Inputs!$G$86,Inputs!G94,IF(Inputs!$B$290=Inputs!$J$86,Inputs!J94,IF(Inputs!$B$290=Inputs!$M$86,Inputs!M94,"na")))) -> 2 | G26: =Inputs!D94 -> 1606.71 | H26: =G26*F26*(1+Inputs!$F$86) -> 5077.6508
C27: Chipping hammer blades | F27: =IF(Inputs!$B$290=Inputs!$C$86,Inputs!C95,IF(Inputs!$B$290=Inputs!$G$86,Inputs!G95,IF(Inputs!$B$290=Inputs!$J$86,Inputs!J95,IF(Inputs!$B$290=Inputs!$M$86,Inputs!M95,"na")))) -> 20 | G27: =Inputs!D95 -> 27.42 | H27: =G27*F27*(1+Inputs!$F$86) -> 866.54832
C28: Purchase an air compressor: | F28: =IF(Inputs!$B$290=Inputs!$C$86,Inputs!C96,IF(Inputs!$B$290=Inputs!$G$86,Inputs!G96,IF(Inputs!$B$290=Inputs!$J$86,Inputs!J96,IF(Inputs!$B$290=Inputs!$M$86,Inputs!M96,"na")))) -> 2 | G28: =Inputs!D96 -> 1723.44 | H28: =G28*F28*(1+Inputs!$F$86) -> 5446.5501
C29: Jackhammer | F29: =IF(Inputs!$B$290=Inputs!$C$86,Inputs!C97,IF(Inputs!$B$290=Inputs!$G$86,Inputs!G97,IF(Inputs!$B$290=Inputs!$J$86,Inputs!J97,IF(Inputs!$B$290=Inputs!$M$86,Inputs!M97,"na")))) -> 4 | G29: =Inputs!D97 -> 1417.11 | H29: =G29*F29*(1+Inputs!$F$86) -> 8956.9241
C30: Jackhammer Chisels | F30: =IF(Inputs!$B$290=Inputs!$C$86,Inputs!C98,IF(Inputs!$B$290=Inputs!$G$86,Inputs!G98,IF(Inputs!$B$290=Inputs!$J$86,Inputs!J98,IF(Inputs!$B$290=Inputs!$M$86,Inputs!M98,"na")))) -> 10 | G30: =Inputs!D98 -> 24.35 | H30: =G30*F30*(1+Inputs!$F$86) -> 384.76389
C31: Safety glasses | F31: =IF(Inputs!$B$290=Inputs!$C$86,Inputs!C99,IF(Inputs!$B$290=Inputs!$G$86,Inputs!G99,IF(Inputs!$B$290=Inputs!$J$86,Inputs!J99,IF(Inputs!$B$290=Inputs!$M$86,Inputs!M99,"na")))) -> 15 | G31: =Inputs!D99 -> 8.6 | H31: =G31*F31*(1+Inputs!$F$86) -> 203.83795
... C45: Crane rental for building removal | F45: =IF(Inputs!$B$290=Inputs!$C$86,Inputs!C113,IF(Inputs!$B$290=Inputs!$G$86,Inputs!G113,IF(Inputs!$B$290=Inputs!$J$86,Inputs!J113,IF(Inputs!$B$290=Inputs!$M$86,Inputs!M113,"na")))) -> 1 | G45: =Inputs!D113 -> 15600 | H45: =G45*F45*(1+Inputs!$F$86) -> 24650.171
H46: =SUM(H20:H45) -> 226414.4
C48: Consumables | E48: Quantity | G48: Duration | I48: # workers | J48: quantity | K48: Unit Qty | L48: Unit Cost | M48: Escalated Cost
C49: Coveralls | E49: =IF(Inputs!$B$290=Inputs!$C$86,Inputs!C117,IF(Inputs!$B$290=Inputs!$G$86,Inputs!D117,IF(Inputs!$B$290=Inputs!$J$86,Inputs!E117,IF(Inputs!$B$290=Inputs!$M$86,Inputs!F117,"na")))) -> 2 | F49: /man/day | G49: =Inputs!G$293 -> 105 | H49: days | I49: =Inputs!H$296 -> 24 | J49: =I49*G49*E49 -> 5040 | K49: 1 | L49: =Inputs!H117 -> 11 | M49: =J49/K49*L49*(1+Inputs!$F$86) -> 87602.916
C50: Hoods | E50: =IF(Inputs!$B$290=Inputs!$C$86,Inputs!C118,IF(Inputs!$B$290=Inputs!$G$86,Inputs!D118,IF(Inputs!$B$290=Inputs!$J$86,Inputs!E118,IF(Inputs!$B$290=Inputs!$M$86,Inputs!F118,"na")))) -> 0.1 | F50: /man/day | G50: =Inputs!G$293 -> 105 | H50: days | I50: =Inputs!H$296 -> 24 | J50: =I50*G50*E50 -> 252 | K50: 1 | L50: =Inputs!H118 -> 0 | M50: =J50/K50*L50*(1+Inputs!$F$86) -> 0
C51: Shoe covers | E51: =IF(Inputs!$B$290=Inputs!$C$86,Inputs!C119,IF(Inputs!$B$290=Inputs!$G$86,Inputs!D119,IF(Inputs!$B$290=Inputs!$J$86,Inputs!E119,IF(Inputs!$B$290=Inputs!$M$86,Inputs!F119,"na")))) -> 4 | F51: /man/day | G51: =Inputs!G$293 -> 105 | H51: days | I51: =Inputs!H$296 -> 24 | J51: =I51*G51*E51 -> 10080 | K51: 1 | L51: =Inputs!H119 -> 0.94 | M51: =J51/K51*L51*(1+Inputs!$F$86) -> 14972.135
C52: Latex gloves | E52: =IF(Inputs!$B$290=Inputs!$C$86,Inputs!C120,IF(Inputs!$B$290=Inputs!$G$86,Inputs!D120,IF(Inputs!$B$290=Inputs!$J$86,Inputs!E120,IF(Inputs!$B$290=Inputs!$M$86,Inputs!F120,"na")))) -> 4 | F52: /man/day | G52: =Inputs!G$293 -> 105 | H52: days | I52: =Inputs!H$296 -> 24 | J52: =I52*G52*E52 -> 10080 | K52: 1 | L52: =Inputs!H120 -> 0.94 | M52: =J52/K52*L52*(1+Inputs!$F$86) -> 14972.135
C53: Rubber overshoes | E53: =IF(Inputs!$B$290=Inputs!$C$86,Inputs!C121,IF(Inputs!$B$290=Inputs!$G$86,Inputs!D121,IF(Inputs!$B$290=Inputs!$J$86,Inputs!E121,IF(Inputs!$B$290=Inputs!$M$86,Inputs!F121,"na")))) -> 0.01 | F53: /man/day | G53: =Inputs!G$293 -> 105 | H53: days | I53: =Inputs!H$296 -> 24 | J53: =I53*G53*E53 -> 25.2 | K53: 1 | L53: =Inputs!H121 -> 3 | M53: =J53/K53*L53*(1+Inputs!$F$86) -> 119.45852
C54: Gloves | E54: =IF(Inputs!$B$290=Inputs!$C$86,Inputs!C122,IF(Inputs!$B$290=Inputs!$G$86,Inputs!D122,IF(Inputs!$B$290=Inputs!$J$86,Inputs!E122,IF(Inputs!$B$290=Inputs!$M$86,Inputs!F122,"na")))) -> 0.01 | F54: /man/day | G54: =Inputs!G$293 -> 105 | H54: days | I54: =Inputs!H$296 -> 24 | J54: =I54*G54*E54 -> 25.2 | K54: 1 | L54: =Inputs!H122 -> 2 | M54: =J54/K54*L54*(1+Inputs!$F$86) -> 79.639014
C55: Dosimeters | E55: =IF(Inputs!$B$290=Inputs!$C$86,Inputs!C123,IF(Inputs!$B$290=Inputs!$G$86,Inputs!D123,IF(Inputs!$B$290=Inputs!$J$86,Inputs!E123,IF(Inputs!$B$290=Inputs!$M$86,Inputs!F123,"na")))) -> 1 | F55: /man/year | G55: 0.25 | H55: year | I55: =Inputs!H$296 -> 24 | J55: =I55*G55*E55 -> 6 | K55: 1 | L55: =Inputs!H123 -> 200 | M55: =J55/K55*L55*(1+Inputs!$F$86) -> 1896.167
C56: TLDs | E56: =IF(Inputs!$B$290=Inputs!$C$86,Inputs!C124,IF(Inputs!$B$290=Inputs!$G$86,Inputs!D124,IF(Inputs!$B$290=Inputs!$J$86,Inputs!E124,IF(Inputs!$B$290=Inputs!$M$86,Inputs!F124,"na")))) -> 1 | F56: /man/mo | G56: 3 | H56: month | I56: =Inputs!H$296 -> 24 | J56: =I56*G56*E56 -> 72 | K56: 1 | L56: =Inputs!H124 -> 3 | M56: =J56/K56*L56*(1+Inputs!$F$86) -> 341.31006
C57: Bioassays | E57: =IF(Inputs!$B$290=Inputs!$C$86,Inputs!C125,IF(Inputs!$B$290=Inputs!$G$86,Inputs!D125,IF(Inputs!$B$290=Inputs!$J$86,Inputs!E125,IF(Inputs!$B$290=Inputs!$M$86,Inputs!F125,"na")))) -> 2 | F57: /man/year | G57: 0.5 | H57: year | I57: =Inputs!H$296 -> 24 | J57: =I57*G57*E57 -> 24 | K57: 1 | L57: =Inputs!H125 -> 250 | M57: =J57/K57*L57*(1+Inputs!$F$86) -> 9480.835
C58: (Bioassays for aver. crew & management) | M58: =SUM(M49:M57) -> 129464.59
C60: Small Tools - 2% of total labor costs = | G60: =(T6-T8) -> 10752955 | H60: labor costs x | I60: =Inputs!F128 -> 0.02 | J60: = | K60: =I60*G60 -> 215059.1
C62: HP Equipment Replacement - 5% of total labor | G62: =G60 -> 10752955 | H62: labor costs x | I62: =Inputs!F130 -> 0.05 | J62: = | K62: =I62*G62 -> 537647.74
C64: DGC OH &P on equipment and materials | G64: =R68+K62+K60+M58+H46 -> 1108585.8 | I64: =Inputs!F132 -> 0.08 | J64: = | K64: =I64*G64 -> 88686.866
A66: 1.2 | B66: Project Planning | J66: =J68+J75+J82 -> 415 | L66: =L68+L75+L82 -> 431 | M66: =M68+M75+M82 -> 2925 | T66: =T68+T75+T82 -> 270994.1 | Z66: =SUM(T66:Y66) -> 270994.1
A68: 1.2.1 | B68: Procedure Development and Review | J68: =I73 -> 160 | K68: 1 | L68: =J68*K68 -> 160 | M68: =L73 -> 240 | T68: =K73 -> 22935.2
D70: Staff | G70: Number | H70: Rate | I70: Duration | J70: PLF | K70: Cost | L70: Man-hours
D71: Project Specialist | G71: 2 | H71: =Inputs!E$48 -> 89.25 | I71: 80 | J71: 1 | K71: =G71*H71*I71*J71 -> 14280 | L71: =J71*I71*G71 -> 160
D72: Project Manager | G72: 1 | H72: =Inputs!E$49 -> 108.19 | I72: 80 | J72: 1 | K72: =G72*H72*I72*J72 -> 8655.2 | L72: =J72*I72*G72 -> 80
G73: =SUM(G71:G72) -> 3 | I73: =SUM(I71:I72) -> 160 | K73: =SUM(K71:K72) -> 22935.2 | L73: =SUM(L71:L72) -> 240
A75: 1.2.2 | B75: Preparation of QA and Safety Documents | J75: =I80 -> 160 | K75: 1.1 | L75: =J75*K75 -> 176 | M75: =L80 -> 240 | T75: =K80 -> 22935.2
D77: Staff | G77: Number | H77: Rate | I77: Duration | J77: PLF | K77: Cost | L77: Man-hours
D78: Project Specialist | G78: 2 | H78: =Inputs!E$48 -> 89.25 | I78: 80 | J78: 1 | K78: =J78*I78*H78*G78 -> 14280 | L78: =J78*I78*G78 -> 160
D79: Project Manager | G79: 1 | H79: =Inputs!E$49 -> 108.19 | I79: 80 | J79: 1 | K79: =J79*I79*H79*G79 -> 8655.2 | L79: =J79*I79*G79 -> 80
G80: =SUM(G78:G79) -> 3 | I80: =SUM(I78:I79) -> 160 | K80: =SUM(K78:K79) -> 22935.2 | L80: =SUM(L78:L79) -> 240
A82: 1.2.3 | B82: Site Mobilization and General Employee Training (GET) | J82: =J84+J97 -> 95 | K82: 1 | L82: =J82*K82 -> 95 | M82: =M84+M97 -> 2445 | T82: =T84+T97 -> 225123.7
C84: 1.2.3.1 | D84: Site Mobilization | J84: =F95 -> 40 | K84: 1 | L84: =J84*K84 -> 40 | M84: =J84*D87 -> 960 | T84: =I95 -> 85680
D86: Crew | G86: Rate, $/hr | H86: Cost, $/hr
D87: =I49 -> 24 | E87: Decom Technician / Safety SME | G87: =Inputs!E48 -> 89.25 | H87: =G87*D87 -> 2142
D89: Receipt of material and equipment | G89: 16 | H89: hr
D90: Staging of equipment | G90: 8 | H90: hr
D91: Set up office and amenities | G91: 12 | H91: hr
D92: Familiarize staff with facility | G92: 4 | H92: hr
G93: =SUM(G89:G92) -> 40 | H93: hr
D95: Total Cost = | F95: =G93 -> 40 | G95: x | H95: =H87 -> 2142 | I95: =H95*F95 -> 85680
C97: 1.2.3.2 | D97: General Employee Training (All proj. management and 3 crews of 4) | J97: =F116 -> 55 | K97: 1 | L97: =K97*J97 -> 55 | M97: =D104*F116 -> 1485 | S97: =J116*Inputs!C37 -> 54054 | T97: =K116 -> 139443.7
D99: Crew | G99: Rate, $/hr | H99: Cost, $/hr
D100: 1 | E100: =B11 -> Portfolio Manager | G100: =F11 -> 157.87 | H100: =G100*D100 -> 157.87
D101: 1 | E101: =B12 -> Senior Project Manager / Characterization SME | G101: =F12 -> 127.28 | H101: =G101*D101 -> 127.28
D102: 1 | E102: =B13 -> Project Manager / Waste Management | G102: =F13 -> 108.19 | H102: =G102*D102 -> 108.19
D103: =I49 -> 24 | E103: =B14 -> Decom Technician / Safety SME | G103: =F14 -> 89.25 | H103: =G103*D103 -> 2142
D104: =SUM(D100:D103) -> 27 | H104: =SUM(H100:H103) -> 2535.34
I106: Number | J106: Test | K106: Labor | L106: Total
H107: Unit Cost | I107: Required | J107: Cost | K107: Costs | L107: Cost
D108: In-Vivo | H108: 600 | I108: =IF(Inputs!B$290="D2",0,D$104) -> 27 | J108: =I108*H108 -> 16200 | K108: =F108*H$104 -> 0 | L108: =K108+J108 -> 16200
D109: In-Vitro | H109: 350 | I109: =IF(Inputs!B$290="D2",0,D$104) -> 27 | J109: =I109*H109 -> 9450 | K109: =F109*H$104 -> 0 | L109: =K109+J109 -> 9450
D110: Physical @ | F110: =IF(Inputs!B$290="D2",0,4) -> 4 | G110: hour and | H110: 150 | I110: =IF(Inputs!B$290="D2",0,D$104) -> 27 | J110: =I110*H110 -> 4050 | K110: =F110*H$104 -> 10141.36 | L110: =K110+J110 -> 14191.36
D111: Resp. Tests | F111: =IF(Inputs!B$290="D2",0,1) -> 1 | G111: hour and | H111: 50 | I111: =IF(Inputs!B$290="D2",0,D$104) -> 27 | J111: =I111*H111 -> 1350 | K111: =F111*H$104 -> 2535.34 | L111: =K111+J111 -> 3885.34
D112: Resp Fit Tests | F112: =IF(Inputs!B$290="D2",0,1) -> 1 | G112: hour and | H112: 25 | I112: =IF(Inputs!B$290="D2",0,D$104) -> 27 | J112: =I112*H112 -> 675 | K112: =F112*H$104 -> 2535.34 | L112: =K112+J112 -> 3210.34
D113: Blood Tests | F113: =IF(Inputs!B$290="D2",0,1) -> 1 | G113: hour and | H113: 125 | I113: =IF(Inputs!B$290="D2",0,D$104) -> 27 | J113: =I113*H113 -> 3375 | K113: =F113*H$104 -> 2535.34 | L113: =K113+J113 -> 5910.34
D114: OSHA recertification | F114: =IF(Inputs!B$290="D2",0,8) -> 8 | G114: hour | K114: =F114*H$104 -> 20282.72 | L114: =K114+J114 -> 20282.72
D115: Site specific 1 week of training | F115: =IF(Inputs!B$290="D2",0,40) -> 40 | G115: hour | K115: =F115*H$104 -> 101413.6 | L115: =K115+J115 -> 101413.6
F116: =SUM(F110:F115) -> 55 | J116: =SUM(J108:J115) -> 35100 | K116: =SUM(K110:K115) -> 139443.7 | L116: =SUM(L108:L115) -> 174543.7
A118: 1.3 | B118: Preliminary Site Investigation | J118: =J120+J122 -> 176 | L118: =L120+L122 -> 176 | M118: =M120+M122 -> 480 | T118: =T120+T122 -> 44658.24 | Z118: =SUM(T118:Y118) -> 44658.24
A120: 1.3.1 | B120: Decontamination Readiness Review - (Contractor staff cost included in Undistributed Costs) | J120: 80 | K120: 1 | L120: =K120*J120 -> 80
A122: 1.3.2 | B122: Site Preparation | H122: A | J122: =J124+J133+J151+J159 -> 96 | K122: 1 | L122: =L124+L133+L151+L159 -> 96 | M122: =M124+M133+M151+M159 -> 480 | T122: =T124+T133+T151+T159 -> 44658.24
B124: 1.3.2.1 | C124: Initial Site Survey | H124: A | J124: =F126 -> 16 | K124: 1 | L124: =K124*J124 -> 16 | M124: =L130 -> 80 | T124: =K130 -> 7443.04
E126: Estimated Duration | F126: 16 | G126: hrs
D127: Staff | G127: Number | H127: Rate | I127: Duration | J127: PLF | K127: Cost | L127: Man-hours
D128: Project Specialist | G128: 4 | H128: =Inputs!E$48 -> 89.25 | I128: =F126 -> 16 | J128: 1 | K128: =J128*I128*H128*G128 -> 5712 | L128: =J128*I128*G128 -> 64
D129: Project Manager | G129: 1 | H129: =Inputs!E$49 -> 108.19 | I129: =F126 -> 16 | J129: 1 | K129: =J129*I129*H129*G129 -> 1731.04 | L129: =J129*I129*G129 -> 16
G130: =SUM(G128:G129) -> 5 | I130: =SUM(I128:I129) -> 32 | K130: =SUM(K128:K129) -> 7443.04 | L130: =SUM(L128:L129) -> 80
B133: 1.3.2.2 | C133: Setup work areas | J133: =J135+J143 -> 32 | L133: =L135+L143 -> 32 | M133: =M135+M143 -> 160 | T133: =T135+T143 -> 14886.08
B135: 1.3.2.2.1 | C135: Setup boundaries, install HEPA filters & seal off openings | H135: A | J135: =F137 -> 16 | K135: 1 | L135: =K135*J135 -> 16 | M135: =L141 -> 80 | T135: =K141 -> 7443.04
E137: Estimated Duration | F137: 16 | G137: hrs
D138: Staff | G138: Number | H138: Rate | I138: Duration | J138: PLF | K138: Cost | L138: Man-hours
D139: Project Specialist | G139: 4 | H139: =Inputs!E$48 -> 89.25 | I139: =F137 -> 16 | J139: 1 | K139: =J139*I139*H139*G139 -> 5712 | L139: =J139*I139*G139 -> 64
D140: Project Manager | G140: 1 | H140: =Inputs!E$49 -> 108.19 | I140: =F137 -> 16 | J140: 1 | K140: =J140*I140*H140*G140 -> 1731.04 | L140: =J140*I140*G140 -> 16
G141: =SUM(G139:G140) -> 5 | I141: =SUM(I139:I140) -> 32 | K141: =SUM(K139:K140) -> 7443.04 | L141: =SUM(L139:L140) -> 80
B143: 1.3.2.2.2 | C143: Establish staging area | H143: A | J143: =F145 -> 16 | K143: 1 | L143: =K143*J143 -> 16 | M143: =L149 -> 80 | T143: =K149 -> 7443.04
E145: Estimated Duration | F145: 16 | G145: hrs
D146: Staff | G146: Number | H146: Rate | I146: Duration | J146: PLF | K146: Cost | L146: Man-hours
...

Sheet Summary 2026 
A1: SUMMARY OF U.S. DCE DATA - INFORMATION ONLY. Do not change data on this workbook OR hidden files
E2: Bldg 1
C3: 2009 | D3: 2026
C4: Removal | D4: Escalated | F4: Waste Volume
B5: Floor area | C5: ='BLDG 1 2009'!E4 -> 28033.8 | E5: sq ft | K5: Exchange rate | L5: 45946.508 | M5: =Inputs!C37 -> 1.54 | P5: Converted from US to Metric | V5: Waste Unit Rate, metric
K6: Summary | N6: Average Removal Rate* | P6: =H8 -> Asbestos | Q6: =H9 -> Asbestos tile | R6: Sys. Clean | S6: Sys. LLW | T6: Sys. Hazardous | U6: Sys. Mixed | V6: Asbestos | W6: Asbestos tile | X6: Sys. Clean | Y6: Sys. LLW | Z6: Sys. Hazardous | AA6: Sys. Mixed
A7: Asbestos removal | K7: =A8 -> Remove asbestos pipe insulation | L7: {=SUM(IF(($A$7:$A$317 = K7),$D$7:$D$316, 0))} -> 571.47621 | M7: 4 | N7: =(L7/M7*M$5)/Inputs!H$134 -> 721.84495 | O7: /meter | P7: {=SUM(IF(($H$7:$H$316 = P$6),$F$7:$F$316, 0))*Inputs!B136} -> 0.18461396 | V7: =P7/M7 -> 0.04615349
A8: Remove asbestos pipe insulation | C8: ='BLDG 1 2009'!Z196 -> 76.92036 | D8: =(LOOKUP(C$3,Inputs!$C$3:$T$5)+1)*C8 -> 121.54487 | E8: $/foot | F8: ='BLDG 1 2009'!AB196 -> 0.5 | G8: cuft/ft | H8: Asbestos | K8: =A9 -> Remove asbestos tile | L8: {=SUM(IF(($A$7:$A$317 = K8),$D$7:$D$316, 0))} -> 14.056082 | M8: 4 | N8: =(L8/M8*M$5)/Inputs!E$134 -> 58.251792 | O8: /m^2 | Q8: {=SUM(IF(($H$7:$H$316 = Q$6),$F$7:$F$316, 0))*Inputs!C135} -> 0.12246036 | W8: =Q8/M8 -> 0.03061509
A9: Remove asbestos tile | C9: ='BLDG 1 2009'!Z197 -> 2.097828 | D9: =(LOOKUP(C$3,Inputs!$C$3:$T$5)+1)*C9 -> 3.3148602 | E9: $/sq ft | F9: ='BLDG 1 2009'!AB197 -> 0.16152381 | G9: cuft/sqft | H9: Asbestos tile | K9: =A11 -> Remove systems and Components
K10: =A12 -> Sys. Clean | L10: {=SUM(IF(($A$7:$A$317 = K10),$D$7:$D$316, 0))} -> 182.17694 | M10: =COUNTIF($A$7:$A$317,"Sys. Clean") -> 5 | N10: =(L10/M10*M$5)/Inputs!E$134 -> 603.98815 | O10: /m^2 | R10: {=SUM(IF(($A$7:$A$317 = $K10),$F$7:$F$316, 0))*Inputs!C135} -> 1.0548593 | X10: =IF(R10>0,R10/$M10, " ") -> 0.21097185 | Y10: =IF(S10>0,S10/$M10, " ") | Z10: =IF(T10>0,T10/$M10, " ") | AA10: =IF(U10>0,U10/$M10, " ")
A11: Remove systems and Components | K11: =A13 -> Sys. LLW | L11: {=SUM(IF(($A$7:$A$317 = K11),$D$7:$D$316, 0))} -> 125.04972 | M11: =COUNTIF($A$7:$A$317,"Sys. LLW") -> 5 | N11: =(L11/M11*M$5)/Inputs!E$134 -> 414.58896 | O11: /m^2 | S11: {=SUM(IF(($A$7:$A$317 = $K11),$F$7:$F$316, 0))*Inputs!C135} -> 0.10913093 | X11: =IF(R11>0,R11/$M11, " ") | Y11: =IF(S11>0,S11/$M11, " ") -> 0.021826187 | Z11: =IF(T11>0,T11/$M11, " ") | AA11: =IF(U11>0,U11/$M11, " ")
A12: Sys. Clean | C12: ='BLDG 1 2009'!Z210 -> 17.540502 | D12: =(LOOKUP(C$3,Inputs!$C$3:$T$5)+1)*C12 -> 27.716434 | E12: /sqft | F12: ='BLDG 1 2009'!AB210 -> 0.17205855 | G12: cuft/sqft | H12: Clean | K12: =A14 -> Sys. Hazardous | L12: {=SUM(IF(($A$7:$A$317 = K12),$D$7:$D$316, 0))} -> 2.7017717 | M12: 4 | N12: =(L12/M12*M$5)/Inputs!E$134 -> 11.196793 | O12: /m^2 | T12: {=SUM(IF(($A$7:$A$317 = $K12),$F$7:$F$316, 0))*Inputs!C135} -> 0.001391892 | X12: =IF(R12>0,R12/$M12, " ") | Y12: =IF(S12>0,S12/$M12, " ") | Z12: =IF(T12>0,T12/$M12, " ") -> 0.000347973 | AA12: =IF(U12>0,U12/$M12, " ")
A13: Sys. LLW | C13: ='BLDG 1 2009'!Z211 -> 9.278232 | D13: =(LOOKUP(C$3,Inputs!$C$3:$T$5)+1)*C13 -> 14.660898 | E13: /sqft | F13: ='BLDG 1 2009'!AD211 -> 0.11739065 | G13: cuft/sqft | H13: LLW | K13: =A15 -> Sys. Mixed | L13: {=SUM(IF(($A$7:$A$317 = K13),$D$7:$D$316, 0))} -> 2.1284123 | M13: 4 | N13: =(L13/M13*M$5)/Inputs!E$134 -> 8.8206536 | O13: /m^2 | U13: {=SUM(IF(($A$7:$A$317 = $K13),$F$7:$F$316, 0))*Inputs!C135} -> 0.011526606 | X13: =IF(R13>0,R13/$M13, " ") | Y13: =IF(S13>0,S13/$M13, " ") | Z13: =IF(T13>0,T13/$M13, " ") | AA13: =IF(U13>0,U13/$M13, " ") -> 0.0028816514
A14: Sys. Hazardous | C14: ='BLDG 1 2009'!Z212 -> 1.4592259 | D14: =(LOOKUP(C$3,Inputs!$C$3:$T$5)+1)*C14 -> 2.3057799 | E14: /sqft | F14: ='BLDG 1 2009'!AC212 -> 0.0045659169 | G14: cuft/sqft | H14: Hazardous | K14: =A17 -> Decontaminate Structure | X14: =IF(R14>0,R14/$M14, " ") | Y14: =IF(S14>0,S14/$M14, " ") | Z14: =IF(T14>0,T14/$M14, " ") | AA14: =IF(U14>0,U14/$M14, " ")
A15: Sys. Mixed | C15: ='BLDG 1 2009'!Z213 -> 1.3469777 | D15: =(LOOKUP(C$3,Inputs!$C$3:$T$5)+1)*C15 -> 2.1284123 | E15: /sqft | F15: ='BLDG 1 2009'!AE213 -> 0.037811499 | G15: cuft/sqft | H15: Mixed | K15: Decon Clean | L15: {=SUM(IF(($A$7:$A$317 = K15),$D$7:$D$316, 0))} -> 4.3795835 | M15: 4 | N15: =(L15/M15*M$5)/Inputs!E$134 -> 18.15005 | O15: /m^2 | R15: {=SUM(IF(($A$7:$A$317 = $K15),$F$7:$F$316, 0))*Inputs!C135} -> 0.039622482 | X15: =IF(R15>0,R15/$M15, " ") -> 0.0099056206 | Y15: =IF(S15>0,S15/$M15, " ") | Z15: =IF(T15>0,T15/$M15, " ") | AA15: =IF(U15>0,U15/$M15, " ")
K16: Decon Contaminated | L16: {=SUM(IF(($A$7:$A$317 = K16),$D$7:$D$316, 0))} -> 129.0262 | M16: =COUNTIF($A$7:$A$317,"Decontaminate Structure") -> 5 | N16: =(L16/M16*M$5)/Inputs!E$134 -> 427.77255 | O16: /m^2 | S16: {=SUM(IF(($A$7:$A$317 = $K16),$F$7:$F$316, 0))*Inputs!C135} -> 0.0042224876 | X16: =IF(R16>0,R16/$M16, " ") | Y16: =IF(S16>0,S16/$M16, " ") -> 0.00084449752 | Z16: =IF(T16>0,T16/$M16, " ") | AA16: =IF(U16>0,U16/$M16, " ")
A17: Decontaminate Structure | K17: =A22 -> Final Survey | L17: {=SUM(IF(($A$7:$A$317 = K17),$D$7:$D$316, 0))} -> 73.096592 | M17: =COUNTIF($A$7:$A$317,"Final Survey") -> 5 | N17: =(L17/M17*M$5)/Inputs!E$134 -> 242.34392 | O17: /m^2 | R17: {=IF(AND($H$7:$H$133=R$6,$A9:$A$132=K$7),SUM($F$7:$F$133)," ")} | Y17: =IF(S17>0,S17/$M17, " ") | Z17: =IF(T17>0,T17/$M17, " ") | AA17: =IF(U17>0,U17/$M17, " ")
A18: Decon Clean | G18: cuft/sqft | H18: Clean | K18: =A24 -> Remove Building | L18: {=SUM(IF(($A$7:$A$317 = K18),$D$7:$D$316, 0))} -> 137.31046 | M18: =COUNTIF($A$7:$A$317,"Remove Building") -> 5 | N18: =(L18/M18*M$5)/Inputs!E$134 -> 455.23814 | O18: /m^2 | R18: {=SUM(IF(($A$7:$A$317 = $K18),$F$7:$F$316, 0))*Inputs!C135} -> 3.8543704 | X18: =IF(R18>0,R18/$M18, " ") -> 0.77087408 | Y18: =IF(S18>0,S18/$M18, " ") | Z18: =IF(T18>0,T18/$M18, " ") | AA18: =IF(U18>0,U18/$M18, " ")
A19: Decon Contaminated | C19: ='BLDG 1 2009'!Z360 -> 3.5097942 | D19: =(LOOKUP(C$3,Inputs!$C$3:$T$5)+1)*C19 -> 5.5459633 | E19: /sqft | F19: ='BLDG 1 2009'!AC360 -> 0.00045740915 | G19: cuft/sqft | H19: LLW | K19: =A29 -> Grade and seed | L19: {=SUM(IF(($A$7:$A$317 = K19),$D$7:$D$316, 0))} -> 4.7730304 | M19: =COUNTIF($A$7:$A$317,"Grade and seed") -> 5 | N19: =(L19/M19*M$5)/Inputs!E$134 -> 15.824471 | O19: /m^2
F20: ='BLDG 1 2009'!AD360 -> 0.036173224 | G20: cuft/sqft | H20: Hazardous | K20: =A30 -> Backfill | L20: {=SUM(IF(($A$7:$A$317 = K20),$D$7:$D$316, 0))} -> 1.7497077 | M20: 4 | N20: =(L20/M20*M$5)/Inputs!B$134 -> 23.786634 | O20: /m^3
G21: cuft/sqft | H21: Mixed | K21: =A33 -> Soil | L21: {=SUM(IF(($A$7:$A$317 = K21),$D$7:$D$316, 0))} -> 1.1557483 | M21: =COUNTIF($A$7:$A$317,"Soil") -> 2 | N21: =(L21/M21*M$5)/Inputs!B$134 -> 31.423947 | O21: /m^3 | R21: {=IF(AND($H$7:$H$133=R$6,$A11:$A$132=K$7),SUM($F$7:$F$133)," ")} | Y21: =IF(S21>0,S21/$M21, " ") | Z21: =IF(T21>0,T21/$M21, " ") | AA21: =IF(U21>0,U21/$M21, " ")
A22: Final Survey | C22: ='BLDG 1 2009'!Z474 -> 0.79571462 | D22: =(LOOKUP(C$3,Inputs!$C$3:$T$5)+1)*C22 -> 1.2573398 | E22: /sqft | K22: =A34 -> Pipe - clean | L22: {=SUM(IF(($A$7:$A$317 = K22),$D$7:$D$316, 0))} -> 104.52041 | M22: =COUNTIF($A$7:$A$317,"Pipe - clean") -> 1 | N22: =(L22/M22*M$5)/Inputs!H$134 -> 528.08867 | O22: /meter | R22: {=SUM(IF(($A$7:$A$317 = $K22),$F$7:$F$316, 0))*Inputs!B136} -> 0.099324409 | X22: =IF(R22>0,R22/$M22, " ") -> 0.099324409 | Y22: =IF(S22>0,S22/$M22, " ") | Z22: =IF(T22>0,T22/$M22, " ") | AA22: =IF(U22>0,U22/$M22, " ")
K23: =A35 -> Pipe - contaminated | L23: {=SUM(IF(($A$7:$A$317 = K23),$D$7:$D$316, 0))} -> 138.81079 | M23: =COUNTIF($A$7:$A$317,"Pipe - contaminated") -> 1 | N23: =(L23/M23*M$5)/Inputs!H$134 -> 701.34063 | O23: /meter | R23: {=IF(AND($H$7:$H$133=R$6,$A16:$A$132=K$7),SUM($F$7:$F$133)," ")} | S23: {=SUM(IF(($A$7:$A$317 = $K23),$F$7:$F$316, 0))*Inputs!B136} -> 0.099324409 | Y23: =IF(S23>0,S23/$M23, " ") -> 0.099324409 | Z23: =IF(T23>0,T23/$M23, " ") | AA23: =IF(U23>0,U23/$M23, " ")
A24: Remove Building | C24: ='BLDG 1 2009'!Z480 -> 7.1982247 | D24: =(LOOKUP(C$3,Inputs!$C$3:$T$5)+1)*C24 -> 11.374197 | E24: /sqft | F24: ='BLDG 1 2009'!AB480 -> 6.0596569 | G24: cuft/sqft | H24: Clean | K24: Hot Cell | X24: =IF(R24>0,R24/$M24, " ") | Y24: =IF(S24>0,S24/$M24, " ") | Z24: =IF(T24>0,T24/$M24, " ") | AA24: =IF(U24>0,U24/$M24, " ")
G25: cuft/sqft | H25: LLW | K25: Hot Cell Clean | L25: {=SUM(IF(($A$7:$A$317 = K25),$D$7:$D$316, 0))} -> 13.996379 | M25: =COUNTIF($A$7:$A$317,"Pipe - contaminated") -> 1 | N25: =(L25/M25*M$5)/Inputs!E$134 -> 232.01749 | O25: /m^2 | R25: {=SUM(IF(($A$7:$A$317 = $K25),$F$7:$F$316, 0))*Inputs!C135} -> 0.03725493 | X25: =IF(R25>0,R25/$M25, " ") -> 0.03725493 | Y25: =IF(S25>0,S25/$M25, " ") | Z25: =IF(T25>0,T25/$M25, " ") | AA25: =IF(U25>0,U25/$M25, " ")
G26: cuft/sqft | H26: Hazardous | K26: Hot Cell LLW | L26: {=SUM(IF(($A$7:$A$317 = K26),$D$7:$D$316, 0))} -> 7.2894463 | M26: =COUNTIF($A$7:$A$317,"Pipe - contaminated") -> 1 | N26: =(L26/M26*M$5)/Inputs!E$134 -> 120.83689 | O26: /m^2 | S26: {=SUM(IF(($A$7:$A$317 = $K26),$F$7:$F$316, 0))*Inputs!C135} -> 0.00077507058 | X26: =IF(R26>0,R26/$M26, " ") | Y26: =IF(S26>0,S26/$M26, " ") -> 0.00077507058 | Z26: =IF(T26>0,T26/$M26, " ") | AA26: =IF(U26>0,U26/$M26, " ")
G27: cuft/sqft | H27: Mixed | K27: Hot Cell Hazardous | L27: {=SUM(IF(($A$7:$A$317 = K27),$D$7:$D$316, 0))} -> 1.2759783 | M27: =COUNTIF($A$7:$A$317,"Pipe - contaminated") -> 1 | N27: =(L27/M27*M$5)/Inputs!E$134 -> 21.151846 | O27: /m^2 | T27: {=SUM(IF(($A$7:$A$317 = $K27),$F$7:$F$316, 0))*Inputs!C135} -> 0.083108951 | X27: =IF(R27>0,R27/$M27, " ") | Y27: =IF(S27>0,S27/$M27, " ") | Z27: =IF(T27>0,T27/$M27, " ") -> 0.083108951 | AA27: =IF(U27>0,U27/$M27, " ")
A29: Grade and seed | C29: ='BLDG 1 2009'!Z689 -> 0.38062963 | D29: =(LOOKUP(C$3,Inputs!$C$3:$T$5)+1)*C29 -> 0.60144779 | E29: /sqft | K29: * Adjusted to Australian dollars
A30: Backfill | C30: ='BLDG 1 2009'!Z690 -> 0.20719289 | D30: =(LOOKUP(C$3,Inputs!$C$3:$T$5)+1)*C30 -> 0.3273936 | E30: /cuft
A32: Remove Contaminated Soil and Pipe
A33: Soil | C33: ='BLDG 1 2009'!Z462 -> 0.25899111 | D33: =(LOOKUP(C$3,Inputs!$C$3:$T$5)+1)*C33 -> 0.409242 | E33: /cuft
A34: Pipe - clean | C34: ='BLDG 1 2009'!Z464 -> 66.14633 | D34: =(LOOKUP(C$3,Inputs!$C$3:$T$5)+1)*C34 -> 104.52041 | E34: /ft | F34: ='BLDG 1 2009'!AB464 -> 1.069 | G34: cuft/ft | H34: Clean
A35: Pipe - contaminated | C35: ='BLDG 1 2009'!Z466 -> 87.847195 | D35: =(LOOKUP(C$3,Inputs!$C$3:$T$5)+1)*C35 -> 138.81079 | E35: /ft | F35: ='BLDG 1 2009'!AD466 -> 1.069 | G35: cuft/ft | H35: LLW
E37: Bldg 2
C38: 2010 | D38: 2026
C39: Removal | D39: Escalated | F39: Waste Volume
A41: Asbestos removal
A42: Remove asbestos pipe insulation | C42: ='BLDG 2 2010'!AC1173 -> 74.6526 | D42: =(LOOKUP(C$38,Inputs!$C$3:$T$5)+1)*C42 -> 114.61475 | E42: $/foot | F42: ='BLDG 2 2010'!AE1173 -> 0.13973661 | G42: cuft/ft | H42: asbestos
A43: Remove asbestos tile | C43: ='BLDG 2 2010'!AC1174 -> 2.03598 | D43: =(LOOKUP(C$38,Inputs!$C$3:$T$5)+1)*C43 -> 3.1258567 | E43: $/sq ft | F43: ='BLDG 2 2010'!AE1174 -> 0.06422177 | G43: cuft/sqft | H43: asbestos tile
A45: Remove systems and Components
A46: Sys. Clean | C46: ='BLDG 2 2010'!AC1169 -> 37.819398 | D46: =(LOOKUP(C$38,Inputs!$C$3:$T$5)+1)*C46 -> 58.064432 | E46: $/sq ft | F46: ='BLDG 2 2010'!AE1169 -> 3.1070186 | G46: cuft/sqft | H46: Clean
A47: Sys. LLW | C47: ='BLDG 2 2010'!AC1170 -> 15.988166 | D47: =(LOOKUP(C$38,Inputs!$C$3:$T$5)+1)*C47 -> 24.546762 | E47: $/sq ft | F47: ='BLDG 2 2010'!AG1170 -> 0.17582369 | G47: cuft/sqft | H47: LLW
A48: Sys. Hazardous | C48: ='BLDG 2 2010'!AC1171 -> 0 | D48: =(LOOKUP(C$38,Inputs!$C$3:$T$5)+1)*C48 -> 0 | E48: $/sq ft | F48: ='BLDG 2 2010'!AF1171 -> 0 | G48: cuft/sqft | H48: Hazardous
A49: Sys. Mixed | C49: ='BLDG 2 2010'!AC1172 -> 0 | D49: =(LOOKUP(C$38,Inputs!$C$3:$T$5)+1)*C49 -> 0 | E49: $/sq ft | F49: ='BLDG 2 2010'!AH1172 -> 0 | G49: cuft/sqft | H49: Mixed
A51: Decontaminate Structure
A52: Decon Clean | F52: ='BLDG 2 2010'!AE1175 | G52: cuft/sqft | H52: Clean
A53: Decon Contaminated | C53: ='BLDG 2 2010'!AC1175 -> 13.625171 | D53: =(LOOKUP(C$38,Inputs!$C$3:$T$5)+1)*C53 -> 20.918837 | E53: /sqft | F53: ='BLDG 2 2010'!AF1171 -> 0 | G53: cuft/sqft | H53: LLW
F54: ='BLDG 2 2010'!AG1170 -> 0.17582369 | G54: cuft/sqft | H54: Hazardous
A55: Hot Cell | G55: cuft/sqft | H55: Mixed
A56: Hot Cell Clean | C56: ='BLDG 2 2010'!AC1177 -> 9.1163323 | D56: =(LOOKUP(C$38,Inputs!$C$3:$T$5)+1)*C56 -> 13.996379 | E56: /sqft | F56: ='BLDG 2 2010'!AE1177 -> 0.12220985 | G56: cuft/sqft | H56: Clean
A57: Hot Cell LLW | C57: ='BLDG 2 2010'!AC1178 -> 4.7478717 | D57: =(LOOKUP(C$38,Inputs!$C$3:$T$5)+1)*C57 -> 7.2894463 | E57: /sqft | F57: ='BLDG 2 2010'!AG1178 -> 0.0025425161 | G57: cuft/sqft | H57: LLW
A58: Hot Cell Hazardous | C58: ='BLDG 2 2010'!AC1179 -> 0.83108934 | D58: =(LOOKUP(C$38,Inputs!$C$3:$T$5)+1)*C58 -> 1.2759783 | E58: /sqft | F58: ='BLDG 2 2010'!AF1179 -> 0.27262788 | G58: cuft/sqft | H58: Hazardous
A61: Final Survey | C61: ='BLDG 2 2010'!AC1180 -> 16.957868 | D61: =(LOOKUP(C$38,Inputs!$C$3:$T$5)+1)*C61 -> 26.035553 | E61: /sqft
A63: Remove Building | C63: ='BLDG 2 2010'!AC1181 -> 15.22894 | D63: =(LOOKUP(C$38,Inputs!$C$3:$T$5)+1)*C63 -> 23.381116 | E63: /sqft | F63: ='BLDG 2 2010'!AE1181 -> 3.7552357 | G63: cuft/sqft | H63: Clean
G64: cuft/sqft | H64: LLW
G65: cuft/sqft | H65: Hazardous
G66: cuft/sqft | H66: Mixed
A68: Grade and seed | C68: ='BLDG 2 2010'!Z1114 -> 0.36940794 | D68: =(LOOKUP(C$3,Inputs!$C$3:$T$5)+1)*C68 -> 0.58371596 | E68: /sqft
A69: Backfill | C69: ='BLDG 2 2010'!Z1115 -> 0.18280404 | D69: =(LOOKUP(C$3,Inputs!$C$3:$T$5)+1)*C69 -> 0.28885583 | E69: /cuft
E71: Bldg 3
C72: 2010 | D72: 2026
C73: Removal | D73: Escalated | F73: Waste Volume
A75: Asbestos removal
A76: Remove asbestos pipe insulation | C76: ='Building 3 - 2010'!AC257 -> 82.12512 | D76: =(LOOKUP(C$72,Inputs!$C$3:$T$5)+1)*C76 -> 126.08737 | E76: $/foot | F76: ='Building 3 - 2010'!AE257 -> 0.035452083 | G76: cuft/ft | H76: asbestos
A77: Remove asbestos tile | C77: ='Building 3 - 2010'!AC258 -> 2.239776 | D77: =(LOOKUP(C$72,Inputs!$C$3:$T$5)+1)*C77 -> 3.4387464 | E77: $/sq ft | F77: ='Building 3 - 2010'!AE258 -> 0.12964529 | G77: cuft/sqft | H77: asbestos tile
A79: Remove systems and Components
A80: Sys. Clean | C80: ='Building 3 - 2010'!AC271 -> 8.3504456 | D80: =(LOOKUP(C$72,Inputs!$C$3:$T$5)+1)*C80 -> 12.820507 | E80: /sqft | F80: ='Building 3 - 2010'!AE271 -> 0.067918776 | G80: cuft/sqft | H80: Clean
A81: Sys. LLW | C81: ='Building 3 - 2010'!AC272 -> 12.197588 | D81: =(LOOKUP(C$72,Inputs!$C$3:$T$5)+1)*C81 -> 18.727057 | E81: /sqft | F81: ='Building 3 - 2010'!AG272 -> 0.06263739 | G81: cuft/sqft | H81: LLW
A82: Sys. Hazardous | C82: ='Building 3 - 2010'!AC273 -> 0.2579233 | D82: =(LOOKUP(C$72,Inputs!$C$3:$T$5)+1)*C82 -> 0.39599175 | E82: /sqft | F82: ='Building 3 - 2010'!AF273 | G82: cuft/sqft | H82: Hazardous
A83: Sys. Mixed | C83: ='Building 3 - 2010'!AC274 | D83: =(LOOKUP(C$72,Inputs!$C$3:$T$5)+1)*C83 -> 0 | E83: /sqft | H83: Mixed
A85: Decontaminate Structure
A86: Decon Clean | F86: ='Building 3 - 2010'!AG385 -> 0.0049801025 | G86: cuft/sqft | H86: LLW
A87: Decon Contaminated | C87: ='Building 3 - 2010'!AC385 -> 2.620707 | D87: =(LOOKUP(C$72,Inputs!$C$3:$T$5)+1)*C87 -> 4.0235929 | E87: /sqft | G87: cuft/sqft | H87: Hazardous
G88: cuft/sqft | H88: Mixed
A90: Final Survey | C90: ='Building 3 - 2010'!AC421 -> 5.2657621 | D90: =(LOOKUP(C$72,Inputs!$C$3:$T$5)+1)*C90 -> 8.0845675 | E90: /sqft
A92: Remove Building | C92: ='Building 3 - 2010'!AC502 -> 5.0315357 | D92: =(LOOKUP(C$72,Inputs!$C$3:$T$5)+1)*C92 -> 7.7249578 | E92: /sqft | F92: ='Building 3 - 2010'!AE502 -> 1.6171345 | G92: cuft/sqft | H92: Clean
G93: cuft/sqft | H93: LLW
G94: cuft/sqft | H94: Hazardous
G95: cuft/sqft | H95: Mixed
A97: Grade and seed | C97: ='Building 3 - 2010'!AC592 -> 0.3694406 | D97: =(LOOKUP(C$3,Inputs!$C$3:$T$5)+1)*C97 -> 0.58376756 | E97: /sqft
A98: Backfill | C98: ='Building 3 - 2010'!AC593 -> 0.1828202 | D98: =(LOOKUP(C$3,Inputs!$C$3:$T$5)+1)*C98 -> 0.28888136 | E98: /cuft
E100: Bldg 4
C101: 2012 | D101: 2026
C102: Removal | D102: Escalated | F102: Waste Volume
A104: Asbestos removal
A105: Remove asbestos pipe insulation | C105: ='Building 4 - 2012'!AC1055 -> 143.25316 | D105: =(LOOKUP(C$101,Inputs!$C$3:$T$5)+1)*C105 -> 209.22922 | E105: $/foot | F105: ='Building 4 - 2012'!AE1055 -> 1.3117582 | G105: cuft/ft | H105: asbestos
A106: Remove asbestos tile | C106: ='Building 4 - 2012'!AC1056 -> 2.859609 | D106: =(LOOKUP(C$101,Inputs!$C$3:$T$5)+1)*C106 -> 4.1766184 | E106: $/sq ft | F106: ='Building 4 - 2012'!AE1056 -> 0.046324082 | G106: cuft/sqft | H106: asbestos tile
A108: Remove systems and Components
A109: Sys. Clean | C109: ='Building 4 - 2012'!AC1051 -> 8.8489112 | D109: =(LOOKUP(C$101,Inputs!$C$3:$T$5)+1)*C109 -> 12.924328 | E109: $/sq ft | F109: ='Building 4 - 2012'!AE1051 -> 0.11332985 | G109: cuft/sqft | H109: Clean
A110: Sys. LLW | C110: ='Building 4 - 2012'!AC1052 -> 0.18770029 | D110: =(LOOKUP(C$101,Inputs!$C$3:$T$5)+1)*C110 -> 0.27414673 | E110: $/sq ft | F110: ='Building 4 - 2012'!AG1052 -> 0.0021378143 | G110: cuft/sqft | H110: LLW
A111: Sys. Hazardous | C111: ='Building 4 - 2012'!AC1053 -> 0 | D111: =(LOOKUP(C$101,Inputs!$C$3:$T$5)+1)*C111 -> 0 | E111: $/sq ft | F111: ='Building 3 - 2010'!AF299 | G111: cuft/sqft | H111: Hazardous
A112: Sys. Mixed | C112: ='Building 4 - 2012'!AC1054 | D112: =(LOOKUP(C$101,Inputs!$C$3:$T$5)+1)*C112 -> 0 | E112: $/sq ft | H112: Mixed
A114: Decontaminate Structure
A115: Decon Clean | C115: ='Building 4 - 2012'!AC1058 -> 2.9985733 | D115: =(LOOKUP(C$101,Inputs!$C$3:$T$5)+1)*C115 -> 4.3795835 | E115: /sqft | F115: ='Building 4 - 2012'!AE1058 -> 0.12499619 | G115: cuft/sqft | H115: Clean
A116: Decon Contaminated | C116: ='Building 4 - 2012'!AC1059 -> 2.2542698 | D116: =(LOOKUP(C$101,Inputs!$C$3:$T$5)+1)*C116 -> 3.2924868 | E116: /sqft | F116: ='Building 4 - 2012'!AG1059 -> 0.013393901 | G116: cuft/sqft | H116: LLW
G117: cuft/sqft | H117: Hazardous
G118: cuft/sqft | H118: Mixed
A120: Final Survey | C120: ='Building 4 - 2012'!AC1060 -> 18.845616 | D120: =(LOOKUP(C$101,Inputs!$C$3:$T$5)+1)*C120 -> 27.525072 | E120: /sqft
A122: Remove Building | C122: ='Building 4 - 2012'!AC1061 -> 16.992363 | D122: =(LOOKUP(C$101,Inputs!$C$3:$T$5)+1)*C122 -> 24.818293 | E122: /sqft | F122: ='Building 4 - 2012'!AE1061 -> 1.2117232 | G122: cuft/sqft | H122: Clean
A124: Grade and seed | C124: ='Building 4 - 2012'!AC984 -> 0.75116105 | D124: =(LOOKUP(C$3,Inputs!$C$3:$T$5)+1)*C124 -> 1.186939 | E124: /sqft
...

Sheet REPORT INFO TABLES
N4: Facility | O4: Description | P4: Cost 2026 AUD
N5: B17 | O5: Material Storage | P5: 3021527.9
N6: B18 | O6: Workshop | P6: 5178909.8
N7: B54 | O7: Warehouse | P7: 14159309
N8: B56 | O8: Mo99 Process Facility | P8: 14150956
N9: B70 | O9: Laboratories | P9: 765186.91
O10: Total | P10: =SUM(P5:P9) -> 37275890

Sheet BLDG 1 2009
P2: Mixed | Q2: Clean | R2: Materials, | U2: Hazardous | W2: Mixed | X2: Clean | AB2: Clean | AC2: Hazardous | AD2: LLW | AE2: Mixed
I3: Uncorrected Duration | K3: Adjusted | M3: LSA Waste | N3: Hazardous | O3: Ballast | P3: Waste | Q3: Waste | R3: Consumables, | T3: LSA Waste | U3: Waste | V3: >LSA Waste | W3: Waste | X3: Waste | Z3: Removal | AB3: Waste | AC3: Waste | AD3: Waste | AE3: Waste
C4: Total floor area | E4: 28033.8 | F4: sqft | H4: Crew | I4: (No. of Hours) | J4: Prod. Factor | K4: Duration | L4: Man-hours | M4: Disp. Vol (cf) | N4: Waste Vol (cf) | O4: Volume (cf) | P4: Volume (cf) | Q4: Volume (cf) | R4: & Equipment | S4: Labor Cost | T4: Cost | U4: Cost | V4: Cost | W4: Cost | X4: Cost | Y4: Total Cost | Z4: Unit Rate | AB4: Volume | AC4: Volume | AD4: Volume | AE4: Volume
B6: Grand Total Building 310 | Y6: 19285612
B8: Contingency = | D8: 0.25 | Y8: 3857122.4
A10: 2 | B10: Total Building 310 | Y10: 15428489
B12: ANL Oversight @ 24% | X12: 0.24 | Y12: 2986159.2
A14: ANL Tax | B14: General and Administration | X14: 0.029 | Y14: 74666.02
A16: ANL Tax | B16: IGPP/IGPE | X16: 0.027 | Y16: 67689.035
A18: ANL Tax | B18: Service Center | X18: 0.185 | Y18: 1811700.2 | Z18: On total
A20: ANL Tax | B20: Material and Subcontracts Tax | X20: 0.071 | Y20: 695301.14 | Z20: On total
A22: 2 | B22: Building 310 | L22: 41086.201 | M22: 62074.659 | N22: 140.82292 | O22: 142 | P22: 1060 | Q22: 252160.87 | R22: 1261378.4 | S22: 3091857.8 | T22: 4704633.4 | U22: 3758.9635 | V22: 0 | W22: 167932.27 | X22: 563413.09 | Y22: 9792973.8
A24: UNDISTRIBUTED COSTS | L24: 24428.571 | R24: 873670.71 | S24: 2100477.1 | T24: 0 | U24: 0 | V24: 0 | W24: 0 | X24: 0 | Y24: 2974147.8
C26: Project duration = | F26: 380 | G26: days/7days/wk = | H26: 54.285714 | I26: See Project Schedule
F27: 271.42857 | G27: working days
C28: Average crew size = | E28: 14842.629 | F28: man-hrs/ | G28: 4894.2098 | H28: sched-hrs = | I28: 3
C29: Labor cost = | E29: 991380.65 | F29: (Used to determine small tool costs and HP Supplies)
B31: 2.1 | C31: Project Management | L31: 24428.571 | S31: 1827257.1 | Y31: 1827257.1
C33: Staff | F33: Number | G33: Rate | H33: Duration, days* | I33: Use Factor | J33: Cost | K33: Man-hours
C34: Project Manager | F34: 1 | G34: 100.85 | H34: 271.42857 | I34: 1 | J34: 273735.71 | K34: 2714.2857
C35: Project Safety Manager | F35: 1 | G35: 78.56 | H35: 271.42857 | I35: 1 | J35: 213234.29 | K35: 2714.2857
C36: Project Specialist | F36: 1 | G36: 67.91 | H36: 271.42857 | I36: 1 | J36: 184327.14 | K36: 2714.2857
C37: Health Physicist | F37: 1 | G37: 89.16 | H37: 271.42857 | I37: 1 | J37: 242005.71 | K37: 2714.2857
C38: Chief HP Tech | F38: 1 | G38: 57.77 | H38: 271.42857 | I38: 1 | J38: 156804.29 | K38: 2714.2857
C39: Building Maintenance | F39: 1 | G39: 51.38 | H39: 271.42857 | I39: 1 | J39: 139460 | K39: 2714.2857
C40: Secretary | F40: 1 | G40: 31.79 | H40: 271.42857 | I40: 1 | J40: 86287.143 | K40: 2714.2857
C41: Project Control Specialist | F41: 1 | G41: 97.64 | H41: 271.42857 | I41: 1 | J41: 265022.86 | K41: 2714.2857
C42: HP Tech | F42: 2 | G42: 49.07 | H42: 271.42857 | I42: 1 | J42: 266380 | K42: 2714.2857
F43: 10 | J43: 1827257.1 | K43: 24428.571
B45: 2.2 | C45: Project Management Per Diem | S45: 273220 | Y45: 273220
G46: Per Diem | H46: Number of
C47: Staff | F47: Number | G47: Rate, $/day | H47: Days | I47: Total
C48: Project Manager | F48: 1 | G48: 161 | H48: 380 | I48: 61180
C49: Project Safety Manager | F49: 1 | G49: 161 | H49: 380 | I49: 61180
C50: Project Specialist | F50: 1 | G50: 161 | H50: 380 | I50: 61180
C51: Health Physicist | F51: 1 | G51: 161 | H51: 380 | I51: 61180
C52: Chief HP Tech | F52: 1 | G52: 75 | H52: 380 | I52: 28500
F53: 5 | I53: 273220
B55: 2.3 | C55: Equipment & Materials | R55: 873670.71 | Y55: 873670.71
C57: Equipment | F57: Quantity | G57: Rate | H57: Cost
C58: HEPA filter systems | F58: 2 | G58: 3598.14 | H58: 7196.28
C59: Replacement filters | F59: 24 | G59: 581.07 | H59: 13945.68
C60: Respirator | F60: 30 | G60: 259 | H60: 7770
C61: Rad/Vac wet-dry high eff. vacuum | F61: 4 | G61: 3879 | H61: 15516
C62: Rad/Vac wet-dry high eff. vacuum filters | F62: 10 | G62: 412 | H62: 4120
C63: Reciprocating Saws | F63: 10 | G63: 1252.26 | H63: 12522.6
C64: Pneumatic chipping hammers | F64: 4 | G64: 1606.71 | H64: 6426.84
C65: Chipping hammer blades | F65: 20 | G65: 27.42 | H65: 548.4
C66: Purchase an air compressor: | F66: 4 | G66: 1723.44 | H66: 6893.76
C67: Jackhammer | F67: 4 | G67: 1417.11 | H67: 5668.44
C68: Jackhammer Chisels | F68: 20 | G68: 24.35 | H68: 487
C69: Safety glasses | F69: 150 | G69: 8.6 | H69: 1290
... C75: Phone and computer hook-up | F75: 1 | G75: 250 | H75: 3121.2354
C76: Industrial hygiene instrumentation, calibration and hygienists - 1% of total activity $. | H76: 68188.26
C77: Tractor loader, wheeled | F77: 1 | G77: 7160.5905 | H77: 66343.879
C78: Wheeled Skid steer with conc. Hammer | F78: 2 | G78: 4421.3693 | H78: 32248.735
C79: Excavator | F79: 2 | G79: 28738.389 | H79: 226608.7
C80: Floor Shaver | F80: 2 | G80: 8000 | H80: 13667.725
C81: Wall Shaver | F81: 2 | G81: 15000 | H81: 25626.985
C82: Man lift | F82: 4 | G82: 4727.44 | H82: 91949.769
C83: Crane rental for building removal | F83: 1 | G83: 15600 | H83: 25626.985
H84: 661728.74
C86: Consumables | E86: Quantity | G86: Duration | I86: # workers | J86: quantity | K86: Unit Qty | L86: Unit Cost | M86: Cost
C87: Coveralls | E87: 2 | F87: /man/day | G87: 271.42857 | H87: days | I87: 6 | J87: 3257.1429 | K87: 1 | L87: 8.7 | M87: 28337.143
C88: Hoods | E88: 0.1 | F88: /man/day | G88: 271.42857 | H88: days | I88: 6 | J88: 162.85714 | K88: 1 | L88: 0.93333333 | M88: 152
C89: Shoe covers | E89: 4 | F89: /man/day | G89: 271.42857 | H89: days | I89: 6 | J89: 6514.2857 | K89: 1 | L89: 0.37 | M89: 2410.2857
C90: Latex gloves | E90: 4 | F90: /man/day | G90: 271.42857 | H90: days | I90: 6 | J90: 6514.2857 | K90: 1 | L90: 2 | M90: 13028.571
C91: Rubber overshoes | E91: 0.01 | F91: /man/day | G91: 271.42857 | H91: days | I91: 6 | J91: 16.285714 | K91: 1 | L91: 3 | M91: 48.857143
C92: Gloves | E92: 0.01 | F92: /man/day | G92: 271.42857 | H92: days | I92: 6 | J92: 16.285714 | K92: 1 | L92: 1.63 | M92: 26.545714
C93: Dosimeters | E93: 1 | F93: /man/year | G93: 1.043956 | H93: year | I93: 17 | J93: 17.747253 | K93: 1 | L93: 201.70588 | M93: 3579.7253
C94: TLDs | E94: 1 | F94: /man/mo | G94: 12.537116 | H94: month | I94: 17 | J94: 213.13098 | K94: 1 | L94: 3 | M94: 639.39294
C95: Bioassays | E95: 2 | F95: /man/year | G95: 1.043956 | H95: year | I95: 17 | J95: 35.494505 | K95: 1 | L95: 25 | M95: 887.36264
C96: (Bioassays for aver. crew & management) | M96: 49109.884
C98: Small Tools - 2% of total labor costs = | G98: 991380.65 | H98: labor costs x | I98: 0.02 | J98: = | K98: 19827.613
C100: HP Equipment Replacement - 5% of total labor | G100: 991380.65 | H100: labor costs x | I100: 0.05 | J100: = | K100: 49569.032
C102: DGC OH &P on equipment and materials | G102: 1167942.9 | I102: 0.08 | J102: = | K102: 93435.436
A104: ACTIVITIES | I104: 5307.2807 | K104: 5502.2098 | L104: 16657.629 | M104: 62074.659 | N104: 140.82292 | O104: 142 | P104: 1060 | Q104: 252160.87 | R104: 387707.68 | S104: 991380.65 | T104: 4704633.4 | U104: 3758.9635 | V104: 0 | W104: 167932.27 | X104: 563413.09 | Y104: 6818826
B106: 2.4 | C106: Procedure Development and Review | I106: 240 | J106: 1.1 | K106: 264 | L106: 440 | S106: 32779.12 | Y106: 32779.12
D108: Staff | G108: Number | H108: Rate | I108: Duration | J108: PLF | K108: Cost | L108: Man-hours
D109: Project Specialist | G109: 2 | H109: 67.91 | I109: 160 | J109: 1.1 | K109: 23904.32 | L109: 352
D110: Project Manager | G110: 1 | H110: 100.85 | I110: 80 | J110: 1.1 | K110: 8874.8 | L110: 88
G111: 3 | I111: 240 | K111: 32779.12 | L111: 440
B113: 2.5 | C113: Preparation of QA and Safety Documents | I113: 240 | J113: 1.1 | K113: 264 | L113: 440 | S113: 32779.12 | Y113: 32779.12
D115: Staff | G115: Number | H115: Rate | I115: Duration | J115: PLF | L115: Cost | M115: Man-hours
D116: Project Specialist | G116: 2 | H116: 67.91 | I116: 160 | J116: 1.1 | L116: 23904.32 | M116: 352
D117: Project Manager | G117: 1 | H117: 100.85 | I117: 80 | J117: 1.1 | L117: 8874.8 | M117: 88
G118: 3 | I118: 240 | L118: 32779.12 | M118: 440
B120: 2.6 | C120: Site Mobilization and General Employee Training (GET) | I120: 80 | J120: 1 | K120: 80 | L120: 1095 | R120: 22100 | S120: 70221.55 | Y120: 92321.55
C122: 2.6.1 | D122: Site Mobilization | I122: 40 | L122: 160 | S122: 9571.84 | Y122: 9571.84
D124: Crew | G124: Rate, $/hr | H124: Cost, $/hr
D125: 1 | E125: HP Tech | G125: 64.477 | H125: 64.477
D126: 3 | E126: Decon Techs | G126: 58.273 | H126: 174.819
D127: 4 | H127: 239.296
D129: Receipt of material and equipment | G129: 16 | H129: hr
D130: Staging of equipment | G130: 8 | H130: hr
D131: Set up office and amenities | G131: 12 | H131: hr
D132: Familiarize staff with facility | G132: 4 | H132: hr
G133: 40 | H133: hr
D135: Total Cost = | F135: 40 | G135: x | H135: 239.296 | I135: 9571.84
C137: 2.6.2 | D137: General Employee Training (All proj. management and 2 crews of 4) | I137: 40 | J137: 1 | L137: 935 | R137: 22100 | S137: 60649.71 | Y137: 82749.71
...

Sheet BLDG 2 2010
C1: G Wing | E1: 15352 | F1: sqft
C2: H Wing | E2: 47210 | F2: sqft | P2: Mixed | Q2: Clean | R2: Lead | S2: Materials, | V2: Hazardous | X2: Mixed | Y2: Clean | Z2: Lead
C3: F Wing | E3: 71860 | F3: sqft | I3: Uncorrected Duration | K3: Adjusted | M3: LSA Waste | N3: Hazardous | O3: Ballast | P3: Waste | Q3: Waste | R3: Waste | S3: Consumables, | U3: LSA Waste | V3: Waste | W3: >LSA Waste | X3: Waste | Y3: Waste | Z3: Waste | AE3: Clean | AF3: Hazardous | AG3: LLW | AH3: Mixed
C4: Fallout shelter | E4: 18264 | F4: sqft | H4: Crew | I4: (No. of Hours) | J4: Prod. Factor | K4: Duration | L4: Man-hours | M4: Disp. Vol (cf) | N4: Waste Vol (cf) | O4: Volume (cf) | P4: Volume (cf) | Q4: Volume (cf) | R4: Volume (cf) | S4: & Equipment | T4: Labor Cost | U4: Cost | V4: Cost | W4: Cost | X4: Cost | Y4: Cost | Z4: Cost | AA4: Total Cost | AC4: Removal | AE4: Waste | AF4: Waste | AG4: Waste | AH4: Waste
AC5: Unit Rate | AE5: Volume | AF5: Volume | AG5: Volume | AH5: Volume
B6: Grand Total Building 212 F, G, H wings and Fallout Shelter | AA6: 45165635
B8: Contingency = | D8: 0.4 | AA8: 12904467
A10: 1 | B10: Total Building 212 F, G, H wings and Fallout Shelter | AA10: 32261168
B12: ANL Oversight @ 24% | Y12: 0.24 | AA12: 6244097.1
A14: ANL Tax | B14: General and Administration | Y14: 0.029 | AA14: 156127.6
A16: ANL Tax | B16: IGPP/IGPE | Y16: 0.027 | AA16: 141538.64
A18: ANL Tax | B18: Service Center | Y18: 0.185 | AA18: 3788288.1 | AB18: On total
A20: ANL Tax | B20: Material and Subcontracts Tax | Y20: 0.071 | AA20: 1453883.6 | AB20: On total
A22: 1 | B22: Building 212 F, G, H wings and Fallout Shelter | L22: 156619.43 | M22: 34784.446 | N22: 19591.039 | O22: 160.2 | P22: 0 | Q22: 669956.44 | R22: 346.82 | S22: 4114974.6 | T22: 11095979 | U22: 1855054.5 | V22: 163262.65 | W22: 0 | X22: 0 | Y22: 3122692.8 | Z22: 125269.37 | AA22: 20477233
A24: UNDISTRIBUTED COSTS | L24: 151131.43 | S24: 3365691.1 | T24: 10941979 | U24: 0 | V24: 0 | W24: 0 | X24: 0 | Y24: 0 | AA24: 14307670
C26: Project duration = | F26: 1133 | G26: days/7days/wk = | H26: 161.85714 | I26: See Project Schedule - Starts with Site Mobilization and ends with Site Demobilization
F27: 809.28571 | G27: working days
C29: Labor cost = | E29: 4307399.2 | F29: (Used to determine small tool costs and HP Supplies)
B31: 1.1 | C31: Project Management | L31: 77691.429 | T31: 5634052.9 | AA31: 5634052.9
C33: Staff | F33: Number | G33: Rate | H33: Duration, days* | I33: Use Factor | J33: Cost | K33: Man-hours
C34: Project Manager | F34: 1 | G34: 130 | H34: 809.28571 | I34: 1 | J34: 841657.14 | K34: 6474.2857
C35: Project Safety Manager | F35: 1 | G35: 100 | H35: 809.28571 | I35: 1 | J35: 647428.57 | K35: 6474.2857
C36: Project Specialist | F36: 1 | G36: 85 | H36: 809.28571 | I36: 1 | J36: 550314.29 | K36: 6474.2857
C37: Health Physicist | F37: 1 | G37: 120 | H37: 809.28571 | I37: 1 | J37: 776914.29 | K37: 6474.2857
C38: Chief HP Tech | F38: 1 | G38: 57.77 | H38: 809.28571 | I38: 1 | J38: 374019.49 | K38: 6474.2857
C39: Building Maintenance | F39: 1 | G39: 51.38 | H39: 809.28571 | I39: 1 | J39: 332648.8 | K39: 6474.2857
C40: Secretary | F40: 1 | G40: 31.79 | H40: 809.28571 | I40: 1 | J40: 205817.54 | K40: 6474.2857
C41: Project Control Specialist | F41: 1 | G41: 98 | H41: 809.28571 | I41: 1 | J41: 634480 | K41: 6474.2857
C42: HP Tech | F42: 4 | G42: 49.07 | H42: 809.28571 | I42: 1 | J42: 1270772.8 | K42: 25897.143
F43: 12 | J43: 5634052.9 | K43: 77691.429
B45: 1.2 | C45: Project Management Per Diem | T45: 1154527 | AA45: 1154527
G46: Per Diem | H46: Number of
C47: Staff | F47: Number | G47: Rate, $/day | H47: Days | I47: Total
C48: Project Manager | F48: 1 | G48: 161 | H48: 1133 | I48: 182413
C49: Project Safety Manager | F49: 1 | G49: 161 | H49: 1133 | I49: 182413
C50: Project Specialist | F50: 1 | G50: 161 | H50: 1133 | I50: 182413
C51: Health Physicist | F51: 1 | G51: 161 | H51: 1133 | I51: 182413
C52: Chief HP Tech | F52: 1 | G52: 75 | H52: 1133 | I52: 84975
C53: HP Tech | F53: 4 | G53: 75 | H53: 1133 | I53: 339900
F54: 9 | I54: 1154527
B56: 1.3 | C56: Crew cost - 4 crews from mobilization through final survey | L56: 59451.429 | T56: 3362275.5 | AA56: 3362275.5
C58: Duration | D58: 867 | E58: days/7days/wk = | F58: 123.85714 | G58: 619.28571 | H58: working days | I58: See Project Schedule - Starts with Site Mobilization and ends with Remove Building
C61: Staff | F61: Number | G61: Rate | H61: Duration, days* | I61: Use Factor | J61: Cost | K61: Man-hours
C62: Decon Techs | F62: 12 | G62: 56.555 | H62: 619.28571 | I62: 1 | J62: 3362275.5 | K62: 59451.429
F63: 12 | J63: 3362275.5 | K63: 59451.429
B65: 1.4 | C65: Crew cost - 4 crews from final survey through site demobilization | L65: 13988.571 | T65: 791123.66 | AA65: 791123.66
C67: Duration | D67: 204 | E67: days/7days/wk = | F67: 29.142857 | G67: 145.71429 | H67: working days | I67: See Project Schedule - Starts with Remove Building and ends with Site Demobilization
C70: Staff | F70: Number | G70: Rate | H70: Duration, days* | I70: Use Factor | J70: Cost | K70: Man-hours
C71: Decon Techs | F71: 12 | G71: 56.555 | H71: 145.71429 | I71: 1 | J71: 791123.66 | K71: 13988.571
F72: 12 | J72: 791123.66 | K72: 13988.571
B74: 1.5 | C74: Equipment & Materials | S74: 3365691.1 | AA74: 3365691.1
C76: Equipment | F76: Quantity | G76: Rate | H76: Cost
C77: HEPA filter systems | F77: 2 | G77: 3598.14 | H77: 7196.28
C78: Replacement filters | F78: 24 | G78: 581.07 | H78: 13945.68
C79: Respirator | F79: 30 | G79: 259 | H79: 7770
C80: Rad/Vac wet-dry high eff. vacuum | F80: 4 | G80: 3879 | H80: 15516
C81: Rad/Vac wet-dry high eff. vacuum filters | F81: 10 | G81: 412 | H81: 4120
C82: Reciprocating Saws | F82: 6 | G82: 1252.26 | H82: 7513.56
C83: Pneumatic chipping hammers | F83: 2 | G83: 1606.71 | H83: 3213.42
C84: Chipping hammer blades | F84: 20 | G84: 27.42 | H84: 548.4
C85: Purchase an air compressor: | F85: 4 | G85: 1723.44 | H85: 6893.76
C86: Jackhammer | F86: 2 | G86: 1417.11 | H86: 2834.22
C87: Jackhammer Chisels | F87: 20 | G87: 24.35 | H87: 487
C88: Safety glasses | F88: 150 | G88: 8.6 | H88: 1290
... C94: Phone and computer hook-up | F94: 1 | G94: 250 | H94: 8501.2594
C95: Industrial hygiene instrumentation, calibration and hygienists - 1% of total activity $. | H95: 103229.62
C96: Tractor loader, wheeled | F96: 1 | G96: 7160.5905 | H96: 235732.51
C97: Wheeled Skid steer with conc. Hammer | F97: 2 | G97: 4421.3693 | H97: 48808.896
C98: Excavator | F98: 2 | G98: 28738.389 | H98: 317252.18
C99: Shot Blaster | F99: 2 | G99: 3522.318 | H99: 25922.656
C100: Floor Shaver | F100: 2 | G100: 8000 | H100: 400569.49
C101: Wall Shaver | F101: 2 | G101: 15000 | H101: 751067.79
C102: Core Drill & Bits | F102: 1 | G102: 10000 | H102: 10000
C103: Man lift | F103: 2 | G103: 4727.44 | H103: 210925.32
C104: Crane rental for building removal | F104: 2 | G104: 15600 | H104: 151711.75
H105: 2373166
C107: Consumables | E107: Quantity | G107: Duration | I107: # workers | J107: quantity | K107: Unit Qty | L107: Unit Cost | M107: Cost
C108: Coveralls | E108: 2 | F108: /man/day | G108: 809.28571 | H108: days | I108: 16 | J108: 25897.143 | K108: 1 | L108: 8.7 | M108: 225305.14 | N108: 4 crews of 4 (3 decon techs and 1 HP tech per crew. HP techs with staff)
C109: Hoods | E109: 0.5 | F109: /man/day | G109: 809.28571 | H109: days | I109: 16 | J109: 6474.2857 | K109: 1 | L109: 0.93333333 | M109: 6042.6667 | N109: 4 crews of 4 (3 decon techs and 1 HP tech per crew. HP techs with staff)
C110: Shoe covers | E110: 4 | F110: /man/day | G110: 809.28571 | H110: days | I110: 16 | J110: 51794.286 | K110: 1 | L110: 0.37 | M110: 19163.886 | N110: 4 crews of 4 (3 decon techs and 1 HP tech per crew. HP techs with staff)
C111: Latex gloves | E111: 4 | F111: /man/day | G111: 809.28571 | H111: days | I111: 16 | J111: 51794.286 | K111: 1 | L111: 2 | M111: 103588.57 | N111: 4 crews of 4 (3 decon techs and 1 HP tech per crew. HP techs with staff)
C112: Rubber overshoes | E112: 0.01 | F112: /man/day | G112: 809.28571 | H112: days | I112: 16 | J112: 129.48571 | K112: 1 | L112: 3 | M112: 388.45714 | N112: 4 crews of 4 (3 decon techs and 1 HP tech per crew. HP techs with staff)
C113: Gloves | E113: 0.5 | F113: /man/day | G113: 809.28571 | H113: days | I113: 16 | J113: 6474.2857 | K113: 1 | L113: 1.63 | M113: 10553.086 | N113: 4 crews of 4 (3 decon techs and 1 HP tech per crew. HP techs with staff)
C114: Dosimeters | E114: 1 | F114: /man/year | G114: 3.1126374 | H114: year | I114: 24 | J114: 74.703297 | K114: 1 | L114: 197.125 | M114: 14725.887
C115: TLDs | E115: 1 | F115: /man/mo | G115: 37.380403 | H115: month | I115: 24 | J115: 897.12966 | K115: 1 | L115: 3 | M115: 2691.389
C116: Bioassays | E116: 2 | F116: /man/year | G116: 3.1126374 | H116: year | I116: 24 | J116: 149.40659 | K116: 1 | L116: 25 | M116: 3735.1648
C117: (Bioassays for aver. crew & management) | M117: 386194.25
C119: Small Tools - 2% of total labor costs = | G119: 4307399.2 | H119: labor costs x | I119: 0.02 | J119: = | K119: 86147.984
C121: HP Equipment Replacement - 5% of total labor | G121: 4307399.2 | H121: labor costs x | I121: 0.05 | J121: = | K121: 215369.96
C123: DGC OH &P on equipment and materials | G123: 3810161.7 | I123: 0.08 | J123: = | K123: 304812.93
A125: ACTIVITIES | I125: 19612.076 | K125: 21301.146 | L125: 5488 | M125: 34784.446 | N125: 19591.039 | O125: 160.2 | P125: 0 | Q125: 669956.44 | R125: 346.82 | S125: 749283.52 | T125: 154000 | U125: 1855054.5 | V125: 163262.65 | W125: 0 | X125: 0 | Y125: 3122692.8 | Z125: 125269.37 | AA125: 6169562.9
B127: 1.6 | C127: Project Engineering | I127: 640 | K127: 704 | L127: 1232 | M127: 0 | N127: 0 | O127: 0 | P127: 0 | Q127: 0 | R127: 0 | S127: 0 | T127: 112640 | U127: 0 | V127: 0 | W127: 0 | X127: 0 | Y127: 0 | Z127: 0 | AA127: 112640
C129: 1.6.1 | D129: Procedure Development and Review - Offsite | I129: 320 | J129: 1.1 | K129: 352 | L129: 616 | T129: 56320 | AA129: 56320
D131: Staff | G131: Number | H131: Rate | I131: Duration | J131: PLF | K131: Cost | L131: Man-hours
D132: Project Specialist | G132: 2 | H132: 85 | I132: 240 | J132: 1.1 | K132: 44880 | L132: 528
D133: Project Manager | G133: 1 | H133: 130 | I133: 80 | J133: 1.1 | K133: 11440 | L133: 88
G134: 3 | I134: 320 | K134: 56320 | L134: 616
C136: 1.6.2 | D136: Preparation of QA and Safety Documents - Offsite | I136: 320 | J136: 1.1 | K136: 352 | L136: 616 | T136: 56320 | AA136: 56320
D138: Staff | G138: Number | H138: Rate | I138: Duration | J138: PLF | L138: Cost | M138: Man-hours
D139: Project Specialist | G139: 2 | H139: 85 | I139: 240 | J139: 1.1 | L139: 44880 | M139: 528
...

Sheet Building 3 - 2010
P2: Mixed | Q2: Clean | R2: Lead | S2: Materials, | V2: Hazardous | X2: Mixed | Y2: Clean | Z2: Lead
A3: Total Floor area | C3: 65787 | I3: Uncorrected Duration | K3: Adjusted | M3: LSA Waste | N3: Hazardous | O3: Ballast | P3: Waste | Q3: Waste | R3: Waste | S3: Consumables, | U3: LSA Waste | V3: Waste | W3: >LSA Waste | X3: Waste | Y3: Waste | Z3: Waste | AE3: Clean | AF3: Hazardous | AG3: LLW | AH3: Mixed
H4: Crew | I4: (No. of Hours) | J4: Prod. Factor | K4: Duration | L4: Man-hours | M4: Disp. Vol (cf) | N4: Waste Vol (cf) | O4: Volume (cf) | P4: Volume (cf) | Q4: Volume (cf) | R4: Volume (cf) | S4: & Equipment | T4: Labor Cost | U4: Cost | V4: Cost | W4: Cost | X4: Cost | Y4: Cost | Z4: Cost | AA4: Total Cost | AC4: Removal | AE4: Waste | AF4: Waste | AG4: Waste | AH4: Waste
AC5: Unit Rate | AE5: Volume | AF5: Volume | AG5: Volume | AH5: Volume
B6: Grand Total Building 200 MA/MB wings | AA6: 28790464
B8: Contingency = | D8: 0.4 | AA8: 8225846.9
A10: 2 | B10: Total Building 200 MA/MB wings | AA10: 20564617
B12: ANL Oversight @ 24% | Y12: 0.24 | AA12: 3980248.5
A14: ANL Tax | B14: General and Administration | Y14: 0.029 | AA14: 99522.259
A16: ANL Tax | B16: IGPP/IGPE | Y16: 0.027 | AA16: 90222.644
A18: ANL Tax | B18: Service Center | Y18: 0.185 | AA18: 2414813.2 | AB18: On total
A20: ANL Tax | B20: Material and Subcontracts Tax | Y20: 0.071 | AA20: 926766.16 | AB20: On total
A22: 2 | B22: Building 200 | L22: 108921.14 | M22: 8626.852 | N22: 69936 | O22: 60 | P22: 0 | Q22: 150531.93 | R22: 9.6 | S22: 3564583.3 | T22: 7723690 | U22: 460070.02 | V22: 505924.36 | W22: 0 | X22: 0 | Y22: 795287.22 | Z22: 3489.6 | AA22: 13053045
A24: UNDISTRIBUTED COSTS | L24: 102857.14 | S24: 1690181.6 | T24: 7569690 | U24: 0 | V24: 0 | W24: 0 | X24: 0 | Y24: 0 | AA24: 9259871.6
C26: Project duration = | F26: 830 | G26: days/7days/wk = | H26: 118.57143 | I26: See Project Schedule - Starts with Site Mobilization and ends with Site Demobilization
F27: 592.85714 | G27: working days
C29: Labor cost = | E29: 2752298.3 | F29: (Used to determine small tool costs and HP Supplies)
B31: 2.1 | C31: Project Management | L31: 56914.286 | T31: 4125621.7 | AA31: 4125621.7
C33: Staff | F33: Number | G33: Rate | H33: Duration, days* | I33: Use Factor | J33: Cost | K33: Man-hours
C34: Project Manager | F34: 1 | G34: 130 | H34: 592.85714 | I34: 1 | J34: 616571.43 | K34: 4742.8571
C35: Project Safety Manager | F35: 1 | G35: 100 | H35: 592.85714 | I35: 1 | J35: 474285.71 | K35: 4742.8571
C36: Project Specialist | F36: 1 | G36: 85 | H36: 592.85714 | I36: 1 | J36: 403142.86 | K36: 4742.8571
C37: Health Physicist | F37: 1 | G37: 120 | H37: 592.85714 | I37: 1 | J37: 569142.86 | K37: 4742.8571
C38: Chief HP Tech | F38: 1 | G38: 57.77 | H38: 592.85714 | I38: 1 | J38: 273994.86 | K38: 4742.8571
C39: Building Maintenance | F39: 1 | G39: 51.38 | H39: 592.85714 | I39: 1 | J39: 243688 | K39: 4742.8571
C40: Secretary | F40: 1 | G40: 31.79 | H40: 592.85714 | I40: 1 | J40: 150775.43 | K40: 4742.8571
C41: Project Control Specialist | F41: 1 | G41: 97.64 | H41: 592.85714 | I41: 1 | J41: 463092.57 | K41: 4742.8571
C42: HP Tech | F42: 4 | G42: 49.07 | H42: 592.85714 | I42: 1 | J42: 930928 | K42: 18971.429
F43: 12 | J43: 4125621.7 | K43: 56914.286
B45: 2.2 | C45: Project Management Per Diem | T45: 845770 | AA45: 845770
G46: Per Diem | H46: Number of
C47: Staff | F47: Number | G47: Rate, $/day | H47: Days | I47: Total
C48: Project Manager | F48: 1 | G48: 161 | H48: 830 | I48: 133630
C49: Project Safety Manager | F49: 1 | G49: 161 | H49: 830 | I49: 133630
C50: Project Specialist | F50: 1 | G50: 161 | H50: 830 | I50: 133630
C51: Health Physicist | F51: 1 | G51: 161 | H51: 830 | I51: 133630
C52: Chief HP Tech | F52: 1 | G52: 75 | H52: 830 | I52: 62250
C53: HP Tech | F53: 4 | G53: 75 | H53: 830 | I53: 249000
F54: 9 | I54: 845770
B56: 2.3 | C56: Crew cost - 4 crews from mobilization through final survey | L56: 34971.429 | T56: 1977809.1 | AA56: 1977809.1
C58: Duration | D58: 510 | E58: days/7days/wk = | F58: 72.857143 | G58: 364.28571 | H58: working days | I58: See Project Schedule - Starts with Site Mobilization and ends with Final Survey
C61: Staff | F61: Number | G61: Rate | H61: Duration, days* | I61: Use Factor | J61: Cost | K61: Man-hours
C62: Decon Techs | F62: 12 | G62: 56.555 | H62: 364.28571 | I62: 1 | J62: 1977809.1 | K62: 34971.429
F63: 12 | J63: 1977809.1 | K63: 34971.429
B65: 2.4 | C65: Crew cost - 2 crews from final survey through site demobilization | L65: 10971.429 | T65: 620489.14 | AA65: 620489.14
C67: Duration | D67: 320 | E67: days/7days/wk = | F67: 45.714286 | G67: 228.57143 | H67: working days | I67: See Project Schedule - Starts with Final Survey and ends with Site Demobilization
C70: Staff | F70: Number | G70: Rate | H70: Duration, days* | I70: Use Factor | J70: Cost | K70: Man-hours
C71: Decon Techs | F71: 6 | G71: 56.555 | H71: 228.57143 | I71: 1 | J71: 620489.14 | K71: 10971.429
F72: 6 | J72: 620489.14 | K72: 10971.429
B74: 2.5 | C74: Equipment & Materials | S74: 1690181.6 | AA74: 1690181.6
C76: Equipment | F76: Quantity | G76: Rate | H76: Cost
C77: HEPA filter systems | F77: 2 | G77: 3598.14 | H77: 7196.28
C78: Replacement filters | F78: 24 | G78: 581.07 | H78: 13945.68
C79: Respirator | F79: 30 | G79: 259 | H79: 7770
C80: Rad/Vac wet-dry high eff. vacuum | F80: 4 | G80: 3879 | H80: 15516
C81: Rad/Vac wet-dry high eff. vacuum filters | F81: 10 | G81: 412 | H81: 4120
C82: Reciprocating Saws | F82: 6 | G82: 1252.26 | H82: 7513.56
C83: Pneumatic chipping hammers | F83: 2 | G83: 1606.71 | H83: 3213.42
C84: Chipping hammer blades | F84: 20 | G84: 27.42 | H84: 548.4
C85: Purchase an air compressor: | F85: 4 | G85: 1723.44 | H85: 6893.76
C86: Jackhammer | F86: 2 | G86: 1417.11 | H86: 2834.22
C87: Jackhammer Chisels | F87: 20 | G87: 24.35 | H87: 487
C88: Safety glasses | F88: 150 | G88: 8.6 | H88: 1290
... C94: Phone and computer hook-up | F94: 1 | G94: 250 | H94: 6817.4351
C95: Industrial hygiene instrumentation, calibration and hygienists - 1% of total activity $. | H95: 63914.712
C96: Tractor loader, wheeled | F96: 1 | G96: 7160.5905 | H96: 175740.7
C97: Wheeled Skid steer with conc. Hammer | F97: 2 | G97: 4421.3693 | H97: 49099.425
C98: Excavator | F98: 2 | G98: 28738.389 | H98: 105750.73
C99: Floor Shaver | F99: 2 | G99: 8000 | H99: 88840.215
C100: Wall Shaver | F100: 2 | G100: 15000 | H100: 166575.4
C101: Core Drill & Bits | F101: 1 | G101: 10000 | H101: 10000
C102: Man lift | F102: 2 | G102: 4727.44 | H102: 151282.22
C103: Crane rental for building removal | F103: 1 | G103: 15600 | H103: 28702.223
H104: 950563.8
C106: Consumables | E106: Quantity | G106: Duration | I106: # workers | J106: quantity | K106: Unit Qty | L106: Unit Cost | M106: Cost
C107: Coveralls | E107: 2 | F107: /man/day | G107: 592.85714 | H107: days | I107: 16 | J107: 18971.429 | K107: 1 | L107: 8.7 | M107: 165051.43 | N107: 4 crews of 4 (3 decon techs and 1 HP tech per crew. HP techs with staff)
C108: Hoods | E108: 0.5 | F108: /man/day | G108: 592.85714 | H108: days | I108: 16 | J108: 4742.8571 | K108: 1 | L108: 0.93333333 | M108: 4426.6667 | N108: 4 crews of 4 (3 decon techs and 1 HP tech per crew. HP techs with staff)
C109: Shoe covers | E109: 4 | F109: /man/day | G109: 592.85714 | H109: days | I109: 16 | J109: 37942.857 | K109: 1 | L109: 0.37 | M109: 14038.857 | N109: 4 crews of 4 (3 decon techs and 1 HP tech per crew. HP techs with staff)
C110: Latex gloves | E110: 4 | F110: /man/day | G110: 592.85714 | H110: days | I110: 16 | J110: 37942.857 | K110: 1 | L110: 2 | M110: 75885.714 | N110: 4 crews of 4 (3 decon techs and 1 HP tech per crew. HP techs with staff)
C111: Rubber overshoes | E111: 0.01 | F111: /man/day | G111: 592.85714 | H111: days | I111: 16 | J111: 94.857143 | K111: 1 | L111: 3 | M111: 284.57143 | N111: 4 crews of 4 (3 decon techs and 1 HP tech per crew. HP techs with staff)
C112: Gloves | E112: 0.5 | F112: /man/day | G112: 592.85714 | H112: days | I112: 16 | J112: 4742.8571 | K112: 1 | L112: 1.63 | M112: 7730.8571 | N112: 4 crews of 4 (3 decon techs and 1 HP tech per crew. HP techs with staff)
C113: Dosimeters | E113: 1 | F113: /man/year | G113: 2.2802198 | H113: year | I113: 24 | J113: 54.725275 | K113: 1 | L113: 197.125 | M113: 10787.72
C114: TLDs | E114: 1 | F114: /man/mo | G114: 27.383702 | H114: month | I114: 24 | J114: 657.20884 | K114: 1 | L114: 3 | M114: 1971.6265
C115: Bioassays | E115: 2 | F115: /man/year | G115: 2.2802198 | H115: year | I115: 24 | J115: 109.45055 | K115: 1 | L115: 25 | M115: 2736.2637
C116: (Bioassays for aver. crew & management) | M116: 282913.71
C118: Small Tools - 2% of total labor costs = | G118: 2752298.3 | H118: labor costs x | I118: 0.02 | J118: = | K118: 55045.966
C120: HP Equipment Replacement - 5% of total labor | G120: 2752298.3 | H120: labor costs x | I120: 0.05 | J120: = | K120: 137614.91
C122: DGC OH &P on equipment and materials | G122: 3300540.1 | I122: 0.08 | J122: = | K122: 264043.21
A124: ACTIVITIES | I124: 9395.9104 | K124: 9663.3274 | L124: 6064 | M124: 8626.852 | N124: 69936 | O124: 60 | P124: 0 | Q124: 150531.93 | R124: 9.6 | S124: 1874401.7 | T124: 154000 | U124: 460070.02 | V124: 505924.36 | W124: 0 | X124: 0 | Y124: 795287.22 | Z124: 3489.6 | AA124: 3793172.9
B126: 2.6 | C126: Procedure Development and Review - Offsite | I126: 320 | J126: 1.1 | K126: 352 | L126: 616 | T126: 56320 | AA126: 56320
D128: Staff | G128: Number | H128: Rate | I128: Duration | J128: PLF | K128: Cost | L128: Man-hours
D129: Project Specialist | G129: 2 | H129: 85 | I129: 240 | J129: 1.1 | K129: 44880 | L129: 528
D130: Project Manager | G130: 1 | H130: 130 | I130: 80 | J130: 1.1 | K130: 11440 | L130: 88
G131: 3 | I131: 320 | K131: 56320 | L131: 616
B133: 2.7 | C133: Preparation of QA and Safety Documents - Offsite | I133: 320 | J133: 1.1 | K133: 352 | L133: 616 | T133: 56320 | AA133: 56320
D135: Staff | G135: Number | H135: Rate | I135: Duration | J135: PLF | L135: Cost | M135: Man-hours
D136: Project Specialist | G136: 2 | H136: 85 | I136: 240 | J136: 1.1 | L136: 44880 | M136: 528
D137: Project Manager | G137: 1 | H137: 130 | I137: 80 | J137: 1.1 | L137: 11440 | M137: 88
G138: 3 | I138: 320 | L138: 56320 | M138: 616
B140: 2.8 | C140: Site Mobilization and General Employee Training (GET) | I140: 88 | J140: 1 | K140: 88 | L140: 2472 | S140: 40800 | T140: 0 | AA140: 40800
...

Sheet Building 4 - 2012
A2: Shell floor area | C2: 153106 | P2: Mixed | Q2: Clean | R2: Lead | S2: Materials, | V2: Hazardous | X2: Mixed | Y2: Clean | Z2: Lead | AE2: Clean | AF2: Hazardous | AG2: LLW | AH2: Mixed
A3: Service Bldg Floor | C3: 27318 | I3: Uncorrected Duration | K3: Adjusted | M3: LSA Waste | N3: Hazardous | O3: Ballast | P3: Waste | Q3: Waste | R3: Waste | S3: Consumables, | U3: LSA Waste | V3: Waste | W3: >LSA Waste | X3: Waste | Y3: Waste | Z3: Waste | AC3: Removal | AE3: Waste | AF3: Waste | AG3: Waste | AH3: Waste
A4: 331A | C4: 8518 | H4: Crew | I4: (No. of Hours) | J4: Prod. Factor | K4: Duration | L4: Man-hours | M4: Disp. Vol (cf) | N4: Waste Vol (cf) | O4: Volume (cf) | P4: Volume (cf) | Q4: Volume (cf) | R4: Volume (cf) | S4: & Equipment | T4: Labor Cost | U4: Cost | V4: Cost | W4: Cost | X4: Cost | Y4: Cost | Z4: Cost | AA4: Total Cost | AC4: Unit Rate | AE4: Volume | AF4: Volume | AG4: Volume | AH4: Volume
B6: Grand Total Building 331 | AA6: 33523974
B8: Contingency = | D8: 0.4 | AA8: 9578278.3
A10: 1 | B10: Total Building 331 | AA10: 23945696
B12: Argonne Oversight @ 24% | Y12: 0.24 | AA12: 4634650.8
A14: Argonne Tax | B14: General and Administration @ 3.8% | Y14: 0.038 | AA14: 706955.4
A16: Argonne Tax | B16: IGPP/IGPE @ 3.4% | Y16: 0.034 | AA16: 611739.89
A18: Argonne Tax | B18: LDRD On total only | Y18: 0.083 | AA18: 1320393.5 | AB18: On total
A20: Argonne Tax | B20: Material and Subcontracts Tax @ 4.8% | Y20: 0.048 | AA20: 763601.05 | AB20: On total
A22: 1 | B22: Building 331 | L22: 96067.714 | M22: 7356.0124 | N22: 42.38 | O22: 7.5 | P22: 237.9 | Q22: 301673.98 | R22: 193.2 | S22: 5689285.7 | T22: 7340199.3 | U22: 1387242.7 | V22: 984.55968 | W22: 0 | X22: 4466.9279 | Y22: 1400268.9 | Z22: 85907.091 | AA22: 15908355
A24: UNDISTRIBUTED COSTS | L24: 89325.714 | S24: 4722397.7 | T24: 7154519.3 | U24: 0 | V24: 0 | W24: 0 | X24: 0 | Y24: 0 | AA24: 11876917
C26: Project duration = | F26: 933 | G26: days/7days/wk = | H26: 133.28571 | I26: See Project Schedule - Starts with Site Mobilization and ends with Site Demobilization
F27: 666.42857 | G27: working days
C29: Labor cost = | E29: 2026764.3 | F29: (Used to determine small tool costs and HP Supplies)
B31: 1.1 | C31: Project Management | L31: 53314.286 | T31: 4403760 | AA31: 4403760
C33: Staff | F33: Number | G33: Rate | H33: Duration, days* | I33: Use Factor | J33: Cost | K33: Man-hours
C34: Project Manager | F34: 1 | G34: 130 | H34: 666.42857 | I34: 1 | J34: 693085.71 | K34: 5331.4286
C35: Project Safety Manager | F35: 1 | G35: 100 | H35: 666.42857 | I35: 1 | J35: 533142.86 | K35: 5331.4286
C36: Project Specialist | F36: 1 | G36: 85 | H36: 666.42857 | I36: 1 | J36: 453171.43 | K36: 5331.4286
C37: Health Physicist | F37: 1 | G37: 120 | H37: 666.42857 | I37: 1 | J37: 639771.43 | K37: 5331.4286
C38: Site Supervisor | F38: 1 | G38: 100 | H38: 666.42857 | I38: 1 | J38: 533142.86 | K38: 5331.4286
C39: Chief HP Tech | F39: 1 | G39: 58 | H39: 666.42857 | I39: 1 | J39: 309222.86 | K39: 5331.4286
C40: Secretary | F40: 1 | G40: 33 | H40: 666.42857 | I40: 1 | J40: 175937.14 | K40: 5331.4286
C41: Project Control Specialist | F41: 1 | G41: 98 | H41: 666.42857 | I41: 1 | J41: 522480 | K41: 5331.4286
C42: HP Tech | F42: 2 | G42: 51 | H42: 666.42857 | I42: 1 | J42: 543805.71 | K42: 10662.857
F43: 10 | J43: 4403760 | K43: 53314.286
B45: 1.2 | C45: Project Management Per Diem | T45: 909675 | AA45: 909675
G46: Per Diem | H46: Number of
C47: Staff | F47: Number | G47: Rate, $/day | H47: Days | I47: Total
C48: Project Manager | F48: 1 | G48: 153 | H48: 933 | I48: 142749
C49: Project Safety Manager | F49: 1 | G49: 153 | H49: 933 | I49: 142749
C50: Project Specialist | F50: 1 | G50: 153 | H50: 933 | I50: 142749
C51: Health Physicist | F51: 1 | G51: 153 | H51: 933 | I51: 142749
C52: Site Supervisor | F52: 1 | G52: 153 | H52: 933 | I52: 142749
C53: Chief HP Tech | F53: 1 | G53: 70 | H53: 933 | I53: 65310
C54: HP Tech | F54: 2 | G54: 70 | H54: 933 | I54: 130620
F55: 8 | I55: 909675
B57: 1.3 | C57: Not Used | L57: 0 | T57: 0 | AA57: 0
C58: Asbestos Crew cost
C59: Duration | D59: 0 | E59: days/7days/wk = | F59: 0 | G59: 0 | H59: working days | I59: See Project Schedule
C62: Staff | F62: Number | G62: Rate | H62: Duration, days* | I62: Use Factor | J62: Cost | K62: Man-hours
C63: Decon Techs | F63: 12 | G63: 45 | H63: 0 | I63: 1 | J63: 0 | K63: 0
F64: 12 | J64: 0 | K64: 0
B66: 1.4 | C66: Crew cost - 2 crews from mobilization through final survey of structures | L66: 16091.429 | T66: 822674.29 | AA66: 822674.29
C68: Duration | D68: 352 | E68: days/7days/wk = | F68: 50.285714 | G68: 251.42857 | H68: working days | I68: See Project Schedule - Starts with Site Mobilization and ends with Remove Building
C71: Staff | F71: Number | G71: Rate | H71: Duration, days* | I71: Use Factor | J71: Cost | K71: Man-hours
C72: Decon Techs per diem | F72: 4 | G72: 70 | H72: 352 | I72: 1 | J72: 98560
C73: Decon Techs | F73: 8 | G73: 45 | H73: 251.42857 | I73: 1 | J73: 724114.29 | K73: 16091.429
F74: 8 | J74: 822674.29 | K74: 16091.429
B76: 1.5 | C76: Crew cost - 2 crews from building demo through site demobilization | L76: 19920 | T76: 1018410 | AA76: 1018410
C78: Duration | D78: 581 | E78: days/7days/wk = | F78: 83 | G78: 415 | H78: working days | I78: See Project Schedule - Starts with Remove Building and ends with Site Demobilization
C81: Staff | F81: Number | G81: Rate | H81: Duration, days* | I81: Use Factor | J81: Cost | K81: Man-hours
C82: Decon Techs per diem | F82: 3 | G82: 70 | H82: 581 | I82: 1 | J82: 122010
C83: Decon Techs | F83: 6 | G83: 45 | H83: 415 | I83: 1 | J83: 896400 | K83: 19920
F84: 6 | J84: 1018410 | K84: 19920
B86: 1.6 | C86: Equipment & Materials | S86: 4722397.7 | AA86: 4722397.7
C88: Equipment | F88: Quantity | G88: Rate | H88: Cost
C89: HEPA filter systems | F89: 2 | G89: 3922.22 | H89: 7844.44
C90: Replacement filters | F90: 24 | G90: 522.5 | H90: 12540
C91: Respirator | F91: 30 | G91: 214 | H91: 6420
C92: Rad/Vac wet-dry high eff. vacuum | F92: 4 | G92: 4080 | H92: 16320
C93: Rad/Vac wet-dry high eff. vacuum filters | F93: 10 | G93: 412 | H93: 4120
C94: Reciprocating Saws | F94: 6 | G94: 1198.62 | H94: 7191.72
C95: Pneumatic chipping hammers | F95: 2 | G95: 1217.82 | H95: 2435.64
C96: Chipping hammer blades | F96: 20 | G96: 35.3 | H96: 706
C97: Purchase an air compressor: | F97: 4 | G97: 1209.73 | H97: 4838.92
C98: Jackhammer | F98: 2 | G98: 1102.37 | H98: 2204.74
C99: Jackhammer Chisels | F99: 20 | G99: 27.42 | H99: 548.4
C100: Safety glasses | F100: 150 | G100: 9.9 | H100: 1485
... C106: Phone and computer hook-up | F106: 1 | G106: 250 | H106: 7663.4542
C107: Industrial hygiene instrumentation, calibration and hygienists - 1% of total activity $. | H107: 58725.224
C108: Front end loader, wheeled | F108: 2 | G108: 6175.7 | H108: 344935.6
C109: Hydraulic hammer for excavator | F109: 2 | G109: 9539.625 | H109: 443183.54
C110: Excavator | F110: 3 | G110: 24994.55 | H110: 1741762.4
C111: Grapple for excavator | F111: 1 | G111: 2275.325 | H111: 52852.528
C112: Scaffolding for shell | F112: 1 | G112: 3101.3654 | H112: 1528.4355
C113: Dump trucks excavation and backfill | F113: 8 | G113: 18638.25 | H113: 367417.04
C114: Rental cars | F114: 5 | G114: 800 | H114: 128529.19
C115: Water tank Trailer | F115: 1 | G115: 3557.95 | H115: 53889.441
C116: Dust Boss DB 60 | F116: 2 | G116: 850 | H116: 111577.05
C117: Dust Boss DB 60 transport | F117: 2 | G117: 3000 | H117: 6000
C118: Shot Blaster | F118: 2 | G118: 3278.3375 | H118: 40714.431
C119: Floor Shaver | F119: 2 | G119: 8487.2 | H119: 105404.5
... C123: Crane rental for building removal | F123: 2 | G123: 25477.125 | H123: 264508.97
H124: 4069923.1
C126: Consumables | E126: Quantity | G126: Duration | I126: # workers | J126: quantity | K126: Unit Qty | L126: Unit Cost | M126: Cost
C127: Coveralls | E127: 2 | F127: /man/day | G127: 251.42857 | H127: days | I127: 10 | J127: 5028.5714 | K127: 1 | L127: 11 | M127: 55314.286 | N127: 2 crews of 4 (3 decon techs and 1 HP tech per crew. HP techs with staff)
C128: Hoods with coveralls | E128: 0.5 | F128: /man/day | G128: 251.42857 | H128: days | I128: 10 | J128: 1257.1429 | K128: 1 | L128: 0 | M128: 0 | N128: 2 crews of 4 (3 decon techs and 1 HP tech per crew. HP techs with staff)
C129: Shoe covers | E129: 4 | F129: /man/day | G129: 251.42857 | H129: days | I129: 10 | J129: 10057.143 | K129: 1 | L129: 0.94 | M129: 9453.7143 | N129: 2 crews of 4 (3 decon techs and 1 HP tech per crew. HP techs with staff)
C130: Latex gloves | E130: 4 | F130: /man/day | G130: 251.42857 | H130: days | I130: 10 | J130: 10057.143 | K130: 1 | L130: 0.94 | M130: 9453.7143 | N130: 2 crews of 4 (3 decon techs and 1 HP tech per crew. HP techs with staff)
C131: Rubber overshoes | E131: 0.01 | F131: /man/day | G131: 251.42857 | H131: days | I131: 10 | J131: 25.142857 | K131: 1 | L131: 3 | M131: 75.428571 | N131: 2 crews of 4 (3 decon techs and 1 HP tech per crew. HP techs with staff)
C132: Gloves | E132: 0.5 | F132: /man/day | G132: 251.42857 | H132: days | I132: 10 | J132: 1257.1429 | K132: 1 | L132: 1.63 | M132: 2049.1429 | N132: 2 crews of 4 (3 decon techs and 1 HP tech per crew. HP techs with staff)
C133: Dosimeters | E133: 1 | F133: /man/year | G133: 0.96703297 | H133: year | I133: 18 | J133: 17.406593 | K133: 1 | L133: 200.83333 | M133: 3495.8242
C134: TLDs | E134: 1 | F134: /man/mo | G134: 11.613329 | H134: month | I134: 18 | J134: 209.03992 | K134: 1 | L134: 3 | M134: 627.11976
C135: Bioassays | E135: 2 | F135: /man/year | G135: 0.96703297 | H135: year | I135: 18 | J135: 34.813187 | K135: 1 | L135: 250 | M135: 8703.2967
C136: (Bioassays for aver. crew & management) | M136: 89172.526
C138: Small Tools - 2% of total labor costs = | G138: 2026764.3 | H138: labor costs x | I138: 0.02 | J138: = | K138: 40535.286
C140: HP Equipment Replacement - 5% of total labor | G140: 2026764.3 | H140: labor costs x | I140: 0.05 | J140: = | K140: 101338.21
...

Sheet PWR - 2015
I6: Contingency | J6: 0.15 | K6: 0.23838265 | L6: 0.25 | M6: 0.12205229 | N6: 0.21951141 | O6: 0.1 | P6: 0.37658885 | Q6: 0.15 | R6: 0.15
